Workbook

Sheet INVOICE
A3: TAX INVOICE
A4: BILL FROM | C4: Bill Date | D4: 45797
A5: 24 Seven Innovative products and services | C5: INVOICE No. | D5: MB1/S046/25-26
A6: Raaga Residency Plot No.782,Road No.44, | C6: GST Number | D6: 36AACFZ0539P1ZN
A7: Flat No-103 Ayyappa Society Madhapur | C7: LUT/Bond No | D7: AD3603250311498
A8: Hyderabad-500081 | C8: ESI CODE No | D8: 52000748150000900
A9: GST: 36AACFZ0539P1ZN | C9: PF CODE No | D9: APHYD2055855000
A10: BILL TO | C10: Work Order No. | D10: WO/DNIPL/B1&B2/2024-25/D326
A11: Divyasree NSL lnfrastructure Pvt Ltd, | C11: Work Order Date | D11: 25.03.2025
A12: Survey No.56/1, Serilingampalli (Mandal) | C12: Delivery Challan No's | D12: -
A13: Raidurgam, R.R.Dist, | C13: MSME Registration No | D13: TS02E0063727
A14: Hyderabad - 500032.
A15: GST: 36AACCD3662N1ZD
A16: DESCRIPTION | B16: SAC code | C16: Quantity | D16: Amount Rs.
A17: Man Power Supply for Apr-2025
A18: B1 Building
A19: Technical Executive | B19: 998519 | C19: ='INVOICE BREAKUP'!H6 -> 1 | D19: =VLOOKUP(A19,'INVOICE BREAKUP'!D$6:R$17,15,0) -> 40950.144
A20: Technical Supervisor | B20: 998519 | C20: ='INVOICE BREAKUP'!H7 -> 10 | D20: =VLOOKUP(A20,'INVOICE BREAKUP'!D$6:R$17,15,0) -> 233128.09
A21: HVAC Technician | B21: 998519 | C21: ='INVOICE BREAKUP'!H9 -> 7 | D21: =VLOOKUP(A21,'INVOICE BREAKUP'!D$6:R$17,15,0) -> 193454.77
A22: Plumber | B22: 998519 | C22: ='INVOICE BREAKUP'!H12 -> 8 | D22: =VLOOKUP(A22,'INVOICE BREAKUP'!D$6:R$17,15,0) -> 167309.22
A23: BMS Technician | B23: 998519 | C23: ='INVOICE BREAKUP'!H10 -> 4 | D23: =VLOOKUP(A23,'INVOICE BREAKUP'!D$6:R$17,15,0) -> 77822.307
A24: Electrician | B24: 998519 | C24: ='INVOICE BREAKUP'!H8 -> 8 | D24: =VLOOKUP(A24,'INVOICE BREAKUP'!D$6:R$17,15,0) -> 220516.79
A25: DG Operator | B25: 998519 | C25: ='INVOICE BREAKUP'!H11 -> 4 | D25: =VLOOKUP(A25,'INVOICE BREAKUP'!D$6:R$17,15,0) -> 106960.46
A26: Mason | B26: 998519 | C26: 1 | D26: =VLOOKUP(A26,'INVOICE BREAKUP'!D$6:R$17,15,0) -> 27139.896
A27: Painter | B27: 998519 | C27: 1 | D27: =VLOOKUP(A27,'INVOICE BREAKUP'!D$6:R$17,15,0) -> 27139.896
A28: Welder | B28: 998519 | C28: 1 | D28: =VLOOKUP(A28,'INVOICE BREAKUP'!D$6:R$17,15,0) -> 25950.015
A29: Carpenter | B29: 998519 | C29: 1 | D29: =VLOOKUP(A29,'INVOICE BREAKUP'!D$6:R$17,15,0) -> 23603.071
A30: Sub-Total | C30: =SUM(C19:C29) -> 46 | D30: =SUM(D19:D29) -> 1143974.7
A31: Management fee @8 % | D31: =D30*8% -> 91517.972
D32: =D30+D31 -> 1235492.6
A33: Tools & Tackles Rental Per Month | D33: ='INVOICE BREAKUP'!#REF! -> #REF!
A34: Uniform Charges Per Month | C34: =(PAYSHEET!F71+PAYSHEET!G71)/30 -> 43.833333 | D34: =C34*330 -> 14465
A35: Total Rs. | D35: =SUM(D32:D34) -> #REF!
B36: IGST @ | C36: 18% | D36: 0
A37: Total Amount Rs. | D37: =D35+D36 -> #REF! | F37: =D37-'INVOICE BREAKUP'!R22 -> #REF!
A39: DECLRACTION: SUPPLY TO SEZ UNIT FOR AUTHORISED OPERATIONS UNDER LUT WITHOUT PAYMENT OF INTEGRATED TAX.
A41: Bank Details : | B41: FOR 24 SEVEN INNOVATIVE PRODUCTS AND SERVICES
A42: M/S. 24 Seven Innovative Products And Services
A43: Bank name : ICICI Bank
A44: Bank account no :004005017980
A45: Bank IFSC Code : ICIC0000040 | B45: Authorized Signatory
A47: Thank you for your Business

Sheet ATTENDANCE
A1: 24SIPS O&M Attendance Report of July-26
A2: S.NO | B2: EMP.CODE | C2: NAME | D2: BIO METRIC CODE | E2: Designation | F2: Duty | G2: 1 | H2: 2 | I2: 3 | J2: 4 | K2: 5 | L2: 6 | M2: 7 | N2: 8 | O2: 9 | P2: 10 | Q2: 11 | R2: 12 | S2: 13 | T2: 14 | U2: 15 | V2: 16 | W2: 17 | X2: 18 | Y2: 19 | Z2: 20 | AA2: 21 | AB2: 22 | AC2: 23 | AD2: 24 | AE2: 25 | AF2: 26 | AG2: 27 | AH2: 28 | AI2: 29 | AJ2: 30 | AK2: 31 | AL2: A | AM2: B | AN2: C | AO2: G | AP2: W | AQ2: ED | AR2: PH | AS2: Total
G3: Wed | H3: Thu | I3: Fri | J3: Sat | K3: Sun | L3: Mon | M3: Tue | N3: Wed | O3: Thu | P3: Fri | Q3: Sat | R3: Sun | S3: Mon | T3: Tue | U3: Wed | V3: Thu | W3: Fri | X3: Sat | Y3: Sun | Z3: Mon | AA3: Tue | AB3: Wed | AC3: Thu | AD3: Fri | AE3: Sat | AF3: Sun | AG3: Mon | AH3: Tue | AI3: Wed | AJ3: Thu | AK3: Fri
A4: 1 | B4: 11029 | C4: SUDHIR KUMAR RAUTARAY | D4: 10602 | E4: TECH EXECUTIVE | F4: Duty | G4: G | H4: G | I4: G | J4: G | K4: G | L4: G | M4: W | N4: G | O4: G | P4: G | Q4: G | R4: G | S4: G | T4: W | U4: G | V4: G | W4: G | X4: G | Y4: G | Z4: G | AA4: W | AB4: G | AC4: G | AD4: G | AE4: G | AF4: G | AG4: G | AH4: W | AI4: G | AJ4: G | AK4: G | AL4: =SUM(COUNTIFS(G4:AK4,"A")) -> 0 | AM4: =SUM(COUNTIFS(G4:AK4,"B")) -> 0 | AN4: =SUM(COUNTIFS(G4:AK4,"C")) -> 0 | AO4: =SUM(COUNTIFS(G4:AK4,"G")) -> 27 | AP4: =SUM(COUNTIFS(G4:AK4,"W")) -> 4 | AQ4: =SUM(COUNTIFS(G5:AK5,"A"))+(COUNTIFS(G5:AK5,"B"))+(COUNTIFS(G5:AK5,"C"))+(COUNTIFS(G5:AK5,"G")) -> 0 | AR4: =SUM(COUNTIFS(G4:AK4,"PH")) -> 0 | AS4: =AL4+AM4+AN4+AO4+AR4+AP4+AQ4 -> 31
F5: E.D
A6: 2 | B6: 10976 | C6: KONGANI NARAYANA | D6: 10431 | E6: TECH SUPERVISOR | F6: Duty | G6: A | H6: A | I6: B | J6: B | K6: C | L6: C | M6: W | N6: A | O6: A | P6: B | Q6: B | R6: C | S6: C | T6: W | U6: A | V6: B | W6: B | X6: A | Y6: C | Z6: C | AA6: W | AB6: A | AC6: A | AD6: C | AE6: B | AF6: C | AG6: B | AH6: W | AI6: A | AJ6: A | AK6: B | AL6: =SUM(COUNTIFS(G6:AK6,"A")) -> 10 | AM6: =SUM(COUNTIFS(G6:AK6,"B")) -> 9 | AN6: =SUM(COUNTIFS(G6:AK6,"C")) -> 8 | AO6: =SUM(COUNTIFS(G6:AK6,"G")) -> 0 | AP6: =SUM(COUNTIFS(G6:AK6,"W")) -> 4 | AQ6: =SUM(COUNTIFS(G7:AK7,"A"))+(COUNTIFS(G7:AK7,"B"))+(COUNTIFS(G7:AK7,"C"))+(COUNTIFS(G7:AK7,"G")) -> 0 | AR6: =SUM(COUNTIFS(G6:AK6,"PH")) -> 0 | AS6: =AL6+AM6+AN6+AO6+AR6+AP6+AQ6 -> 31
F7: E.D
A8: 3 | B8: 10984 | C8: KUMMARA RAJYALAKSHMI | D8: 1227 | E8: TECH SUPERVISOR | F8: Duty | G8: G | H8: G | I8: G | J8: G | K8: W | L8: G | M8: G | N8: G | O8: G | P8: G | Q8: G | R8: W | S8: G | T8: G | U8: G | V8: G | W8: G | X8: G | Y8: W | Z8: G | AA8: G | AB8: G | AC8: G | AD8: G | AE8: G | AF8: W | AG8: G | AH8: G | AI8: G | AJ8: G | AK8: L | AL8: =SUM(COUNTIFS(G8:AK8,"A")) -> 0 | AM8: =SUM(COUNTIFS(G8:AK8,"B")) -> 0 | AN8: =SUM(COUNTIFS(G8:AK8,"C")) -> 0 | AO8: =SUM(COUNTIFS(G8:AK8,"G")) -> 26 | AP8: =SUM(COUNTIFS(G8:AK8,"W")) -> 4 | AQ8: =SUM(COUNTIFS(G9:AK9,"A"))+(COUNTIFS(G9:AK9,"B"))+(COUNTIFS(G9:AK9,"C"))+(COUNTIFS(G9:AK9,"G")) -> 0 | AR8: =SUM(COUNTIFS(G8:AK8,"PH")) -> 0 | AS8: =AL8+AM8+AN8+AO8+AR8+AP8+AQ8 -> 30
F9: E.D
A10: 4 | B10: 10986 | C10: KSHIROD KUMAR DAS | D10: 11038 | E10: TECH SUPERVISOR | F10: Duty | G10: G | H10: W | I10: G | J10: G | K10: G | L10: G | M10: L | N10: L | O10: L | P10: L | Q10: L | R10: L | S10: L | T10: L | U10: L | V10: L | W10: L | X10: L | Y10: L | Z10: L | AA10: L | AB10: L | AC10: G | AD10: G | AE10: G | AF10: G | AG10: G | AH10: G | AI10: G | AJ10: W | AK10: G | AL10: =SUM(COUNTIFS(G10:AK10,"A")) -> 0 | AM10: =SUM(COUNTIFS(G10:AK10,"B")) -> 0 | AN10: =SUM(COUNTIFS(G10:AK10,"C")) -> 0 | AO10: =SUM(COUNTIFS(G10:AK10,"G")) -> 13 | AP10: =SUM(COUNTIFS(G10:AK10,"W")) -> 2 | AQ10: =SUM(COUNTIFS(G11:AK11,"A"))+(COUNTIFS(G11:AK11,"B"))+(COUNTIFS(G11:AK11,"C"))+(COUNTIFS(G11:AK11,"G")) -> 0 | AR10: =SUM(COUNTIFS(G10:AK10,"PH")) -> 0 | AS10: =AL10+AM10+AN10+AO10+AR10+AP10+AQ10 -> 15
F11: E.D
A12: 5 | B12: 10013 | C12: HRUSIKESH PANDA | D12: 11182 | E12: TECH SUPERVISOR | F12: Duty | G12: W | H12: G | I12: A | J12: G | K12: B | L12: G | M12: A | N12: W | O12: G | P12: A | Q12: G | R12: B | S12: G | T12: A | U12: W | V12: A | W12: A | X12: G | Y12: A | Z12: G | AA12: A | AB12: W | AC12: B | AD12: B | AE12: B | AF12: A | AG12: A | AH12: A | AI12: W | AJ12: G | AK12: G | AL12: =SUM(COUNTIFS(G12:AK12,"A")) -> 11 | AM12: =SUM(COUNTIFS(G12:AK12,"B")) -> 5 | AN12: =SUM(COUNTIFS(G12:AK12,"C")) -> 0 | AO12: =SUM(COUNTIFS(G12:AK12,"G")) -> 10 | AP12: =SUM(COUNTIFS(G12:AK12,"W")) -> 5 | AQ12: =SUM(COUNTIFS(G13:AK13,"A"))+(COUNTIFS(G13:AK13,"B"))+(COUNTIFS(G13:AK13,"C"))+(COUNTIFS(G13:AK13,"G")) -> 0 | AR12: =SUM(COUNTIFS(G12:AK12,"PH")) -> 0 | AS12: =AL12+AM12+AN12+AO12+AR12+AP12+AQ12 -> 31
F13: E.D
A14: 6 | B14: 11365 | C14: BADAM SANDEEP | D14: 11203 | E14: TECH SUPERVISOR | F14: Duty | G14: C | H14: C | I14: W | J14: A | K14: A | L14: B | M14: C | N14: C | O14: C | P14: W | Q14: A | R14: A | S14: A | T14: C | U14: B | V14: A | W14: W | X14: C | Y14: B | Z14: B | AA14: C | AB14: C | AC14: B | AD14: W | AE14: C | AF14: B | AG14: B | AH14: C | AI14: C | AJ14: L | AK14: W | AL14: =SUM(COUNTIFS(G14:AK14,"A")) -> 6 | AM14: =SUM(COUNTIFS(G14:AK14,"B")) -> 7 | AN14: =SUM(COUNTIFS(G14:AK14,"C")) -> 12 | AO14: =SUM(COUNTIFS(G14:AK14,"G")) -> 0 | AP14: =SUM(COUNTIFS(G14:AK14,"W")) -> 5 | AQ14: =SUM(COUNTIFS(G15:AK15,"A"))+(COUNTIFS(G15:AK15,"B"))+(COUNTIFS(G15:AK15,"C"))+(COUNTIFS(G15:AK15,"G")) -> 0 | AR14: =SUM(COUNTIFS(G14:AK14,"PH")) -> 0 | AS14: =AL14+AM14+AN14+AO14+AR14+AP14+AQ14 -> 30
F15: E.D
A16: 7 | B16: 10989 | C16: B NAGENDRA BABU | D16: 10423 | E16: TECH SUPERVISOR | F16: Duty | G16: B | H16: B | I16: C | J16: C | K16: W | L16: A | M16: B | N16: B | O16: B | P16: C | Q16: C | R16: W | S16: B | T16: B | U16: C | V16: C | W16: C | X16: B | Y16: W | Z16: A | AA16: B | AB16: B | AC16: C | AD16: B | AE16: A | AF16: W | AG16: C | AH16: B | AI16: B | AJ16: B | AK16: C | AL16: =SUM(COUNTIFS(G16:AK16,"A")) -> 3 | AM16: =SUM(COUNTIFS(G16:AK16,"B")) -> 14 | AN16: =SUM(COUNTIFS(G16:AK16,"C")) -> 10 | AO16: =SUM(COUNTIFS(G16:AK16,"G")) -> 0 | AP16: =SUM(COUNTIFS(G16:AK16,"W")) -> 4 | AQ16: =SUM(COUNTIFS(G17:AK17,"A"))+(COUNTIFS(G17:AK17,"B"))+(COUNTIFS(G17:AK17,"C"))+(COUNTIFS(G17:AK17,"G")) -> 0 | AR16: =SUM(COUNTIFS(G16:AK16,"PH")) -> 0 | AS16: =AL16+AM16+AN16+AO16+AR16+AP16+AQ16 -> 31
F17: E.D
A18: 8 | B18: 10982 | C18: SAGAR KUMAR BEHERA | D18: 11101 | E18: TECH SUPERVISOR | F18: Duty | G18: A | H18: G | I18: G | J18: G | K18: G | L18: W | M18: G | N18: G | O18: G | P18: G | Q18: G | R18: G | S18: W | T18: G | U18: G | V18: G | W18: G | X18: G | Y18: G | Z18: W | AA18: G | AB18: G | AC18: G | AD18: A | AE18: G | AF18: B | AG18: W | AH18: A | AI18: A | AJ18: G | AK18: A | AL18: =SUM(COUNTIFS(G18:AK18,"A")) -> 5 | AM18: =SUM(COUNTIFS(G18:AK18,"B")) -> 1 | AN18: =SUM(COUNTIFS(G18:AK18,"C")) -> 0 | AO18: =SUM(COUNTIFS(G18:AK18,"G")) -> 21 | AP18: =SUM(COUNTIFS(G18:AK18,"W")) -> 4 | AQ18: =SUM(COUNTIFS(G19:AK19,"A"))+(COUNTIFS(G19:AK19,"B"))+(COUNTIFS(G19:AK19,"C"))+(COUNTIFS(G19:AK19,"G")) -> 0 | AR18: =SUM(COUNTIFS(G18:AK18,"PH")) -> 0 | AS18: =AL18+AM18+AN18+AO18+AR18+AP18+AQ18 -> 31
F19: E.D
A20: 9 | B20: 12076 | C20: JALEM ROHAN | D20: 11227 | E20: TECH SUPERVISOR | F20: Duty | G20: C | H20: C | I20: C | J20: W | K20: G | L20: B | M20: G | N20: G | O20: B | P20: G | Q20: W | R20: C | S20: C | T20: C | U20: C | V20: C | W20: B | X20: W | Y20: G | Z20: G | AA20: G | AB20: G | AC20: C | AD20: C | AE20: W | AF20: C | AG20: C | AH20: B | AI20: B | AJ20: B | AK20: C | AL20: =SUM(COUNTIFS(G20:AK20,"A")) -> 0 | AM20: =SUM(COUNTIFS(G20:AK20,"B")) -> 6 | AN20: =SUM(COUNTIFS(G20:AK20,"C")) -> 13 | AO20: =SUM(COUNTIFS(G20:AK20,"G")) -> 8 | AP20: =SUM(COUNTIFS(G20:AK20,"W")) -> 4 | AQ20: =SUM(COUNTIFS(G21:AK21,"A"))+(COUNTIFS(G21:AK21,"B"))+(COUNTIFS(G21:AK21,"C"))+(COUNTIFS(G21:AK21,"G")) -> 0 | AR20: =SUM(COUNTIFS(G20:AK20,"PH")) -> 0 | AS20: =AL20+AM20+AN20+AO20+AR20+AP20+AQ20 -> 31
F21: E.D
A22: 10 | B22: 11032 | C22: ANANDA SHA | D22: 11104 | E22: ELECTRICIAN | F22: Duty | G22: W | H22: C | I22: C | J22: B | K22: B | L22: A | M22: B | N22: W | O22: A | P22: A | Q22: G | R22: B | S22: B | T22: C | U22: W | V22: A | W22: A | X22: G | Y22: G | Z22: B | AA22: C | AB22: W | AC22: B | AD22: B | AE22: G | AF22: B | AG22: B | AH22: C | AI22: W | AJ22: B | AK22: B | AL22: =SUM(COUNTIFS(G22:AK22,"A")) -> 5 | AM22: =SUM(COUNTIFS(G22:AK22,"B")) -> 12 | AN22: =SUM(COUNTIFS(G22:AK22,"C")) -> 5 | AO22: =SUM(COUNTIFS(G22:AK22,"G")) -> 4 | AP22: =SUM(COUNTIFS(G22:AK22,"W")) -> 5 | AQ22: =SUM(COUNTIFS(G23:AK23,"A"))+(COUNTIFS(G23:AK23,"B"))+(COUNTIFS(G23:AK23,"C"))+(COUNTIFS(G23:AK23,"G")) -> 0 | AR22: =SUM(COUNTIFS(G22:AK22,"PH")) -> 0 | AS22: =AL22+AM22+AN22+AO22+AR22+AP22+AQ22 -> 31
F23: E.D
A24: 11 | B24: 10981 | C24: CHINTHAKUNTA GANESH | D24: 11053 | E24: ELECTRICIAN | F24: Duty | G24: C | H24: B | I24: L | J24: L | K24: W | L24: C | M24: C | N24: B | O24: G | P24: G | Q24: C | R24: W | S24: G | T24: A | U24: G | V24: G | W24: C | X24: C | Y24: W | Z24: A | AA24: G | AB24: G | AC24: G | AD24: C | AE24: C | AF24: W | AG24: A | AH24: B | AI24: G | AJ24: G | AK24: C | AL24: =SUM(COUNTIFS(G24:AK24,"A")) -> 3 | AM24: =SUM(COUNTIFS(G24:AK24,"B")) -> 3 | AN24: =SUM(COUNTIFS(G24:AK24,"C")) -> 9 | AO24: =SUM(COUNTIFS(G24:AK24,"G")) -> 10 | AP24: =SUM(COUNTIFS(G24:AK24,"W")) -> 4 | AQ24: =SUM(COUNTIFS(G25:AK25,"A"))+(COUNTIFS(G25:AK25,"B"))+(COUNTIFS(G25:AK25,"C"))+(COUNTIFS(G25:AK25,"G")) -> 0 | AR24: =SUM(COUNTIFS(G24:AK24,"PH")) -> 0 | AS24: =AL24+AM24+AN24+AO24+AR24+AP24+AQ24 -> 29
F25: E.D
A26: 12 | B26: 11651 | C26: RUDRA MADHAB SENAPATI | D26: 11194 | E26: ELECTRICIAN | F26: Duty | G26: L | H26: L | I26: L | J26: L | K26: L | L26: L | M26: L | N26: L | O26: L | P26: L | Q26: L | R26: L | S26: L | T26: L | U26: L | V26: L | W26: L | X26: L | Y26: L | Z26: L | AA26: L | AB26: L | AC26: L | AD26: L | AE26: L | AF26: L | AG26: L | AH26: L | AI26: L | AJ26: L | AK26: L | AL26: =SUM(COUNTIFS(G26:AK26,"A")) -> 0 | AM26: =SUM(COUNTIFS(G26:AK26,"B")) -> 0 | AN26: =SUM(COUNTIFS(G26:AK26,"C")) -> 0 | AO26: =SUM(COUNTIFS(G26:AK26,"G")) -> 0 | AP26: =SUM(COUNTIFS(G26:AK26,"W")) -> 0 | AQ26: =SUM(COUNTIFS(G27:AK27,"A"))+(COUNTIFS(G27:AK27,"B"))+(COUNTIFS(G27:AK27,"C"))+(COUNTIFS(G27:AK27,"G")) -> 0 | AR26: =SUM(COUNTIFS(G26:AK26,"PH")) -> 0 | AS26: =AL26+AM26+AN26+AO26+AR26+AP26+AQ26 -> 0
F27: E.D
A28: 13 | B28: 11377 | C28: MANOJ KUMAR DAS | D28: 11196 | E28: ELECTRICIAN | F28: Duty | G28: B | H28: A | I28: B | J28: C | K28: C | L28: B | M28: W | N28: A | O28: B | P28: B | Q28: B | R28: C | S28: C | T28: W | U28: B | V28: B | W28: B | X28: B | Y28: C | Z28: L | AA28: W | AB28: B | AC28: A | AD28: B | AE28: B | AF28: C | AG28: L | AH28: L | AI28: L | AJ28: L | AK28: L | AL28: =SUM(COUNTIFS(G28:AK28,"A")) -> 3 | AM28: =SUM(COUNTIFS(G28:AK28,"B")) -> 13 | AN28: =SUM(COUNTIFS(G28:AK28,"C")) -> 6 | AO28: =SUM(COUNTIFS(G28:AK28,"G")) -> 0 | AP28: =SUM(COUNTIFS(G28:AK28,"W")) -> 3 | AQ28: =SUM(COUNTIFS(G29:AK29,"A"))+(COUNTIFS(G29:AK29,"B"))+(COUNTIFS(G29:AK29,"C"))+(COUNTIFS(G29:AK29,"G")) -> 0 | AR28: =SUM(COUNTIFS(G28:AK28,"PH")) -> 0 | AS28: =AL28+AM28+AN28+AO28+AR28+AP28+AQ28 -> 25
F29: E.D
A30: 14 | B30: 1 | C30: BANAVATH BALAJI | D30: 11229 | E30: ELECTRICIAN | F30: Duty | G30: NEW JOINING | H30: G | I30: G | J30: G | K30: B | L30: A | M30: B | N30: G | O30: W | P30: C | Q30: B | R30: C | S30: C | T30: B | U30: C | V30: W | W30: L | X30: L | Y30: C | Z30: C | AA30: B | AB30: A | AC30: W | AD30: A | AE30: A | AF30: B | AG30: B | AH30: B | AI30: C | AJ30: W | AK30: G | AL30: =SUM(COUNTIFS(G30:AK30,"A")) -> 4 | AM30: =SUM(COUNTIFS(G30:AK30,"B")) -> 8 | AN30: =SUM(COUNTIFS(G30:AK30,"C")) -> 7 | AO30: =SUM(COUNTIFS(G30:AK30,"G")) -> 5 | AP30: =SUM(COUNTIFS(G30:AK30,"W")) -> 4 | AQ30: =SUM(COUNTIFS(G31:AK31,"A"))+(COUNTIFS(G31:AK31,"B"))+(COUNTIFS(G31:AK31,"C"))+(COUNTIFS(G31:AK31,"G")) -> 0 | AR30: =SUM(COUNTIFS(G30:AK30,"PH")) -> 0 | AS30: =AL30+AM30+AN30+AO30+AR30+AP30+AQ30 -> 28
F31: E.D
A32: 15 | B32: 2 | C32: GATTU BHANUTEJA | D32: 11230 | E32: ELECTRICIAN | F32: Duty | G32: NEW JOINING | H32: G | I32: G | J32: G | K32: C | L32: C | M32: C | N32: B | O32: W | P32: L | Q32: C | R32: B | S32: A | T32: A | U32: L | V32: W | W32: C | X32: L | Y32: A | Z32: A | AA32: A | AB32: A | AC32: C | AD32: C | AE32: A | AF32: A | AG32: A | AH32: A | AI32: B | AJ32: W | AK32: C | AL32: =SUM(COUNTIFS(G32:AK32,"A")) -> 10 | AM32: =SUM(COUNTIFS(G32:AK32,"B")) -> 3 | AN32: =SUM(COUNTIFS(G32:AK32,"C")) -> 8 | AO32: =SUM(COUNTIFS(G32:AK32,"G")) -> 3 | AP32: =SUM(COUNTIFS(G32:AK32,"W")) -> 3 | AQ32: =SUM(COUNTIFS(G33:AK33,"A"))+(COUNTIFS(G33:AK33,"B"))+(COUNTIFS(G33:AK33,"C"))+(COUNTIFS(G33:AK33,"G")) -> 0 | AR32: =SUM(COUNTIFS(G32:AK32,"PH")) -> 0 | AS32: =AL32+AM32+AN32+AO32+AR32+AP32+AQ32 -> 27
F33: E.D
A34: 16 | B34: 3 | C34: MERUPULA SANDEEP GOUD | D34: 11231 | E34: ELECTRICIAN | F34: Duty | G34: NEW JOINING | H34: G | I34: G | J34: A | K34: A | L34: B | M34: A | N34: C | O34: C | P34: B | Q34: A | R34: A | S34: A | T34: W | U34: A | V34: B | W34: B | X34: A | Y34: L | Z34: B | AA34: W | AB34: B | AC34: B | AD34: A | AE34: C | AF34: C | AG34: C | AH34: W | AI34: A | AJ34: A | AK34: A | AL34: =SUM(COUNTIFS(G34:AK34,"A")) -> 12 | AM34: =SUM(COUNTIFS(G34:AK34,"B")) -> 7 | AN34: =SUM(COUNTIFS(G34:AK34,"C")) -> 5 | AO34: =SUM(COUNTIFS(G34:AK34,"G")) -> 2 | AP34: =SUM(COUNTIFS(G34:AK34,"W")) -> 3 | AQ34: =SUM(COUNTIFS(G35:AK35,"A"))+(COUNTIFS(G35:AK35,"B"))+(COUNTIFS(G35:AK35,"C"))+(COUNTIFS(G35:AK35,"G")) -> 0 | AR34: =SUM(COUNTIFS(G34:AK34,"PH")) -> 0 | AS34: =AL34+AM34+AN34+AO34+AR34+AP34+AQ34 -> 29
F35: E.D
A36: 17 | B36: 4 | C36: RAJANIKANT | D36: 11232 | E36: ELECTRICIAN | F36: Duty | G36: NEW JOINING | J36: G | K36: G | L36: C | M36: B | N36: G | O36: W | P36: A | Q36: A | R36: B | S36: B | T36: L | U36: L | V36: L | W36: L | X36: L | Y36: L | Z36: L | AA36: L | AB36: L | AC36: L | AD36: L | AE36: L | AF36: L | AG36: L | AH36: L | AI36: L | AJ36: L | AK36: L | AL36: =SUM(COUNTIFS(G36:AK36,"A")) -> 2 | AM36: =SUM(COUNTIFS(G36:AK36,"B")) -> 3 | AN36: =SUM(COUNTIFS(G36:AK36,"C")) -> 1 | AO36: =SUM(COUNTIFS(G36:AK36,"G")) -> 3 | AP36: =SUM(COUNTIFS(G36:AK36,"W")) -> 1 | AQ36: =SUM(COUNTIFS(G37:AK37,"A"))+(COUNTIFS(G37:AK37,"B"))+(COUNTIFS(G37:AK37,"C"))+(COUNTIFS(G37:AK37,"G")) -> 0 | AR36: =SUM(COUNTIFS(G36:AK36,"PH")) -> 0 | AS36: =AL36+AM36+AN36+AO36+AR36+AP36+AQ36 -> 10
F37: E.D
A38: 18 | B38: 5 | C38: ALOKA MUDULI | D38: 11233 | E38: ELECTRICIAN | F38: Duty | G38: NEW JOINING | J38: G | K38: G | L38: G | M38: G | N38: C | O38: B | P38: A | Q38: G | R38: G | S38: B | T38: C | U38: C | V38: W | W38: G | X38: G | Y38: G | Z38: G | AA38: B | AB38: C | AC38: W | AD38: B | AE38: B | AF38: A | AG38: A | AH38: C | AI38: B | AJ38: W | AK38: B | AL38: =SUM(COUNTIFS(G38:AK38,"A")) -> 3 | AM38: =SUM(COUNTIFS(G38:AK38,"B")) -> 7 | AN38: =SUM(COUNTIFS(G38:AK38,"C")) -> 5 | AO38: =SUM(COUNTIFS(G38:AK38,"G")) -> 10 | AP38: =SUM(COUNTIFS(G38:AK38,"W")) -> 3 | AQ38: =SUM(COUNTIFS(G39:AK39,"A"))+(COUNTIFS(G39:AK39,"B"))+(COUNTIFS(G39:AK39,"C"))+(COUNTIFS(G39:AK39,"G")) -> 0 | AR38: =SUM(COUNTIFS(G38:AK38,"PH")) -> 0 | AS38: =AL38+AM38+AN38+AO38+AR38+AP38+AQ38 -> 28
F39: E.D
A40: 19 | B40: 6 | C40: MD Saleem | D40: 11237 | E40: ELECTRICIAN | F40: Duty | G40: NEW JOINING | M40: G | N40: G | O40: G | P40: G | Q40: A | R40: G | S40: G | T40: G | U40: A | V40: C | W40: W | X40: B | Y40: B | Z40: L | AA40: L | AB40: C | AC40: C | AD40: W | AE40: A | AF40: G | AG40: G | AH40: A | AI40: C | AJ40: C | AK40: W | AL40: =SUM(COUNTIFS(G40:AK40,"A")) -> 4 | AM40: =SUM(COUNTIFS(G40:AK40,"B")) -> 2 | AN40: =SUM(COUNTIFS(G40:AK40,"C")) -> 5 | AO40: =SUM(COUNTIFS(G40:AK40,"G")) -> 9 | AP40: =SUM(COUNTIFS(G40:AK40,"W")) -> 3 | AQ40: =SUM(COUNTIFS(G41:AK41,"A"))+(COUNTIFS(G41:AK41,"B"))+(COUNTIFS(G41:AK41,"C"))+(COUNTIFS(G41:AK41,"G")) -> 0 | AR40: =SUM(COUNTIFS(G40:AK40,"PH")) -> 0 | AS40: =AL40+AM40+AN40+AO40+AR40+AP40+AQ40 -> 23
F41: E.D
A42: 20 | B42: 7 | C42: Shaik Shaheed | D42: 11238 | E42: ELECTRICIAN | F42: Duty | G42: NEW JOINING | M42: G | N42: G | O42: G | P42: G | Q42: G | R42: G | S42: L | T42: W | U42: G | V42: G | W42: G | X42: G | Y42: G | Z42: C | AA42: W | AB42: G | AC42: G | AD42: G | AE42: A | AF42: C | AG42: C | AH42: W | AI42: G | AJ42: G | AK42: B | AL42: =SUM(COUNTIFS(G42:AK42,"A")) -> 1 | AM42: =SUM(COUNTIFS(G42:AK42,"B")) -> 1 | AN42: =SUM(COUNTIFS(G42:AK42,"C")) -> 3 | AO42: =SUM(COUNTIFS(G42:AK42,"G")) -> 16 | AP42: =SUM(COUNTIFS(G42:AK42,"W")) -> 3 | AQ42: =SUM(COUNTIFS(G43:AK43,"A"))+(COUNTIFS(G43:AK43,"B"))+(COUNTIFS(G43:AK43,"C"))+(COUNTIFS(G43:AK43,"G")) -> 0 | AR42: =SUM(COUNTIFS(G42:AK42,"PH")) -> 0 | AS42: =AL42+AM42+AN42+AO42+AR42+AP42+AQ42 -> 24
F43: E.D
A44: 21 | B44: 11958 | C44: MANGA PRATAP KUMAR | D44: 11224 | E44: ELECTRICIAN | F44: Duty | G44: L | H44: L | I44: L | J44: L | K44: L | L44: L | M44: L | N44: L | O44: C | P44: C | Q44: B | R44: A | S44: W | T44: B | U44: L | V44: L | W44: L | X44: L | Y44: L | Z44: L | AA44: L | AB44: L | AC44: L | AD44: L | AE44: L | AF44: L | AG44: L | AH44: L | AI44: L | AJ44: L | AK44: L | AL44: =SUM(COUNTIFS(G44:AK44,"A")) -> 1 | AM44: =SUM(COUNTIFS(G44:AK44,"B")) -> 2 | AN44: =SUM(COUNTIFS(G44:AK44,"C")) -> 2 | AO44: =SUM(COUNTIFS(G44:AK44,"G")) -> 0 | AP44: =SUM(COUNTIFS(G44:AK44,"W")) -> 1 | AQ44: =SUM(COUNTIFS(G45:AK45,"A"))+(COUNTIFS(G45:AK45,"B"))+(COUNTIFS(G45:AK45,"C"))+(COUNTIFS(G45:AK45,"G")) -> 0 | AR44: =SUM(COUNTIFS(G44:AK44,"PH")) -> 0 | AS44: =AL44+AM44+AN44+AO44+AR44+AP44+AQ44 -> 6
F45: E.D
A46: 22 | B46: 8 | C46: KAZIPETA RAVI KIRAN | D46: 11239 | E46: ELECTRICIAN | F46: Duty | G46: NEW JOINING | AA46: G | AB46: G | AC46: G | AD46: G | AE46: G | AF46: L | AG46: G | AH46: G | AI46: G | AJ46: G | AK46: G | AL46: =SUM(COUNTIFS(G46:AK46,"A")) -> 0 | AM46: =SUM(COUNTIFS(G46:AK46,"B")) -> 0 | AN46: =SUM(COUNTIFS(G46:AK46,"C")) -> 0 | AO46: =SUM(COUNTIFS(G46:AK46,"G")) -> 10 | AP46: =SUM(COUNTIFS(G46:AK46,"W")) -> 0 | AQ46: =SUM(COUNTIFS(G47:AK47,"A"))+(COUNTIFS(G47:AK47,"B"))+(COUNTIFS(G47:AK47,"C"))+(COUNTIFS(G47:AK47,"G")) -> 0 | AR46: =SUM(COUNTIFS(G46:AK46,"PH")) -> 0 | AS46: =AL46+AM46+AN46+AO46+AR46+AP46+AQ46 -> 10
F47: E.D
A48: 23 | B48: 10991 | C48: JOGENDRA SETHI | D48: 10338 | E48: HVAC OPERATOR | F48: Duty | G48: W | H48: A | I48: A | J48: G | K48: A | L48: C | M48: C | N48: W | O48: A | P48: A | Q48: G | R48: B | S48: C | T48: C | U48: W | V48: A | W48: A | X48: G | Y48: B | Z48: C | AA48: C | AB48: W | AC48: A | AD48: A | AE48: G | AF48: B | AG48: C | AH48: C | AI48: W | AJ48: A | AK48: A | AL48: =SUM(COUNTIFS(G48:AK48,"A")) -> 11 | AM48: =SUM(COUNTIFS(G48:AK48,"B")) -> 3 | AN48: =SUM(COUNTIFS(G48:AK48,"C")) -> 8 | AO48: =SUM(COUNTIFS(G48:AK48,"G")) -> 4 | AP48: =SUM(COUNTIFS(G48:AK48,"W")) -> 5 | AQ48: =SUM(COUNTIFS(G49:AK49,"A"))+(COUNTIFS(G49:AK49,"B"))+(COUNTIFS(G49:AK49,"C"))+(COUNTIFS(G49:AK49,"G")) -> 0 | AR48: =SUM(COUNTIFS(G48:AK48,"PH")) -> 0 | AS48: =AL48+AM48+AN48+AO48+AR48+AP48+AQ48 -> 31
F49: E.D
A50: 24 | B50: 11476 | C50: HARISH KHAN | D50: 11166 | E50: HVAC OPERATOR | F50: Duty | G50: L | H50: L | I50: L | J50: L | K50: L | L50: L | M50: L | N50: L | O50: B | P50: C | Q50: B | R50: W | S50: A | T50: A | U50: B | V50: B | W50: B | X50: B | Y50: W | Z50: A | AA50: A | AB50: B | AC50: B | AD50: C | AE50: B | AF50: W | AG50: A | AH50: B | AI50: B | AJ50: B | AK50: C | AL50: =SUM(COUNTIFS(G50:AK50,"A")) -> 5 | AM50: =SUM(COUNTIFS(G50:AK50,"B")) -> 12 | AN50: =SUM(COUNTIFS(G50:AK50,"C")) -> 3 | AO50: =SUM(COUNTIFS(G50:AK50,"G")) -> 0 | AP50: =SUM(COUNTIFS(G50:AK50,"W")) -> 3 | AQ50: =SUM(COUNTIFS(G51:AK51,"A"))+(COUNTIFS(G51:AK51,"B"))+(COUNTIFS(G51:AK51,"C"))+(COUNTIFS(G51:AK51,"G")) -> 0 | AR50: =SUM(COUNTIFS(G50:AK50,"PH")) -> 0 | AS50: =AL50+AM50+AN50+AO50+AR50+AP50+AQ50 -> 23
F51: E.D
A52: 25 | B52: 11862 | C52: MOHAMAD REHAN RAJE | D52: 11209 | E52: HVAC OPERATOR | F52: Duty | G52: C | H52: C | I52: W | J52: A | K52: B | L52: A | M52: A | N52: C | O52: C | P52: W | Q52: A | R52: A | S52: B | T52: B | U52: C | V52: C | W52: W | X52: A | Y52: A | Z52: L | AA52: B | AB52: C | AC52: C | AD52: W | AE52: A | AF52: A | AG52: G | AH52: A | AI52: C | AJ52: C | AK52: W | AL52: =SUM(COUNTIFS(G52:AK52,"A")) -> 10 | AM52: =SUM(COUNTIFS(G52:AK52,"B")) -> 4 | AN52: =SUM(COUNTIFS(G52:AK52,"C")) -> 10 | AO52: =SUM(COUNTIFS(G52:AK52,"G")) -> 1 | AP52: =SUM(COUNTIFS(G52:AK52,"W")) -> 5 | AQ52: =SUM(COUNTIFS(G53:AK53,"A"))+(COUNTIFS(G53:AK53,"B"))+(COUNTIFS(G53:AK53,"C"))+(COUNTIFS(G53:AK53,"G")) -> 0 | AR52: =SUM(COUNTIFS(G52:AK52,"PH")) -> 0 | AS52: =AL52+AM52+AN52+AO52+AR52+AP52+AQ52 -> 30
F53: E.D
A54: 26 | B54: 11749 | C54: SAJID HUSAIN | D54: 11201 | E54: HVAC OPERATOR | F54: Duty | G54: B | H54: B | I54: B | J54: C | K54: C | L54: B | M54: W | N54: B | O54: B | P54: B | Q54: C | R54: C | S54: B | T54: W | U54: A | V54: B | W54: C | X54: C | Y54: C | Z54: B | AA54: W | AB54: A | AC54: B | AD54: B | AE54: C | AF54: C | AG54: B | AH54: W | AI54: A | AJ54: A | AK54: A | AL54: =SUM(COUNTIFS(G54:AK54,"A")) -> 5 | AM54: =SUM(COUNTIFS(G54:AK54,"B")) -> 13 | AN54: =SUM(COUNTIFS(G54:AK54,"C")) -> 9 | AO54: =SUM(COUNTIFS(G54:AK54,"G")) -> 0 | AP54: =SUM(COUNTIFS(G54:AK54,"W")) -> 4 | AQ54: =SUM(COUNTIFS(G55:AK55,"A"))+(COUNTIFS(G55:AK55,"B"))+(COUNTIFS(G55:AK55,"C"))+(COUNTIFS(G55:AK55,"G")) -> 0 | AR54: =SUM(COUNTIFS(G54:AK54,"PH")) -> 0 | AS54: =AL54+AM54+AN54+AO54+AR54+AP54+AQ54 -> 31
F55: E.D
A56: 27 | B56: 11954 | C56: AKASHSHA | D56: 11214 | E56: HVAC OPERATOR | F56: Duty | G56: A | H56: W | I56: C | J56: B | K56: B | L56: B | M56: B | N56: A | O56: W | P56: B | Q56: B | R56: B | S56: A | T56: A | U56: A | V56: W | W56: B | X56: B | Y56: B | Z56: B | AA56: B | AB56: L | AC56: W | AD56: B | AE56: B | AF56: B | AG56: B | AH56: A | AI56: A | AJ56: W | AK56: B | AL56: =SUM(COUNTIFS(G56:AK56,"A")) -> 7 | AM56: =SUM(COUNTIFS(G56:AK56,"B")) -> 17 | AN56: =SUM(COUNTIFS(G56:AK56,"C")) -> 1 | AO56: =SUM(COUNTIFS(G56:AK56,"G")) -> 0 | AP56: =SUM(COUNTIFS(G56:AK56,"W")) -> 5 | AQ56: =SUM(COUNTIFS(G57:AK57,"A"))+(COUNTIFS(G57:AK57,"B"))+(COUNTIFS(G57:AK57,"C"))+(COUNTIFS(G57:AK57,"G")) -> 0 | AR56: =SUM(COUNTIFS(G56:AK56,"PH")) -> 0 | AS56: =AL56+AM56+AN56+AO56+AR56+AP56+AQ56 -> 30
F57: E.D
A58: 28 | B58: 12035 | C58: SAMAR QUDIR | D58: 11222 | E58: HVAC OPERATOR | F58: Duty | G58: G | H58: G | I58: C | J58: W | K58: G | L58: G | M58: B | N58: A | O58: C | P58: C | Q58: W | R58: B | S58: G | T58: G | U58: B | V58: C | W58: C | X58: W | Y58: A | Z58: A | AA58: A | AB58: A | AC58: C | AD58: C | AE58: W | AF58: A | AG58: A | AH58: B | AI58: B | AJ58: C | AK58: C | AL58: =SUM(COUNTIFS(G58:AK58,"A")) -> 7 | AM58: =SUM(COUNTIFS(G58:AK58,"B")) -> 5 | AN58: =SUM(COUNTIFS(G58:AK58,"C")) -> 9 | AO58: =SUM(COUNTIFS(G58:AK58,"G")) -> 6 | AP58: =SUM(COUNTIFS(G58:AK58,"W")) -> 4 | AQ58: =SUM(COUNTIFS(G59:AK59,"A"))+(COUNTIFS(G59:AK59,"B"))+(COUNTIFS(G59:AK59,"C"))+(COUNTIFS(G59:AK59,"G")) -> 0 | AR58: =SUM(COUNTIFS(G58:AK58,"PH")) -> 0 | AS58: =AL58+AM58+AN58+AO58+AR58+AP58+AQ58 -> 31
F59: E.D
A60: 29 | B60: 11558 | C60: CHANDRA PRAKASH MOHANTY | D60: 11185 | E60: HVAC OPERATOR | F60: Duty | AI60: G | AJ60: B | AK60: B | AL60: =SUM(COUNTIFS(G60:AK60,"A")) -> 0 | AM60: =SUM(COUNTIFS(G60:AK60,"B")) -> 2 | AN60: =SUM(COUNTIFS(G60:AK60,"C")) -> 0 | AO60: =SUM(COUNTIFS(G60:AK60,"G")) -> 1 | AP60: =SUM(COUNTIFS(G60:AK60,"W")) -> 0 | AQ60: =SUM(COUNTIFS(G61:AK61,"A"))+(COUNTIFS(G61:AK61,"B"))+(COUNTIFS(G61:AK61,"C"))+(COUNTIFS(G61:AK61,"G")) -> 0 | AR60: =SUM(COUNTIFS(G60:AK60,"PH")) -> 0 | AS60: =AL60+AM60+AN60+AO60+AR60+AP60+AQ60 -> 3
F61: E.D
A62: 30 | B62: 9 | C62: MURALI KRUSHNA | D62: 11235 | E62: HVAC OPERATOR | F62: Duty | G62: NEW JOINING | L62: G | M62: G | N62: G | O62: G | P62: G | Q62: C | R62: C | S62: W | T62: B | U62: G | V62: A | W62: A | X62: G | Y62: C | Z62: W | AA62: G | AB62: G | AC62: A | AD62: A | AE62: C | AF62: B | AG62: W | AH62: G | AI62: G | AJ62: G | AK62: G | AL62: =SUM(COUNTIFS(G62:AK62,"A")) -> 4 | AM62: =SUM(COUNTIFS(G62:AK62,"B")) -> 2 | AN62: =SUM(COUNTIFS(G62:AK62,"C")) -> 4 | AO62: =SUM(COUNTIFS(G62:AK62,"G")) -> 13 | AP62: =SUM(COUNTIFS(G62:AK62,"W")) -> 3 | AQ62: =SUM(COUNTIFS(G63:AK63,"A"))+(COUNTIFS(G63:AK63,"B"))+(COUNTIFS(G63:AK63,"C"))+(COUNTIFS(G63:AK63,"G")) -> 0 | AR62: =SUM(COUNTIFS(G62:AK62,"PH")) -> 0 | AS62: =AL62+AM62+AN62+AO62+AR62+AP62+AQ62 -> 26
F63: E.D
A64: 31 | B64: 10 | C64: RAMGIRI SATISH | D64: 11236 | E64: HVAC OPERATOR | F64: Duty | G64: NEW JOINING | L64: G | M64: G | N64: G | O64: G | P64: G | Q64: A | R64: G | S64: G | T64: C | U64: C | V64: W | W64: G | X64: G | Y64: G | Z64: G | AA64: C | AB64: B | AC64: W | AD64: B | AE64: G | AF64: G | AG64: G | AH64: C | AI64: C | AJ64: W | AK64: L | AL64: =SUM(COUNTIFS(G64:AK64,"A")) -> 1 | AM64: =SUM(COUNTIFS(G64:AK64,"B")) -> 2 | AN64: =SUM(COUNTIFS(G64:AK64,"C")) -> 5 | AO64: =SUM(COUNTIFS(G64:AK64,"G")) -> 14 | AP64: =SUM(COUNTIFS(G64:AK64,"W")) -> 3 | AQ64: =SUM(COUNTIFS(G65:AK65,"A"))+(COUNTIFS(G65:AK65,"B"))+(COUNTIFS(G65:AK65,"C"))+(COUNTIFS(G65:AK65,"G")) -> 0 | AR64: =SUM(COUNTIFS(G64:AK64,"PH")) -> 0 | AS64: =AL64+AM64+AN64+AO64+AR64+AP64+AQ64 -> 25
F65: E.D
A66: 32 | B66: 11000 | C66: ALLAUDDIN MAINUDDIN KHAJURE | D66: 11048 | E66: DG OPERATOR | F66: Duty | G66: W | H66: G | I66: G | J66: G | K66: G | L66: G | M66: G | N66: W | O66: G | P66: G | Q66: G | R66: G | S66: G | T66: G | U66: W | V66: G | W66: G | X66: G | Y66: G | Z66: G | AA66: G | AB66: W | AC66: G | AD66: G | AE66: G | AF66: G | AG66: B | AH66: G | AI66: W | AJ66: G | AK66: G | AL66: =SUM(COUNTIFS(G66:AK66,"A")) -> 0 | AM66: =SUM(COUNTIFS(G66:AK66,"B")) -> 1 | AN66: =SUM(COUNTIFS(G66:AK66,"C")) -> 0 | AO66: =SUM(COUNTIFS(G66:AK66,"G")) -> 25 | AP66: =SUM(COUNTIFS(G66:AK66,"W")) -> 5 | AQ66: =SUM(COUNTIFS(G67:AK67,"A"))+(COUNTIFS(G67:AK67,"B"))+(COUNTIFS(G67:AK67,"C"))+(COUNTIFS(G67:AK67,"G")) -> 0 | AR66: =SUM(COUNTIFS(G66:AK66,"PH")) -> 0 | AS66: =AL66+AM66+AN66+AO66+AR66+AP66+AQ66 -> 31
F67: E.D
A68: 33 | B68: 11273 | C68: P CHANDRA SHEKAR PATRA | D68: 11153 | E68: DG OPERATOR | F68: Duty | G68: C | H68: C | I68: W | J68: G | K68: B | L68: B | M68: B | N68: C | O68: C | P68: W | Q68: G | R68: A | S68: C | T68: C | U68: C | V68: C | W68: W | X68: G | Y68: B | Z68: C | AA68: C | AB68: C | AC68: C | AD68: W | AE68: A | AF68: A | AG68: C | AH68: B | AI68: B | AJ68: C | AK68: W | AL68: =SUM(COUNTIFS(G68:AK68,"A")) -> 3 | AM68: =SUM(COUNTIFS(G68:AK68,"B")) -> 6 | AN68: =SUM(COUNTIFS(G68:AK68,"C")) -> 14 | AO68: =SUM(COUNTIFS(G68:AK68,"G")) -> 3 | AP68: =SUM(COUNTIFS(G68:AK68,"W")) -> 5 | AQ68: =SUM(COUNTIFS(G69:AK69,"A"))+(COUNTIFS(G69:AK69,"B"))+(COUNTIFS(G69:AK69,"C"))+(COUNTIFS(G69:AK69,"G")) -> 0 | AR68: =SUM(COUNTIFS(G68:AK68,"PH")) -> 0 | AS68: =AL68+AM68+AN68+AO68+AR68+AP68+AQ68 -> 31
F69: E.D
A70: 34 | B70: 11551 | C70: RAUPYAPRAKASH MOHANTY | D70: 11180 | E70: DG OPERATOR | F70: Duty | G70: A | H70: B | I70: C | J70: C | K70: W | L70: A | M70: A | N70: A | O70: B | P70: C | Q70: C | R70: W | S70: A | T70: A | U70: B | V70: B | W70: C | X70: C | Y70: W | Z70: B | AA70: B | AB70: B | AC70: B | AD70: C | AE70: C | AF70: W | AG70: B | AH70: A | AI70: A | AJ70: A | AK70: C | AL70: =SUM(COUNTIFS(G70:AK70,"A")) -> 9 | AM70: =SUM(COUNTIFS(G70:AK70,"B")) -> 9 | AN70: =SUM(COUNTIFS(G70:AK70,"C")) -> 9 | AO70: =SUM(COUNTIFS(G70:AK70,"G")) -> 0 | AP70: =SUM(COUNTIFS(G70:AK70,"W")) -> 4 | AQ70: =SUM(COUNTIFS(G71:AK71,"A"))+(COUNTIFS(G71:AK71,"B"))+(COUNTIFS(G71:AK71,"C"))+(COUNTIFS(G71:AK71,"G")) -> 0 | AR70: =SUM(COUNTIFS(G70:AK70,"PH")) -> 0 | AS70: =AL70+AM70+AN70+AO70+AR70+AP70+AQ70 -> 31
F71: E.D
A72: 35 | B72: 11907 | C72: PEDDAMODU SAI SATHEESH | D72: 11213 | E72: DG OPERATOR | F72: Duty | G72: B | H72: A | I72: B | J72: B | K72: C | L72: W | M72: C | N72: B | O72: A | P72: B | Q72: B | R72: C | S72: W | T72: B | U72: A | V72: A | W72: B | X72: B | Y72: C | Z72: W | AA72: A | AB72: A | AC72: A | AD72: A | AE72: B | AF72: C | AG72: W | AH72: C | AI72: C | AJ72: B | AK72: A | AL72: =SUM(COUNTIFS(G72:AK72,"A")) -> 9 | AM72: =SUM(COUNTIFS(G72:AK72,"B")) -> 11 | AN72: =SUM(COUNTIFS(G72:AK72,"C")) -> 7 | AO72: =SUM(COUNTIFS(G72:AK72,"G")) -> 0 | AP72: =SUM(COUNTIFS(G72:AK72,"W")) -> 4 | AQ72: =SUM(COUNTIFS(G73:AK73,"A"))+(COUNTIFS(G73:AK73,"B"))+(COUNTIFS(G73:AK73,"C"))+(COUNTIFS(G73:AK73,"G")) -> 0 | AR72: =SUM(COUNTIFS(G72:AK72,"PH")) -> 0 | AS72: =AL72+AM72+AN72+AO72+AR72+AP72+AQ72 -> 31
F73: E.D
A74: 36 | B74: 10990 | C74: MUKESH SRICHANDAN | D74: 11091 | E74: BMS OPERATOR | F74: Duty | G74: L | H74: B | I74: A | J74: L | K74: L | L74: L | M74: L | N74: L | O74: L | P74: L | Q74: L | R74: L | S74: L | T74: L | U74: L | V74: L | W74: L | X74: L | Y74: L | Z74: L | AA74: L | AB74: L | AC74: L | AD74: L | AE74: L | AF74: L | AG74: L | AH74: L | AI74: L | AJ74: L | AK74: L | AL74: =SUM(COUNTIFS(G74:AK74,"A")) -> 1 | AM74: =SUM(COUNTIFS(G74:AK74,"B")) -> 1 | AN74: =SUM(COUNTIFS(G74:AK74,"C")) -> 0 | AO74: =SUM(COUNTIFS(G74:AK74,"G")) -> 0 | AP74: =SUM(COUNTIFS(G74:AK74,"W")) -> 0 | AQ74: =SUM(COUNTIFS(G75:AK75,"A"))+(COUNTIFS(G75:AK75,"B"))+(COUNTIFS(G75:AK75,"C"))+(COUNTIFS(G75:AK75,"G")) -> 0 | AR74: =SUM(COUNTIFS(G74:AK74,"PH")) -> 0 | AS74: =AL74+AM74+AN74+AO74+AR74+AP74+AQ74 -> 2
F75: E.D
A76: 37 | B76: 11 | C76: DAGE RAMA KRISHNA | D76: 11234 | E76: BMS OPERATOR | F76: Duty | G76: NEW JOINING | J76: G | K76: G | L76: G | M76: G | N76: G | O76: A | P76: G | Q76: G | R76: A | S76: G | T76: A | U76: C | V76: C | W76: G | X76: W | Y76: A | Z76: G | AA76: C | AB76: C | AC76: B | AD76: W | AE76: G | AF76: A | AG76: G | AH76: A | AI76: A | AJ76: A | AK76: W | AL76: =SUM(COUNTIFS(G76:AK76,"A")) -> 8 | AM76: =SUM(COUNTIFS(G76:AK76,"B")) -> 1 | AN76: =SUM(COUNTIFS(G76:AK76,"C")) -> 4 | AO76: =SUM(COUNTIFS(G76:AK76,"G")) -> 12 | AP76: =SUM(COUNTIFS(G76:AK76,"W")) -> 3 | AQ76: =SUM(COUNTIFS(G77:AK77,"A"))+(COUNTIFS(G77:AK77,"B"))+(COUNTIFS(G77:AK77,"C"))+(COUNTIFS(G77:AK77,"G")) -> 0 | AR76: =SUM(COUNTIFS(G76:AK76,"PH")) -> 0 | AS76: =AL76+AM76+AN76+AO76+AR76+AP76+AQ76 -> 28
F77: E.D
A78: 38 | B78: 11311 | C78: MOTIPALLI RAVI SHANKER DURGA | D78: 11155 | E78: BMS OPERATOR | F78: Duty | G78: A | H78: A | I78: C | J78: C | K78: W | L78: C | M78: C | N78: C | O78: B | P78: A | Q78: A | R78: W | S78: C | T78: C | U78: C | V78: B | W78: B | X78: A | Y78: W | Z78: C | AA78: B | AB78: B | AC78: A | AD78: B | AE78: A | AF78: W | AG78: C | AH78: C | AI78: C | AJ78: B | AK78: A | AL78: =SUM(COUNTIFS(G78:AK78,"A")) -> 8 | AM78: =SUM(COUNTIFS(G78:AK78,"B")) -> 7 | AN78: =SUM(COUNTIFS(G78:AK78,"C")) -> 12 | AO78: =SUM(COUNTIFS(G78:AK78,"G")) -> 0 | AP78: =SUM(COUNTIFS(G78:AK78,"W")) -> 4 | AQ78: =SUM(COUNTIFS(G79:AK79,"A"))+(COUNTIFS(G79:AK79,"B"))+(COUNTIFS(G79:AK79,"C"))+(COUNTIFS(G79:AK79,"G")) -> 0 | AR78: =SUM(COUNTIFS(G78:AK78,"PH")) -> 0 | AS78: =AL78+AM78+AN78+AO78+AR78+AP78+AQ78 -> 31
F79: E.D
A80: 39 | B80: 11376 | C80: J.CHATTYNYA | D80: 11220 | E80: BMS OPERATOR | F80: Duty | G80: B | H80: C | I80: B | J80: B | K80: C | L80: B | M80: A | N80: A | O80: C | P80: C | Q80: B | R80: B | S80: A | T80: W | U80: B | V80: A | W80: A | X80: C | Y80: B | Z80: A | AA80: W | AB80: C | AC80: C | AD80: C | AE80: B | AF80: B | AG80: A | AH80: W | AI80: G | AJ80: A | AK80: B | AL80: =SUM(COUNTIFS(G80:AK80,"A")) -> 8 | AM80: =SUM(COUNTIFS(G80:AK80,"B")) -> 11 | AN80: =SUM(COUNTIFS(G80:AK80,"C")) -> 8 | AO80: =SUM(COUNTIFS(G80:AK80,"G")) -> 1 | AP80: =SUM(COUNTIFS(G80:AK80,"W")) -> 3 | AQ80: =SUM(COUNTIFS(G81:AK81,"A"))+(COUNTIFS(G81:AK81,"B"))+(COUNTIFS(G81:AK81,"C"))+(COUNTIFS(G81:AK81,"G")) -> 0 | AR80: =SUM(COUNTIFS(G80:AK80,"PH")) -> 0 | AS80: =AL80+AM80+AN80+AO80+AR80+AP80+AQ80 -> 31
F81: E.D
A82: 40 | B82: 10980 | C82: ANURUDHA SAMAL | D82: 10609 | E82: PLUMBER | F82: Duty | G82: A | H82: C | I82: W | J82: G | K82: A | L82: L | M82: L | N82: L | O82: L | P82: L | Q82: L | R82: L | S82: L | T82: L | U82: L | V82: L | W82: L | X82: L | Y82: L | Z82: L | AA82: L | AB82: L | AC82: L | AD82: L | AE82: L | AF82: L | AG82: L | AH82: L | AI82: L | AJ82: L | AK82: L | AL82: =SUM(COUNTIFS(G82:AK82,"A")) -> 2 | AM82: =SUM(COUNTIFS(G82:AK82,"B")) -> 0 | AN82: =SUM(COUNTIFS(G82:AK82,"C")) -> 1 | AO82: =SUM(COUNTIFS(G82:AK82,"G")) -> 1 | AP82: =SUM(COUNTIFS(G82:AK82,"W")) -> 1 | AQ82: =SUM(COUNTIFS(G83:AK83,"A"))+(COUNTIFS(G83:AK83,"B"))+(COUNTIFS(G83:AK83,"C"))+(COUNTIFS(G83:AK83,"G")) -> 0 | AR82: =SUM(COUNTIFS(G82:AK82,"PH")) -> 0 | AS82: =AL82+AM82+AN82+AO82+AR82+AP82+AQ82 -> 5
F83: E.D
A84: 41 | B84: 10978 | C84: PABITRA MALIK | D84: 11085 | E84: PLUMBER | F84: Duty | G84: W | H84: A | I84: A | J84: A | K84: G | L84: B | M84: A | N84: W | O84: C | P84: B | Q84: B | R84: G | S84: A | T84: C | U84: W | V84: A | W84: A | X84: G | Y84: G | Z84: A | AA84: C | AB84: W | AC84: A | AD84: A | AE84: B | AF84: G | AG84: C | AH84: C | AI84: W | AJ84: A | AK84: A | AL84: =SUM(COUNTIFS(G84:AK84,"A")) -> 12 | AM84: =SUM(COUNTIFS(G84:AK84,"B")) -> 4 | AN84: =SUM(COUNTIFS(G84:AK84,"C")) -> 5 | AO84: =SUM(COUNTIFS(G84:AK84,"G")) -> 5 | AP84: =SUM(COUNTIFS(G84:AK84,"W")) -> 5 | AQ84: =SUM(COUNTIFS(G85:AK85,"A"))+(COUNTIFS(G85:AK85,"B"))+(COUNTIFS(G85:AK85,"C"))+(COUNTIFS(G85:AK85,"G")) -> 0 | AR84: =SUM(COUNTIFS(G84:AK84,"PH")) -> 0 | AS84: =AL84+AM84+AN84+AO84+AR84+AP84+AQ84 -> 31
F85: E.D
A86: S.NO | B86: EMP.CODE | C86: NAME | D86: BIO METRIC CODE | E86: Designation | F86: Duty | G86: 1 | H86: 2 | I86: 3 | J86: 4 | K86: 5 | L86: 6 | M86: 7 | N86: 8 | O86: 9 | P86: 10 | Q86: 11 | R86: 12 | S86: 13 | T86: 14 | U86: 15 | V86: 16 | W86: 17 | X86: 18 | Y86: 19 | Z86: 20 | AA86: 21 | AB86: 22 | AC86: 23 | AD86: 24 | AE86: 25 | AF86: 26 | AG86: 27 | AH86: 28 | AI86: 29 | AJ86: 30 | AK86: 31 | AL86: A | AM86: B | AN86: C | AO86: G | AP86: W | AQ86: ED | AR86: PH | AS86: Total
G87: Wed | H87: Thu | I87: Fri | J87: Sat | K87: Sun | L87: Mon | M87: Tue | N87: Wed | O87: Thu | P87: Fri | Q87: Sat | R87: Sun | S87: Mon | T87: Tue | U87: Wed | V87: Thu | W87: Fri | X87: Sat | Y87: Sun | Z87: Mon | AA87: Tue | AB87: Wed | AC87: Thu | AD87: Fri | AE87: Sat | AF87: Sun | AG87: Mon | AH87: Tue | AI87: Wed | AJ87: Thu | AK87: Fri
A88: 42 | B88: 10974 | C88: GADADHAR MALIK | D88: 11098 | E88: PLUMBER | F88: Duty | G88: C | H88: W | I88: C | J88: B | K88: B | L88: A | M88: C | N88: C | O88: W | P88: A | Q88: A | R88: A | S88: B | T88: A | U88: A | V88: W | W88: G | X88: A | Y88: A | Z88: B | AA88: A | AB88: A | AC88: W | AD88: B | AE88: A | AF88: B | AG88: A | AH88: A | AI88: A | AJ88: W | AK88: B | AL88: =SUM(COUNTIFS(G88:AK88,"A")) -> 14 | AM88: =SUM(COUNTIFS(G88:AK88,"B")) -> 7 | AN88: =SUM(COUNTIFS(G88:AK88,"C")) -> 4 | AO88: =SUM(COUNTIFS(G88:AK88,"G")) -> 1 | AP88: =SUM(COUNTIFS(G88:AK88,"W")) -> 5 | AQ88: =SUM(COUNTIFS(G89:AK89,"A"))+(COUNTIFS(G89:AK89,"B"))+(COUNTIFS(G89:AK89,"C"))+(COUNTIFS(G89:AK89,"G")) -> 0 | AR88: =SUM(COUNTIFS(G88:AK88,"PH")) -> 0 | AS88: =AL88+AM88+AN88+AO88+AR88+AP88+AQ88 -> 31
F89: E.D
A90: 43 | B90: 10983 | C90: NEELAIAH GARI SUDHAKAR | D90: 11117 | E90: PLUMBER | F90: Duty | G90: L | H90: L | I90: L | J90: L | K90: L | L90: L | M90: L | N90: L | O90: L | P90: L | Q90: L | R90: L | S90: L | T90: L | U90: L | V90: L | W90: L | X90: L | Y90: L | Z90: L | AA90: L | AB90: L | AC90: L | AD90: C | AE90: C | AF90: C | AG90: C | AH90: C | AI90: C | AJ90: W | AK90: L | AL90: =SUM(COUNTIFS(G90:AK90,"A")) -> 0 | AM90: =SUM(COUNTIFS(G90:AK90,"B")) -> 0 | AN90: =SUM(COUNTIFS(G90:AK90,"C")) -> 6 | AO90: =SUM(COUNTIFS(G90:AK90,"G")) -> 0 | AP90: =SUM(COUNTIFS(G90:AK90,"W")) -> 1 | AQ90: =SUM(COUNTIFS(G91:AK91,"A"))+(COUNTIFS(G91:AK91,"B"))+(COUNTIFS(G91:AK91,"C"))+(COUNTIFS(G91:AK91,"G")) -> 0 | AR90: =SUM(COUNTIFS(G90:AK90,"PH")) -> 0 | AS90: =AL90+AM90+AN90+AO90+AR90+AP90+AQ90 -> 7
F91: E.D
A92: 44 | B92: 11158 | C92: NARESH DAS | D92: 11134 | E92: PLUMBER | F92: Duty | G92: B | H92: B | I92: B | J92: B | K92: C | L92: C | M92: W | N92: G | O92: A | P92: B | Q92: G | R92: C | S92: C | T92: W | U92: G | V92: B | W92: B | X92: B | Y92: C | Z92: C | AA92: W | AB92: G | AC92: B | AD92: B | AE92: A | AF92: C | AG92: B | AH92: W | AI92: A | AJ92: C | AK92: C | AL92: =SUM(COUNTIFS(G92:AK92,"A")) -> 3 | AM92: =SUM(COUNTIFS(G92:AK92,"B")) -> 11 | AN92: =SUM(COUNTIFS(G92:AK92,"C")) -> 9 | AO92: =SUM(COUNTIFS(G92:AK92,"G")) -> 4 | AP92: =SUM(COUNTIFS(G92:AK92,"W")) -> 4 | AQ92: =SUM(COUNTIFS(G93:AK93,"A"))+(COUNTIFS(G93:AK93,"B"))+(COUNTIFS(G93:AK93,"C"))+(COUNTIFS(G93:AK93,"G")) -> 0 | AR92: =SUM(COUNTIFS(G92:AK92,"PH")) -> 0 | AS92: =AL92+AM92+AN92+AO92+AR92+AP92+AQ92 -> 31
F93: E.D
A94: 45 | B94: 11203 | C94: BISWAJIT SAHOO | D94: 11139 | E94: PLUMBER | F94: Duty | G94: G | H94: G | I94: G | J94: W | K94: G | L94: G | M94: G | N94: A | O94: G | P94: G | Q94: W | R94: G | S94: G | T94: G | U94: C | V94: C | W94: B | X94: W | Y94: B | Z94: G | AA94: G | AB94: C | AC94: C | AD94: Tansfer B1 to B6 | AL94: =SUM(COUNTIFS(G94:AK94,"A")) -> 1 | AM94: =SUM(COUNTIFS(G94:AK94,"B")) -> 2 | AN94: =SUM(COUNTIFS(G94:AK94,"C")) -> 4 | AO94: =SUM(COUNTIFS(G94:AK94,"G")) -> 13 | AP94: =SUM(COUNTIFS(G94:AK94,"W")) -> 3 | AQ94: =SUM(COUNTIFS(G95:AK95,"A"))+(COUNTIFS(G95:AK95,"B"))+(COUNTIFS(G95:AK95,"C"))+(COUNTIFS(G95:AK95,"G")) -> 0 | AR94: =SUM(COUNTIFS(G94:AK94,"PH")) -> 0 | AS94: =AL94+AM94+AN94+AO94+AR94+AP94+AQ94 -> 23
F95: E.D
A96: 46 | B96: 11276 | C96: GOPAL ROUT | D96: 11151 | E96: PLUMBER | F96: Duty | G96: B | H96: B | I96: C | J96: C | K96: C | L96: W | M96: B | N96: B | O96: B | P96: C | Q96: C | R96: B | S96: W | T96: B | U96: B | V96: G | W96: C | X96: C | Y96: B | Z96: W | AA96: B | AB96: B | AC96: B | AD96: C | AE96: C | AF96: B | AG96: W | AH96: B | AI96: B | AJ96: B | AK96: B | AL96: =SUM(COUNTIFS(G96:AK96,"A")) -> 0 | AM96: =SUM(COUNTIFS(G96:AK96,"B")) -> 17 | AN96: =SUM(COUNTIFS(G96:AK96,"C")) -> 9 | AO96: =SUM(COUNTIFS(G96:AK96,"G")) -> 1 | AP96: =SUM(COUNTIFS(G96:AK96,"W")) -> 4 | AQ96: =SUM(COUNTIFS(G97:AK97,"A"))+(COUNTIFS(G97:AK97,"B"))+(COUNTIFS(G97:AK97,"C"))+(COUNTIFS(G97:AK97,"G")) -> 0 | AR96: =SUM(COUNTIFS(G96:AK96,"PH")) -> 0 | AS96: =AL96+AM96+AN96+AO96+AR96+AP96+AQ96 -> 31
F97: E.D
A98: 47 | B98: 11439 | C98: RAJA MALIK | D98: 11171 | E98: PLUMBER | F98: Duty | G98: C | H98: W | I98: B | J98: L | K98: L | L98: B | M98: C | N98: C | O98: L | P98: L | Q98: L | R98: L | S98: L | T98: L | U98: L | V98: L | W98: L | X98: L | Y98: L | Z98: L | AA98: L | AB98: C | AC98: C | AD98: B | AE98: B | AF98: A | AG98: B | AH98: G | AI98: C | AJ98: W | AK98: G | AL98: =SUM(COUNTIFS(G98:AK98,"A")) -> 1 | AM98: =SUM(COUNTIFS(G98:AK98,"B")) -> 5 | AN98: =SUM(COUNTIFS(G98:AK98,"C")) -> 6 | AO98: =SUM(COUNTIFS(G98:AK98,"G")) -> 2 | AP98: =SUM(COUNTIFS(G98:AK98,"W")) -> 2 | AQ98: =SUM(COUNTIFS(G99:AK99,"A"))+(COUNTIFS(G99:AK99,"B"))+(COUNTIFS(G99:AK99,"C"))+(COUNTIFS(G99:AK99,"G")) -> 0 | AR98: =SUM(COUNTIFS(G98:AK98,"PH")) -> 0 | AS98: =AL98+AM98+AN98+AO98+AR98+AP98+AQ98 -> 16
F99: E.D
A100: 48 | B100: 12 | C100: TAPAS MALIK | D100: 11240 | E100: PLUMBER | F100: Duty | G100: NEW JOINING | AB100: G | AC100: G | AD100: G | AE100: G | AF100: A | AG100: G | AH100: B | AI100: B | AJ100: B | AK100: C | AL100: =SUM(COUNTIFS(G100:AK100,"A")) -> 1 | AM100: =SUM(COUNTIFS(G100:AK100,"B")) -> 3 | AN100: =SUM(COUNTIFS(G100:AK100,"C")) -> 1 | AO100: =SUM(COUNTIFS(G100:AK100,"G")) -> 5 | AP100: =SUM(COUNTIFS(G100:AK100,"W")) -> 0 | AQ100: =SUM(COUNTIFS(G101:AK101,"A"))+(COUNTIFS(G101:AK101,"B"))+(COUNTIFS(G101:AK101,"C"))+(COUNTIFS(G101:AK101,"G")) -> 0 | AR100: =SUM(COUNTIFS(G100:AK100,"PH")) -> 0 | AS100: =AL100+AM100+AN100+AO100+AR100+AP100+AQ100 -> 10
...

Sheet PAYSHEET
AD2: grooming deduction
A3: MIDAS-B1&B2 FOR THE MONTH OF JUL-2026 | H3: ACTUAL COMPONENTS | Q3: EARNING COMPONENTS | AA3: DEDUCTIONS
A4: S.NO | B4: EMP CODE | C4: EMPLOYEE NAME | D4: Designation | E4: ACTUAL DAYS | F4: NET PAID DAYS | G4: EXTRA DEPLOYMENT | H4: GROSS SALARY | I4: BASIC | J4: DA | K4: HRA | L4: OTHER ALLOWANCE | M4: Bonus 8.33% (Basic + DA) | N4: Leave Wage (EL @ 18days) 4.93% | O4: Leave Wage (CL @ 12days) 3.29% | P4: National Holiday and Festival Holidays 10 days @2.88% | Q4: BASIC | R4: DA | S4: HRA | T4: OTHER ALLOWANCE | U4: Bonus 8.33% (Basic + DA) | V4: Leave Wage (EL @ 18days) 4.93% | W4: Leave Wage (CL @ 12days) 3.29% | X4: National Holiday and Festival Holidays 10 days @2.88% | Y4: Extra Deployment Amount | Z4: GROSS EARNINGS | AA4: EMPLOYEE PF@12% | AB4: EMPLOYEE ESI@0.75% | AC4: PROFESSION TAX | AD4: Advances | AE4: TOTAL DEDUCTIONS | AF4: NET PAY | AG4: EMPLOYER PF@13% | AH4: EMPLOYER ESI @3.25% / INSURANCE | AI4: CTC | AJ4: WO VALUE | AK4: WO EXCESS VALUE | AL4: CURRENT TAKE HOME
A5: 1 | B5: 11029 | C5: SUDHIR KUMAR RAUTARAY | D5: TECHNICAL EXECUTIVE | E5: 31 | F5: =VLOOKUP(B5,ATTENDANCE!$B$4:$AS$113,44,0) -> 31 | G5: 0 | H5: =I5+J5+K5+L5 -> 32704 | I5: 5557 | J5: 14443 | K5: =(I5+J5)*40% -> 8000 | L5: 4704 | M5: =(I5+J5)*8.33% -> 1666 | N5: =H5*4.93% -> 1612.3072 | O5: =H5*3.29% -> 1075.9616 | P5: =H5*2.88% -> 941.8752 | Q5: =I5/E5*F5 -> 5557 | R5: =J5/E5*F5 -> 14443 | S5: =+K5/E5*F5 -> 8000 | T5: =L5/E5*F5 -> 4704 | U5: =M5/E5*F5 -> 1666 | V5: =N5/E5*F5 -> 1612.3072 | W5: =O5/E5*F5 -> 1075.9616 | X5: =P5/E5*F5 -> 941.8752 | Y5: =(H5+M5+N5+O5+P5)/E5*G5 -> 0 | Z5: =Q5+R5+S5+T5+U5+V5+W5+X5+Y5 -> 38000.144 | AA5: =1800*F5/E5 -> 1800 | AB5: 0 | AC5: =IF(Z5>20000,200,IF(Z5>15000,150,0)) -> 200 | AD5: 0 | AE5: =AA5+AB5+AC5+AD5 -> 2000 | AF5: =ROUND(Z5-AE5,0) -> 36000 | AG5: =AA5*13/12 -> 1950 | AH5: 1000 | AI5: =Z5+AG5+AH5 -> 40950.144 | AJ5: =39780*(F5+G5)/E5 -> 39780 | AK5: =AJ5-AI5 -> -1170.144 | AL5: 36000
C6: TECHNICAL EXECUTIVE | E6: =SUM(E5) -> 31 | F6: =SUM(F5) -> 31 | G6: =SUM(G5) -> 0 | H6: =SUM(H5) -> 32704 | I6: =SUM(I5) -> 5557 | J6: =SUM(J5) -> 14443 | K6: =SUM(K5) -> 8000 | L6: =SUM(L5) -> 4704 | ... AL6: =SUM(AL5) -> 36000
A7: 2 | B7: 10984 | C7: K.RAJYALAKSHMI | D7: TECHNICAL SUPERVISOR | E7: 31 | F7: =VLOOKUP(B7,ATTENDANCE!$B$4:$AS$113,44,0) -> 30 | G7: 0 | H7: =I7+J7+K7+L7 -> 24715.5 | I7: 4722 | J7: 13778 | K7: 6215.5 | L7: 0 | M7: =(I7+J7)*8.33% -> 1541.05 | N7: =H7*4.93% -> 1218.4742 | O7: =H7*3.29% -> 813.13995 | P7: =H7*2.88% -> 711.8064 | Q7: =I7/E7*F7 -> 4569.6774 | R7: =J7/E7*F7 -> 13333.548 | S7: =+K7/E7*F7 -> 6015 | T7: =L7/E7*F7 -> 0 | U7: =M7/E7*F7 -> 1491.3387 | V7: =N7/E7*F7 -> 1179.1685 | W7: =O7/E7*F7 -> 786.90963 | X7: =P7/E7*F7 -> 688.8449 | Y7: =(H7+M7+N7+O7+P7)/E7*G7 -> 0 | Z7: =Q7+R7+S7+T7+U7+V7+W7+X7+Y7 -> 28064.488 | AA7: =1800*F7/E7 -> 1741.9355 | AB7: 0 | AC7: =IF(Z7>20000,200,IF(Z7>15000,150,0)) -> 200 | AD7: 0 | AE7: =AA7+AB7+AC7+AD7 -> 1941.9355 | AF7: =ROUND(Z7-AE7,0) -> 26123 | AG7: =AA7*13/12 -> 1887.0968 | AH7: 1000 | AI7: =Z7+AG7+AH7 -> 30951.584 | AJ7: =31244*(F7+G7)/E7 -> 30236.129 | AK7: =AJ7-AI7 -> -715.45532 | AL7: 27000
A8: =+A7+1 -> 3 | B8: 10986 | C8: KHIROD DAS | D8: TECHNICAL SUPERVISOR | E8: 31 | F8: =VLOOKUP(B8,ATTENDANCE!$B$4:$AS$113,44,0) -> 15 | G8: 0 | H8: =I8+J8+K8+L8 -> 26516 | I8: 4722 | J8: 13778 | K8: =(I8+J8)*40% -> 7400 | L8: 616 | M8: =(I8+J8)*8.33% -> 1541.05 | N8: =H8*4.93% -> 1307.2388 | O8: =H8*3.29% -> 872.3764 | P8: =H8*2.88% -> 763.6608 | Q8: =I8/E8*F8 -> 2284.8387 | R8: =J8/E8*F8 -> 6666.7742 | S8: =+K8/E8*F8 -> 3580.6452 | T8: =L8/E8*F8 -> 298.06452 | U8: =M8/E8*F8 -> 745.66935 | V8: =N8/E8*F8 -> 632.5349 | W8: =O8/E8*F8 -> 422.11761 | X8: =P8/E8*F8 -> 369.51329 | Y8: =(H8+M8+N8+O8+P8)/E8*G8 -> 0 | Z8: =Q8+R8+S8+T8+U8+V8+W8+X8+Y8 -> 15000.158 | AA8: =1800*F8/E8 -> 870.96774 | AB8: 0 | AC8: =IF(Z8>20000,200,IF(Z8>15000,150,0)) -> 150 | AD8: 0 | AE8: =AA8+AB8+AC8+AD8 -> 1020.9677 | AF8: =ROUND(Z8-AE8,0) -> 13979 | AG8: =AA8*13/12 -> 943.54839 | AH8: 1000 | AI8: =Z8+AG8+AH8 -> 16943.706 | AJ8: =31244*(F8+G8)/E8 -> 15118.065 | AK8: =AJ8-AI8 -> -1825.6416 | AL8: 29000
A9: =+A8+1 -> 4 | B9: 10976 | C9: KONGANI NARAYANA | D9: TECHNICAL SUPERVISOR | E9: 31 | F9: =VLOOKUP(B9,ATTENDANCE!$B$4:$AS$113,44,0) -> 31 | G9: 0 | H9: =I9+J9+K9+L9 -> 24715.5 | I9: 4722 | J9: 13778 | K9: 6215.5 | L9: 0 | M9: =(I9+J9)*8.33% -> 1541.05 | N9: =H9*4.93% -> 1218.4742 | O9: =H9*3.29% -> 813.13995 | P9: =H9*2.88% -> 711.8064 | Q9: =I9/E9*F9 -> 4722 | R9: =J9/E9*F9 -> 13778 | S9: =+K9/E9*F9 -> 6215.5 | T9: =L9/E9*F9 -> 0 | U9: =M9/E9*F9 -> 1541.05 | V9: =N9/E9*F9 -> 1218.4742 | W9: =O9/E9*F9 -> 813.13995 | X9: =P9/E9*F9 -> 711.8064 | Y9: =(H9+M9+N9+O9+P9)/E9*G9 -> 0 | Z9: =Q9+R9+S9+T9+U9+V9+W9+X9+Y9 -> 28999.97 | AA9: =1800*F9/E9 -> 1800 | AB9: 0 | AC9: =IF(Z9>20000,200,IF(Z9>15000,150,0)) -> 200 | AD9: 0 | AE9: =AA9+AB9+AC9+AD9 -> 2000 | AF9: =ROUND(Z9-AE9,0) -> 27000 | AG9: =AA9*13/12 -> 1950 | AH9: 1000 | AI9: =Z9+AG9+AH9 -> 31949.97 | AJ9: =31244*(F9+G9)/E9 -> 31244 | AK9: =AJ9-AI9 -> -705.9705 | AL9: 27000
A10: =+A9+1 -> 5 | B10: 11365 | C10: B.SANDEEP | D10: TECHNICAL SUPERVISOR | E10: 31 | F10: =VLOOKUP(B10,ATTENDANCE!$B$4:$AS$113,44,0) -> 30 | G10: 0 | H10: =I10+J10+K10+L10 -> 23815.4 | I10: 4722 | J10: 13778 | K10: 5315.4 | L10: 0 | M10: =(I10+J10)*8.33% -> 1541.05 | N10: =H10*4.93% -> 1174.0992 | O10: =H10*3.29% -> 783.52666 | P10: =H10*2.88% -> 685.88352 | Q10: =I10/E10*F10 -> 4569.6774 | R10: =J10/E10*F10 -> 13333.548 | S10: =+K10/E10*F10 -> 5143.9355 | T10: =L10/E10*F10 -> 0 | U10: =M10/E10*F10 -> 1491.3387 | V10: =N10/E10*F10 -> 1136.2251 | W10: =O10/E10*F10 -> 758.25161 | X10: =P10/E10*F10 -> 663.75825 | Y10: =(H10+M10+N10+O10+P10)/E10*G10 -> 0 | Z10: =Q10+R10+S10+T10+U10+V10+W10+X10+Y10 -> 27096.735 | AA10: =1800*F10/E10 -> 1741.9355 | AB10: 0 | AC10: =IF(Z10>20000,200,IF(Z10>15000,150,0)) -> 200 | AD10: 0 | AE10: =AA10+AB10+AC10+AD10 -> 1941.9355 | AF10: =ROUND(Z10-AE10,0) -> 25155 | AG10: =AA10*13/12 -> 1887.0968 | AH10: 1000 | AI10: =Z10+AG10+AH10 -> 29983.832 | AJ10: =31244*(F10+G10)/E10 -> 30236.129 | AK10: =AJ10-AI10 -> 252.29735 | AL10: 26000
A11: =+A10+1 -> 6 | B11: 10989 | C11: NAGENDRA BABU | D11: TECHNICAL SUPERVISOR | E11: 31 | F11: =VLOOKUP(B11,ATTENDANCE!$B$4:$AS$113,44,0) -> 31 | G11: 0 | H11: =I11+J11+K11+L11 -> 24715.4 | I11: 4722 | J11: 13778 | K11: 6215.4 | L11: 0 | M11: =(I11+J11)*8.33% -> 1541.05 | N11: =H11*4.93% -> 1218.4692 | O11: =H11*3.29% -> 813.13666 | P11: =H11*2.88% -> 711.80352 | Q11: =I11/E11*F11 -> 4722 | R11: =J11/E11*F11 -> 13778 | S11: =+K11/E11*F11 -> 6215.4 | T11: =L11/E11*F11 -> 0 | U11: =M11/E11*F11 -> 1541.05 | V11: =N11/E11*F11 -> 1218.4692 | W11: =O11/E11*F11 -> 813.13666 | X11: =P11/E11*F11 -> 711.80352 | Y11: =(H11+M11+N11+O11+P11)/E11*G11 -> 0 | Z11: =Q11+R11+S11+T11+U11+V11+W11+X11+Y11 -> 28999.859 | AA11: =1800*F11/E11 -> 1800 | AB11: 0 | AC11: =IF(Z11>20000,200,IF(Z11>15000,150,0)) -> 200 | AD11: 0 | AE11: =AA11+AB11+AC11+AD11 -> 2000 | AF11: =ROUND(Z11-AE11,0) -> 27000 | AG11: =AA11*13/12 -> 1950 | AH11: 1000 | AI11: =Z11+AG11+AH11 -> 31949.859 | AJ11: =31244*(F11+G11)/E11 -> 31244 | AK11: =AJ11-AI11 -> -705.8594 | AL11: 27000
A12: =+A11+1 -> 7 | B12: 10982 | C12: SAGAR KUMAR BEHERA | D12: TECHNICAL SUPERVISOR | E12: 31 | F12: =VLOOKUP(B12,ATTENDANCE!$B$4:$AS$113,44,0) -> 31 | G12: 0 | H12: =I12+J12+K12+L12 -> 23365 | I12: 4722 | J12: 13778 | K12: 4865 | L12: 0 | M12: =(I12+J12)*8.33% -> 1541.05 | N12: =H12*4.93% -> 1151.8945 | O12: =H12*3.29% -> 768.7085 | P12: =H12*2.88% -> 672.912 | Q12: =I12/E12*F12 -> 4722 | R12: =J12/E12*F12 -> 13778 | S12: =+K12/E12*F12 -> 4865 | T12: =L12/E12*F12 -> 0 | U12: =M12/E12*F12 -> 1541.05 | V12: =N12/E12*F12 -> 1151.8945 | W12: =O12/E12*F12 -> 768.7085 | X12: =P12/E12*F12 -> 672.912 | Y12: =(H12+M12+N12+O12+P12)/E12*G12 -> 0 | Z12: =Q12+R12+S12+T12+U12+V12+W12+X12+Y12 -> 27499.565 | AA12: =1800*F12/E12 -> 1800 | AB12: 0 | AC12: =IF(Z12>20000,200,IF(Z12>15000,150,0)) -> 200 | AD12: 0 | AE12: =AA12+AB12+AC12+AD12 -> 2000 | AF12: =ROUND(Z12-AE12,0) -> 25500 | AG12: =AA12*13/12 -> 1950 | AH12: 1000 | AI12: =Z12+AG12+AH12 -> 30449.565 | AJ12: =31244*(F12+G12)/E12 -> 31244 | AK12: =AJ12-AI12 -> 794.435 | AL12: 25500
A13: =+A12+1 -> 8 | B13: 12076 | C13: JALEM ROHAN | D13: TECHNICAL SUPERVISOR | E13: 31 | F13: =VLOOKUP(B13,ATTENDANCE!$B$4:$AS$113,44,0) -> 31 | G13: 0 | H13: =I13+J13+K13+L13 -> 22915 | I13: 4722 | J13: 13778 | K13: 4415 | L13: 0 | M13: =(I13+J13)*8.33% -> 1541.05 | N13: =H13*4.93% -> 1129.7095 | O13: =H13*3.29% -> 753.9035 | P13: =H13*2.88% -> 659.952 | Q13: =I13/E13*F13 -> 4722 | R13: =J13/E13*F13 -> 13778 | S13: =+K13/E13*F13 -> 4415 | T13: =L13/E13*F13 -> 0 | U13: =M13/E13*F13 -> 1541.05 | V13: =N13/E13*F13 -> 1129.7095 | W13: =O13/E13*F13 -> 753.9035 | X13: =P13/E13*F13 -> 659.952 | Y13: =(H13+M13+N13+O13+P13)/E13*G13 -> 0 | Z13: =Q13+R13+S13+T13+U13+V13+W13+X13+Y13 -> 26999.615 | AA13: =1800*F13/E13 -> 1800 | AB13: 0 | AC13: =IF(Z13>20000,200,IF(Z13>15000,150,0)) -> 200 | AD13: 0 | AE13: =AA13+AB13+AC13+AD13 -> 2000 | AF13: =ROUND(Z13-AE13,0) -> 25000 | AG13: =AA13*13/12 -> 1950 | AH13: 1000 | AI13: =Z13+AG13+AH13 -> 29949.615 | AJ13: =31244*(F13+G13)/E13 -> 31244 | AK13: =AJ13-AI13 -> 1294.385 | AL13: 25000
A14: =+A13+1 -> 9 | B14: 10013 | C14: H.PANDA | D14: TECHNICAL SUPERVISOR | E14: 31 | F14: =VLOOKUP(B14,ATTENDANCE!$B$4:$AS$113,44,0) -> 31 | G14: 0 | H14: =I14+J14+K14+L14 -> 23815.4 | I14: 4722 | J14: 13778 | K14: 5315.4 | L14: 0 | M14: =(I14+J14)*8.33% -> 1541.05 | N14: =H14*4.93% -> 1174.0992 | O14: =H14*3.29% -> 783.52666 | P14: =H14*2.88% -> 685.88352 | Q14: =I14/E14*F14 -> 4722 | R14: =J14/E14*F14 -> 13778 | S14: =+K14/E14*F14 -> 5315.4 | T14: =L14/E14*F14 -> 0 | U14: =M14/E14*F14 -> 1541.05 | V14: =N14/E14*F14 -> 1174.0992 | W14: =O14/E14*F14 -> 783.52666 | X14: =P14/E14*F14 -> 685.88352 | Y14: =(H14+M14+N14+O14+P14)/E14*G14 -> 0 | Z14: =Q14+R14+S14+T14+U14+V14+W14+X14+Y14 -> 27999.959 | AA14: =1800*F14/E14 -> 1800 | AB14: 0 | AC14: =IF(Z14>20000,200,IF(Z14>15000,150,0)) -> 200 | AD14: 0 | AE14: =AA14+AB14+AC14+AD14 -> 2000 | AF14: =ROUND(Z14-AE14,0) -> 26000 | AG14: =AA14*13/12 -> 1950 | AH14: 1000 | AI14: =Z14+AG14+AH14 -> 30949.959 | AJ14: =31244*(F14+G14)/E14 -> 31244 | AK14: =AJ14-AI14 -> 294.0406 | AL14: 26000
C15: TECHNICAL SUPERVISOR | E15: =SUM(E7:E14) -> 248 | F15: =SUM(F7:F14) -> 230 | G15: =SUM(G7:G14) -> 0 | H15: =SUM(H7:H14) -> 194573.2 | I15: =SUM(I7:I14) -> 37776 | J15: =SUM(J7:J14) -> 110224 | K15: =SUM(K7:K14) -> 45957.2 | L15: =SUM(L7:L14) -> 616 | ... AL15: =SUM(AL7:AL14) -> 212500
A16: =A14+1 -> 10 | B16: 11032 | C16: ANANDA SHA | D16: ELECTRICIAN | E16: 31 | F16: =VLOOKUP(B16,ATTENDANCE!$B$4:$AS$113,44,0) -> 31 | G16: 0 | H16: =I16+J16+K16+L16 -> 20935 | I16: 4722 | J16: 13778 | K16: 2435 | L16: 0 | M16: =(I16+J16)*8.33% -> 1541.05 | N16: =H16*4.93% -> 1032.0955 | O16: =H16*3.29% -> 688.7615 | P16: =H16*2.88% -> 602.928 | Q16: =I16/E16*F16 -> 4722 | R16: =J16/E16*F16 -> 13778 | S16: =+K16/E16*F16 -> 2435 | T16: =L16/E16*F16 -> 0 | U16: =M16/E16*F16 -> 1541.05 | V16: =N16/E16*F16 -> 1032.0955 | W16: =O16/E16*F16 -> 688.7615 | X16: =P16/E16*F16 -> 602.928 | Y16: =(H16+M16+N16+O16+P16)/E16*G16 -> 0 | Z16: =Q16+R16+S16+T16+U16+V16+W16+X16+Y16 -> 24799.835 | AA16: =1800*F16/E16 -> 1800 | AB16: 0 | AC16: =IF(Z16>20000,200,IF(Z16>15000,150,0)) -> 200 | AD16: 0 | AE16: =AA16+AB16+AC16+AD16 -> 2000 | AF16: =ROUND(Z16-AE16,0) -> 22800 | AG16: =AA16*13/12 -> 1950 | AH16: 1000 | AI16: =Z16+AG16+AH16 -> 27749.835 | AJ16: =26607*(F16+G16)/E16 -> 26607 | AK16: =AJ16-AI16 -> -1142.835 | AL16: 22800
A17: =A16+1 -> 11 | B17: 10981 | C17: C. GANESH | D17: ELECTRICIAN | E17: 31 | F17: =VLOOKUP(B17,ATTENDANCE!$B$4:$AS$113,44,0) -> 29 | G17: 0 | H17: =I17+J17+K17+L17 -> 20215 | I17: 4722 | J17: 13778 | K17: 1715 | L17: 0 | M17: =(I17+J17)*8.33% -> 1541.05 | N17: =H17*4.93% -> 996.5995 | O17: =H17*3.29% -> 665.0735 | P17: =H17*2.88% -> 582.192 | Q17: =I17/E17*F17 -> 4417.3548 | R17: =J17/E17*F17 -> 12889.097 | S17: =+K17/E17*F17 -> 1604.3548 | T17: =L17/E17*F17 -> 0 | U17: =M17/E17*F17 -> 1441.6274 | V17: =N17/E17*F17 -> 932.30276 | W17: =O17/E17*F17 -> 622.16553 | X17: =P17/E17*F17 -> 544.63123 | Y17: =(H17+M17+N17+O17+P17)/E17*G17 -> 0 | Z17: =Q17+R17+S17+T17+U17+V17+W17+X17+Y17 -> 22451.533 | AA17: =1800*F17/E17 -> 1683.871 | AB17: 0 | AC17: =IF(Z17>20000,200,IF(Z17>15000,150,0)) -> 200 | AD17: 0 | AE17: =AA17+AB17+AC17+AD17 -> 1883.871 | AF17: =ROUND(Z17-AE17,0) -> 20568 | AG17: =AA17*13/12 -> 1824.1935 | AH17: 1000 | AI17: =Z17+AG17+AH17 -> 25275.727 | AJ17: =26607*(F17+G17)/E17 -> 24890.419 | AK17: =AJ17-AI17 -> -385.30758 | AL17: 22000
A18: =A17+1 -> 12 | B18: 11377 | C18: MANOJ KUMAR | D18: ELECTRICIAN | E18: 31 | F18: =VLOOKUP(B18,ATTENDANCE!$B$4:$AS$113,44,0) -> 25 | G18: 0 | H18: =I18+J18+K18+L18 -> 20215 | I18: 4722 | J18: 13778 | K18: 1715 | L18: 0 | M18: =(I18+J18)*8.33% -> 1541.05 | N18: =H18*4.93% -> 996.5995 | O18: =H18*3.29% -> 665.0735 | P18: =H18*2.88% -> 582.192 | Q18: =I18/E18*F18 -> 3808.0645 | R18: =J18/E18*F18 -> 11111.29 | S18: =+K18/E18*F18 -> 1383.0645 | T18: =L18/E18*F18 -> 0 | U18: =M18/E18*F18 -> 1242.7823 | V18: =N18/E18*F18 -> 803.70927 | W18: =O18/E18*F18 -> 536.3496 | X18: =P18/E18*F18 -> 469.50968 | Y18: =(H18+M18+N18+O18+P18)/E18*G18 -> 0 | Z18: =Q18+R18+S18+T18+U18+V18+W18+X18+Y18 -> 19354.77 | AA18: =1800*F18/E18 -> 1451.6129 | AB18: 0 | AC18: =IF(Z18>20000,200,IF(Z18>15000,150,0)) -> 150 | AD18: 0 | AE18: =AA18+AB18+AC18+AD18 -> 1601.6129 | AF18: =ROUND(Z18-AE18,0) -> 17753 | AG18: =AA18*13/12 -> 1572.5806 | AH18: 1000 | AI18: =Z18+AG18+AH18 -> 21927.351 | AJ18: =26607*(F18+G18)/E18 -> 21457.258 | AK18: =AJ18-AI18 -> -470.09274 | AL18: 22000
A19: =A18+1 -> 13 | B19: 1 | C19: BANAVATH BALAJI | D19: ELECTRICIAN | E19: 31 | F19: =VLOOKUP(B19,ATTENDANCE!$B$4:$AS$113,44,0) -> 28 | G19: 0 | H19: =I19+J19+K19+L19 -> 17716 | I19: 4722 | J19: 12994 | K19: 0 | L19: 0 | M19: =(I19+J19)*8.33% -> 1475.7428 | N19: =H19*4.93% -> 873.3988 | O19: =H19*3.29% -> 582.8564 | P19: =H19*2.88% -> 510.2208 | Q19: =I19/E19*F19 -> 4265.0323 | R19: =J19/E19*F19 -> 11736.516 | S19: =+K19/E19*F19 -> 0 | T19: =L19/E19*F19 -> 0 | U19: =M19/E19*F19 -> 1332.929 | V19: =N19/E19*F19 -> 788.87634 | W19: =O19/E19*F19 -> 526.45094 | X19: =P19/E19*F19 -> 460.84459 | Y19: =(H19+M19+N19+O19+P19)/E19*G19 -> 0 | Z19: =Q19+R19+S19+T19+U19+V19+W19+X19+Y19 -> 19110.649 | AA19: =1800*F19/E19 -> 1625.8065 | AB19: =Z19*0.75% -> 143.32987 | AC19: =IF(Z19>20000,200,IF(Z19>15000,150,0)) -> 150 | AD19: 0 | AE19: =AA19+AB19+AC19+AD19 -> 1919.1363 | AF19: =ROUND(Z19-AE19,0) -> 17192 | AG19: =AA19*13/12 -> 1761.2903 | AH19: =AB19*3.25/0.75 -> 621.0961 | AI19: =Z19+AG19+AH19 -> 21493.036 | AJ19: =26607*(F19+G19)/E19 -> 24032.129 | AK19: =AJ19-AI19 -> 2539.0934 | AL19: 22000
A20: =A19+1 -> 14 | B20: 2 | C20: GATTU BHANUTEJA | D20: ELECTRICIAN | E20: 31 | F20: =VLOOKUP(B20,ATTENDANCE!$B$4:$AS$113,44,0) -> 27 | G20: 0 | H20: =I20+J20+K20+L20 -> 17716 | I20: 4722 | J20: 12994 | K20: 0 | L20: 0 | M20: =(I20+J20)*8.33% -> 1475.7428 | N20: =H20*4.93% -> 873.3988 | O20: =H20*3.29% -> 582.8564 | P20: =H20*2.88% -> 510.2208 | Q20: =I20/E20*F20 -> 4112.7097 | R20: =J20/E20*F20 -> 11317.355 | S20: =+K20/E20*F20 -> 0 | T20: =L20/E20*F20 -> 0 | U20: =M20/E20*F20 -> 1285.3244 | V20: =N20/E20*F20 -> 760.70218 | W20: =O20/E20*F20 -> 507.64912 | X20: =P20/E20*F20 -> 444.38586 | Y20: =(H20+M20+N20+O20+P20)/E20*G20 -> 0 | Z20: =Q20+R20+S20+T20+U20+V20+W20+X20+Y20 -> 18428.126 | AA20: =1800*F20/E20 -> 1567.7419 | AB20: =Z20*0.75% -> 138.21095 | AC20: =IF(Z20>20000,200,IF(Z20>15000,150,0)) -> 150 | AD20: 0 | AE20: =AA20+AB20+AC20+AD20 -> 1855.9529 | AF20: =ROUND(Z20-AE20,0) -> 16572 | AG20: =AA20*13/12 -> 1698.3871 | AH20: =AB20*3.25/0.75 -> 598.9141 | AI20: =Z20+AG20+AH20 -> 20725.427 | AJ20: =26607*(F20+G20)/E20 -> 23173.839 | AK20: =AJ20-AI20 -> 2448.4115 | AL20: 22000
A21: =A20+1 -> 15 | B21: 3 | C21: MERUPULA SANDEEP GOUD | D21: ELECTRICIAN | E21: 31 | F21: =VLOOKUP(B21,ATTENDANCE!$B$4:$AS$113,44,0) -> 29 | G21: 0 | H21: =I21+J21+K21+L21 -> 17716 | I21: 4722 | J21: 12994 | K21: 0 | L21: 0 | M21: =(I21+J21)*8.33% -> 1475.7428 | N21: =H21*4.93% -> 873.3988 | O21: =H21*3.29% -> 582.8564 | P21: =H21*2.88% -> 510.2208 | Q21: =I21/E21*F21 -> 4417.3548 | R21: =J21/E21*F21 -> 12155.677 | S21: =+K21/E21*F21 -> 0 | T21: =L21/E21*F21 -> 0 | U21: =M21/E21*F21 -> 1380.5336 | V21: =N21/E21*F21 -> 817.05049 | W21: =O21/E21*F21 -> 545.25276 | X21: =P21/E21*F21 -> 477.30333 | Y21: =(H21+M21+N21+O21+P21)/E21*G21 -> 0 | Z21: =Q21+R21+S21+T21+U21+V21+W21+X21+Y21 -> 19793.172 | AA21: =1800*F21/E21 -> 1683.871 | AB21: =Z21*0.75% -> 148.44879 | AC21: =IF(Z21>20000,200,IF(Z21>15000,150,0)) -> 150 | AD21: 0 | AE21: =AA21+AB21+AC21+AD21 -> 1982.3198 | AF21: =ROUND(Z21-AE21,0) -> 17811 | AG21: =AA21*13/12 -> 1824.1935 | AH21: =AB21*3.25/0.75 -> 643.2781 | AI21: =Z21+AG21+AH21 -> 22260.644 | AJ21: =26607*(F21+G21)/E21 -> 24890.419 | AK21: =AJ21-AI21 -> 2629.7753 | AL21: 22000
A22: =A21+1 -> 16 | B22: 4 | C22: RAJANIKANT | D22: ELECTRICIAN | E22: 31 | F22: =VLOOKUP(B22,ATTENDANCE!$B$4:$AS$113,44,0) -> 10 | G22: 0 | H22: =I22+J22+K22+L22 -> 17716 | I22: 4722 | J22: 12994 | K22: 0 | L22: 0 | M22: =(I22+J22)*8.33% -> 1475.7428 | N22: =H22*4.93% -> 873.3988 | O22: =H22*3.29% -> 582.8564 | P22: =H22*2.88% -> 510.2208 | Q22: =I22/E22*F22 -> 1523.2258 | R22: =J22/E22*F22 -> 4191.6129 | S22: =+K22/E22*F22 -> 0 | T22: =L22/E22*F22 -> 0 | U22: =M22/E22*F22 -> 476.04606 | V22: =N22/E22*F22 -> 281.74155 | W22: =O22/E22*F22 -> 188.01819 | X22: =P22/E22*F22 -> 164.58735 | Y22: =(H22+M22+N22+O22+P22)/E22*G22 -> 0 | Z22: =Q22+R22+S22+T22+U22+V22+W22+X22+Y22 -> 6825.2319 | AA22: =1800*F22/E22 -> 580.64516 | AB22: =Z22*0.75% -> 51.189239 | AC22: =IF(Z22>20000,200,IF(Z22>15000,150,0)) -> 0 | AD22: 0 | AE22: =AA22+AB22+AC22+AD22 -> 631.8344 | AF22: =ROUND(Z22-AE22,0) -> 6193 | AG22: =AA22*13/12 -> 629.03226 | AH22: =AB22*3.25/0.75 -> 221.82004 | AI22: =Z22+AG22+AH22 -> 7676.0842 | AJ22: =26607*(F22+G22)/E22 -> 8582.9032 | AK22: =AJ22-AI22 -> 906.81906 | AL22: 22000
A23: =A22+1 -> 17 | B23: 5 | C23: ALOKA MUDULI | D23: ELECTRICIAN | E23: 31 | F23: =VLOOKUP(B23,ATTENDANCE!$B$4:$AS$113,44,0) -> 28 | G23: 0 | H23: =I23+J23+K23+L23 -> 18421 | I23: 4722 | J23: 13699 | K23: 0 | L23: 0 | M23: =(I23+J23)*8.33% -> 1534.4693 | N23: =H23*4.93% -> 908.1553 | O23: =H23*3.29% -> 606.0509 | P23: =H23*2.88% -> 530.5248 | Q23: =I23/E23*F23 -> 4265.0323 | R23: =J23/E23*F23 -> 12373.29 | S23: =+K23/E23*F23 -> 0 | T23: =L23/E23*F23 -> 0 | U23: =M23/E23*F23 -> 1385.9723 | V23: =N23/E23*F23 -> 820.2693 | W23: =O23/E23*F23 -> 547.40081 | X23: =P23/E23*F23 -> 479.18369 | Y23: =(H23+M23+N23+O23+P23)/E23*G23 -> 0 | Z23: =Q23+R23+S23+T23+U23+V23+W23+X23+Y23 -> 19871.149 | AA23: =1800*F23/E23 -> 1625.8065 | AB23: 0 | AC23: =IF(Z23>20000,200,IF(Z23>15000,150,0)) -> 150 | AD23: 0 | AE23: =AA23+AB23+AC23+AD23 -> 1775.8065 | AF23: =ROUND(Z23-AE23,0) -> 18095 | AG23: =AA23*13/12 -> 1761.2903 | AH23: 1000 | AI23: =Z23+AG23+AH23 -> 22632.439 | AJ23: =26607*(F23+G23)/E23 -> 24032.129 | AK23: =AJ23-AI23 -> 1399.6901 | AL23: 22000
A24: =A23+1 -> 18 | B24: 6 | C24: MD Saleem | D24: ELECTRICIAN | E24: 31 | F24: =VLOOKUP(B24,ATTENDANCE!$B$4:$AS$113,44,0) -> 23 | G24: 0 | H24: =I24+J24+K24+L24 -> 17716 | I24: 4722 | J24: 12994 | K24: 0 | L24: 0 | M24: =(I24+J24)*8.33% -> 1475.7428 | N24: =H24*4.93% -> 873.3988 | O24: =H24*3.29% -> 582.8564 | P24: =H24*2.88% -> 510.2208 | Q24: =I24/E24*F24 -> 3503.4194 | R24: =J24/E24*F24 -> 9640.7097 | S24: =+K24/E24*F24 -> 0 | T24: =L24/E24*F24 -> 0 | U24: =M24/E24*F24 -> 1094.9059 | V24: =N24/E24*F24 -> 648.00556 | W24: =O24/E24*F24 -> 432.44185 | X24: =P24/E24*F24 -> 378.55092 | Y24: =(H24+M24+N24+O24+P24)/E24*G24 -> 0 | Z24: =Q24+R24+S24+T24+U24+V24+W24+X24+Y24 -> 15698.033 | AA24: =1800*F24/E24 -> 1335.4839 | AB24: =Z24*0.75% -> 117.73525 | AC24: =IF(Z24>20000,200,IF(Z24>15000,150,0)) -> 150 | AD24: 0 | AE24: =AA24+AB24+AC24+AD24 -> 1603.2191 | AF24: =ROUND(Z24-AE24,0) -> 14095 | AG24: =AA24*13/12 -> 1446.7742 | AH24: =AB24*3.25/0.75 -> 510.18608 | AI24: =Z24+AG24+AH24 -> 17654.994 | AJ24: =26607*(F24+G24)/E24 -> 19740.677 | AK24: =AJ24-AI24 -> 2085.6838 | AL24: 22000
A25: =A24+1 -> 19 | B25: 7 | C25: Shaik Shaheed | D25: ELECTRICIAN | E25: 31 | F25: =VLOOKUP(B25,ATTENDANCE!$B$4:$AS$113,44,0) -> 24 | G25: 0 | H25: =I25+J25+K25+L25 -> 17716 | I25: 4722 | J25: 12994 | K25: 0 | L25: 0 | M25: =(I25+J25)*8.33% -> 1475.7428 | N25: =H25*4.93% -> 873.3988 | O25: =H25*3.29% -> 582.8564 | P25: =H25*2.88% -> 510.2208 | Q25: =I25/E25*F25 -> 3655.7419 | R25: =J25/E25*F25 -> 10059.871 | S25: =+K25/E25*F25 -> 0 | T25: =L25/E25*F25 -> 0 | U25: =M25/E25*F25 -> 1142.5106 | V25: =N25/E25*F25 -> 676.17972 | W25: =O25/E25*F25 -> 451.24366 | X25: =P25/E25*F25 -> 395.00965 | Y25: =(H25+M25+N25+O25+P25)/E25*G25 -> 0 | Z25: =Q25+R25+S25+T25+U25+V25+W25+X25+Y25 -> 16380.556 | AA25: =1800*F25/E25 -> 1393.5484 | AB25: =Z25*0.75% -> 122.85417 | AC25: =IF(Z25>20000,200,IF(Z25>15000,150,0)) -> 150 | AD25: 0 | AE25: =AA25+AB25+AC25+AD25 -> 1666.4026 | AF25: =ROUND(Z25-AE25,0) -> 14714 | AG25: =AA25*13/12 -> 1509.6774 | AH25: =AB25*3.25/0.75 -> 532.36809 | AI25: =Z25+AG25+AH25 -> 18422.602 | AJ25: =26607*(F25+G25)/E25 -> 20598.968 | AK25: =AJ25-AI25 -> 2176.3657 | AL25: 22000
A26: =A25+1 -> 20 | B26: 8 | C26: KAZIPETA RAVI KIRAN | D26: ELECTRICIAN | E26: 31 | F26: =VLOOKUP(B26,ATTENDANCE!$B$4:$AS$113,44,0) -> 10 | G26: 0 | H26: =I26+J26+K26+L26 -> 17716 | I26: 4722 | J26: 12994 | K26: 0 | L26: 0 | M26: =(I26+J26)*8.33% -> 1475.7428 | N26: =H26*4.93% -> 873.3988 | O26: =H26*3.29% -> 582.8564 | P26: =H26*2.88% -> 510.2208 | Q26: =I26/E26*F26 -> 1523.2258 | R26: =J26/E26*F26 -> 4191.6129 | S26: =+K26/E26*F26 -> 0 | T26: =L26/E26*F26 -> 0 | U26: =M26/E26*F26 -> 476.04606 | V26: =N26/E26*F26 -> 281.74155 | W26: =O26/E26*F26 -> 188.01819 | X26: =P26/E26*F26 -> 164.58735 | Y26: =(H26+M26+N26+O26+P26)/E26*G26 -> 0 | Z26: =Q26+R26+S26+T26+U26+V26+W26+X26+Y26 -> 6825.2319 | AA26: =1800*F26/E26 -> 580.64516 | AB26: =Z26*0.75% -> 51.189239 | AC26: =IF(Z26>20000,200,IF(Z26>15000,150,0)) -> 0 | AD26: 0 | AE26: =AA26+AB26+AC26+AD26 -> 631.8344 | AF26: =ROUND(Z26-AE26,0) -> 6193 | AG26: =AA26*13/12 -> 629.03226 | AH26: =AB26*3.25/0.75 -> 221.82004 | AI26: =Z26+AG26+AH26 -> 7676.0842 | AJ26: =26607*(F26+G26)/E26 -> 8582.9032 | AK26: =AJ26-AI26 -> 906.81906 | AL26: 22000
A27: =A26+1 -> 21 | B27: 11958 | C27: M.PRATHAP KUMAR | D27: ELECTRICIAN | E27: 31 | F27: =VLOOKUP(B27,ATTENDANCE!$B$4:$AS$113,44,0) -> 6 | G27: 0 | H27: =I27+J27+K27+L27 -> 20215 | I27: 4722 | J27: 13778 | K27: 1715 | L27: 0 | M27: =(I27+J27)*8.33% -> 1541.05 | N27: =H27*4.93% -> 996.5995 | O27: =H27*3.29% -> 665.0735 | P27: =H27*2.88% -> 582.192 | Q27: =I27/E27*F27 -> 913.93548 | R27: =J27/E27*F27 -> 2666.7097 | S27: =+K27/E27*F27 -> 331.93548 | T27: =L27/E27*F27 -> 0 | U27: =M27/E27*F27 -> 298.26774 | V27: =N27/E27*F27 -> 192.89023 | W27: =O27/E27*F27 -> 128.7239 | X27: =P27/E27*F27 -> 112.68232 | Y27: =(H27+M27+N27+O27+P27)/E27*G27 -> 0 | Z27: =Q27+R27+S27+T27+U27+V27+W27+X27+Y27 -> 4645.1448 | AA27: =1800*F27/E27 -> 348.3871 | AB27: 0 | AC27: =IF(Z27>20000,200,IF(Z27>15000,150,0)) -> 0 | AD27: 0 | AE27: =AA27+AB27+AC27+AD27 -> 348.3871 | AF27: =ROUND(Z27-AE27,0) -> 4297 | AG27: =AA27*13/12 -> 377.41935 | AH27: 1000 | AI27: =Z27+AG27+AH27 -> 6022.5642 | AJ27: =26607*(F27+G27)/E27 -> 5149.7419 | AK27: =AJ27-AI27 -> -872.82226 | AL27: 22000
A28: =A27+1 -> 22 | B28: 11651 | C28: RUDRA MADHAB SENAPATI | D28: ELECTRICIAN | E28: 31 | F28: =VLOOKUP(B28,ATTENDANCE!$B$4:$AS$113,44,0) -> 0 | G28: 0 | H28: =I28+J28+K28+L28 -> 18421 | I28: 4722 | J28: 13699 | K28: 0 | L28: 0 | M28: =(I28+J28)*8.33% -> 1534.4693 | N28: =H28*4.93% -> 908.1553 | O28: =H28*3.29% -> 606.0509 | P28: =H28*2.88% -> 530.5248 | Q28: =I28/E28*F28 -> 0 | R28: =J28/E28*F28 -> 0 | S28: =+K28/E28*F28 -> 0 | T28: =L28/E28*F28 -> 0 | U28: =M28/E28*F28 -> 0 | V28: =N28/E28*F28 -> 0 | W28: =O28/E28*F28 -> 0 | X28: =P28/E28*F28 -> 0 | Y28: =(H28+M28+N28+O28+P28)/E28*G28 -> 0 | Z28: =Q28+R28+S28+T28+U28+V28+W28+X28+Y28 -> 0 | AA28: =1800*F28/E28 -> 0 | AB28: 0 | AC28: =IF(Z28>20000,200,IF(Z28>15000,150,0)) -> 0 | AD28: 0 | AE28: =AA28+AB28+AC28+AD28 -> 0 | AF28: =ROUND(Z28-AE28,0) -> 0 | AG28: =AA28*13/12 -> 0 | AH28: 1000 | AI28: =Z28+AG28+AH28 -> 1000 | AJ28: =26607*(F28+G28)/E28 -> 0 | AK28: =AJ28-AI28 -> -1000 | AL28: 20000
C29: ELECTRICIAN | E29: =SUM(E16:E28) -> 403 | F29: =SUM(F16:F28) -> 270 | G29: =SUM(G16:G28) -> 0 | H29: =SUM(H16:H28) -> 242434 | I29: =SUM(I16:I28) -> 61386 | J29: =SUM(J16:J28) -> 173468 | K29: =SUM(K16:K28) -> 7580 | L29: =SUM(L16:L28) -> 0 | ... AL29: =SUM(AL16:AL28) -> 284800
A30: =A28+1 -> 23 | B30: 11311 | C30: MOTUPALLI RAVI SANKARA DURGA | D30: BMS OPERATOR | E30: 31 | F30: =VLOOKUP(B30,ATTENDANCE!$B$4:$AS$113,44,0) -> 31 | G30: 0 | H30: =I30+J30+K30+L30 -> 18955 | I30: 4722 | J30: 13778 | K30: 455 | L30: 0 | M30: =(I30+J30)*8.33% -> 1541.05 | N30: =H30*4.93% -> 934.4815 | O30: =H30*3.29% -> 623.6195 | P30: =H30*2.88% -> 545.904 | Q30: =I30/E30*F30 -> 4722 | R30: =J30/E30*F30 -> 13778 | S30: =+K30/E30*F30 -> 455 | T30: =L30/E30*F30 -> 0 | U30: =M30/E30*F30 -> 1541.05 | V30: =N30/E30*F30 -> 934.4815 | W30: =O30/E30*F30 -> 623.6195 | X30: =P30/E30*F30 -> 545.904 | Y30: =(H30+M30+N30+O30+P30)/E30*G30 -> 0 | Z30: =Q30+R30+S30+T30+U30+V30+W30+X30+Y30 -> 22600.055 | AA30: =1800*F30/E30 -> 1800 | AB30: 0 | AC30: =IF(Z30>20000,200,IF(Z30>15000,150,0)) -> 200 | AD30: 0 | AE30: =AA30+AB30+AC30+AD30 -> 2000 | AF30: =ROUND(Z30-AE30,0) -> 20600 | AG30: =AA30*13/12 -> 1950 | AH30: 1000 | AI30: =Z30+AG30+AH30 -> 25550.055 | AJ30: =26472*(F30+G30)/E30 -> 26472 | AK30: =AJ30-AI30 -> 921.945 | AL30: 20600
A31: =A30+1 -> 24 | B31: 11376 | C31: J.CHATTYNYA | D31: BMS OPERATOR | E31: 31 | F31: =VLOOKUP(B31,ATTENDANCE!$B$4:$AS$113,44,0) -> 31 | G31: 0 | H31: =I31+J31+K31+L31 -> 20665 | I31: 4722 | J31: 13778 | K31: 2165 | L31: 0 | M31: =(I31+J31)*8.33% -> 1541.05 | N31: =H31*4.93% -> 1018.7845 | O31: =H31*3.29% -> 679.8785 | P31: =H31*2.88% -> 595.152 | Q31: =I31/E31*F31 -> 4722 | R31: =J31/E31*F31 -> 13778 | S31: =+K31/E31*F31 -> 2165 | T31: =L31/E31*F31 -> 0 | U31: =M31/E31*F31 -> 1541.05 | V31: =N31/E31*F31 -> 1018.7845 | W31: =O31/E31*F31 -> 679.8785 | X31: =P31/E31*F31 -> 595.152 | Y31: =(H31+M31+N31+O31+P31)/E31*G31 -> 0 | Z31: =Q31+R31+S31+T31+U31+V31+W31+X31+Y31 -> 24499.865 | AA31: =1800*F31/E31 -> 1800 | AB31: 0 | AC31: =IF(Z31>20000,200,IF(Z31>15000,150,0)) -> 200 | AD31: 0 | AE31: =AA31+AB31+AC31+AD31 -> 2000 | AF31: =ROUND(Z31-AE31,0) -> 22500 | AG31: =AA31*13/12 -> 1950 | AH31: 1000 | AI31: =Z31+AG31+AH31 -> 27449.865 | AJ31: =26472*(F31+G31)/E31 -> 26472 | AK31: =AJ31-AI31 -> -977.865 | AL31: 23000
A32: =A31+1 -> 25 | B32: 11 | C32: DAGE RAMA KRISHNA | D32: BMS OPERATOR | E32: 31 | F32: =VLOOKUP(B32,ATTENDANCE!$B$4:$AS$113,44,0) -> 28 | G32: 0 | H32: =I32+J32+K32+L32 -> 18002 | I32: 4722 | J32: 13280 | K32: 0 | L32: 0 | M32: =(I32+J32)*8.33% -> 1499.5666 | N32: =H32*4.93% -> 887.4986 | O32: =H32*3.29% -> 592.2658 | P32: =H32*2.88% -> 518.4576 | Q32: =I32/E32*F32 -> 4265.0323 | R32: =J32/E32*F32 -> 11994.839 | S32: =+K32/E32*F32 -> 0 | T32: =L32/E32*F32 -> 0 | U32: =M32/E32*F32 -> 1354.4473 | V32: =N32/E32*F32 -> 801.61164 | W32: =O32/E32*F32 -> 534.94975 | X32: =P32/E32*F32 -> 468.28428 | Y32: =(H32+M32+N32+O32+P32)/E32*G32 -> 0 | Z32: =Q32+R32+S32+T32+U32+V32+W32+X32+Y32 -> 19419.164 | AA32: =1800*F32/E32 -> 1625.8065 | AB32: 0 | AC32: =IF(Z32>20000,200,IF(Z32>15000,150,0)) -> 150 | AD32: 0 | AE32: =AA32+AB32+AC32+AD32 -> 1775.8065 | AF32: =ROUND(Z32-AE32,0) -> 17643 | AG32: =AA32*13/12 -> 1761.2903 | AH32: 1000 | AI32: =Z32+AG32+AH32 -> 22180.454 | AJ32: =26472*(F32+G32)/E32 -> 23910.194 | AK32: =AJ32-AI32 -> 1729.7393 | AL32: 23000
A33: =A32+1 -> 26 | B33: 10990 | C33: MUKESH SRICHANDAN | D33: BMS OPERATOR | E33: 31 | F33: =VLOOKUP(B33,ATTENDANCE!$B$4:$AS$113,44,0) -> 2 | G33: 0 | H33: =I33+J33+K33+L33 -> 19765 | I33: 4722 | J33: 13778 | K33: 1265 | L33: 0 | M33: =(I33+J33)*8.33% -> 1541.05 | N33: =H33*4.93% -> 974.4145 | O33: =H33*3.29% -> 650.2685 | P33: =H33*2.88% -> 569.232 | Q33: =I33/E33*F33 -> 304.64516 | R33: =J33/E33*F33 -> 888.90323 | S33: =+K33/E33*F33 -> 81.612903 | T33: =L33/E33*F33 -> 0 | U33: =M33/E33*F33 -> 99.422581 | V33: =N33/E33*F33 -> 62.865452 | W33: =O33/E33*F33 -> 41.952806 | X33: =P33/E33*F33 -> 36.724645 | Y33: =(H33+M33+N33+O33+P33)/E33*G33 -> 0 | Z33: =Q33+R33+S33+T33+U33+V33+W33+X33+Y33 -> 1516.1268 | AA33: =1800*F33/E33 -> 116.12903 | AB33: 0 | AC33: =IF(Z33>20000,200,IF(Z33>15000,150,0)) -> 0 | AD33: 0 | AE33: =AA33+AB33+AC33+AD33 -> 116.12903 | AF33: =ROUND(Z33-AE33,0) -> 1400 | AG33: =AA33*13/12 -> 125.80645 | AH33: 1000 | AI33: =Z33+AG33+AH33 -> 2641.9332 | AJ33: =26472*(F33+G33)/E33 -> 1707.871 | AK33: =AJ33-AI33 -> -934.06226 | AL33: 21500
C34: BMS Technician | E34: =SUM(E30:E33) -> 124 | F34: =SUM(F30:F33) -> 92 | G34: =SUM(G30:G33) -> 0 | H34: =SUM(H30:H33) -> 77387 | I34: =SUM(I30:I33) -> 18888 | J34: =SUM(J30:J33) -> 54614 | K34: =SUM(K30:K33) -> 3885 | L34: =SUM(L30:L33) -> 0 | ... AL34: =SUM(AL30:AL33) -> 88100
A35: =A33+1 -> 27 | B35: 11907 | C35: P.SAI SATHISH | D35: DG OPERATOR | E35: 31 | F35: =VLOOKUP(B35,ATTENDANCE!$B$4:$AS$113,44,0) -> 31 | G35: 0 | H35: =I35+J35+K35+L35 -> 17835 | I35: 4722 | J35: 13113 | K35: 0 | L35: 0 | M35: =(I35+J35)*8.33% -> 1485.6555 | N35: =H35*4.93% -> 879.2655 | O35: =H35*3.29% -> 586.7715 | P35: =H35*2.88% -> 513.648 | Q35: =I35/E35*F35 -> 4722 | R35: =J35/E35*F35 -> 13113 | S35: =+K35/E35*F35 -> 0 | T35: =L35/E35*F35 -> 0 | U35: =M35/E35*F35 -> 1485.6555 | V35: =N35/E35*F35 -> 879.2655 | W35: =O35/E35*F35 -> 586.7715 | X35: =P35/E35*F35 -> 513.648 | Y35: =(H35+M35+N35+O35+P35)/E35*G35 -> 0 | Z35: =Q35+R35+S35+T35+U35+V35+W35+X35+Y35 -> 21300.341 | AA35: =1800*F35/E35 -> 1800 | AB35: 0 | AC35: =IF(Z35>20000,200,IF(Z35>15000,150,0)) -> 200 | AD35: 0 | AE35: =AA35+AB35+AC35+AD35 -> 2000 | AF35: =ROUND(Z35-AE35,0) -> 19300 | AG35: =AA35*13/12 -> 1950 | AH35: 1000 | AI35: =Z35+AG35+AH35 -> 24250.341 | AJ35: =26472*(F35+G35)/E35 -> 26472 | AK35: =AJ35-AI35 -> 2221.6595 | AL35: 19300
A36: =A35+1 -> 28 | B36: 11273 | C36: P CHANDRA SHEKAR PATRA | D36: DG OPERATOR | E36: 31 | F36: =VLOOKUP(B36,ATTENDANCE!$B$4:$AS$113,44,0) -> 31 | G36: 0 | H36: =I36+J36+K36+L36 -> 19765 | I36: 4722 | J36: 13778 | K36: 1265 | L36: 0 | M36: =(I36+J36)*8.33% -> 1541.05 | N36: =H36*4.93% -> 974.4145 | O36: =H36*3.29% -> 650.2685 | P36: =H36*2.88% -> 569.232 | Q36: =I36/E36*F36 -> 4722 | R36: =J36/E36*F36 -> 13778 | S36: =+K36/E36*F36 -> 1265 | T36: =L36/E36*F36 -> 0 | U36: =M36/E36*F36 -> 1541.05 | V36: =N36/E36*F36 -> 974.4145 | W36: =O36/E36*F36 -> 650.2685 | X36: =P36/E36*F36 -> 569.232 | Y36: =(H36+M36+N36+O36+P36)/E36*G36 -> 0 | Z36: =Q36+R36+S36+T36+U36+V36+W36+X36+Y36 -> 23499.965 | AA36: =1800*F36/E36 -> 1800 | AB36: 0 | AC36: =IF(Z36>20000,200,IF(Z36>15000,150,0)) -> 200 | AD36: 0 | AE36: =AA36+AB36+AC36+AD36 -> 2000 | AF36: =ROUND(Z36-AE36,0) -> 21500 | AG36: =AA36*13/12 -> 1950 | AH36: 1000 | AI36: =Z36+AG36+AH36 -> 26449.965 | AJ36: =26472*(F36+G36)/E36 -> 26472 | AK36: =AJ36-AI36 -> 22.035 | AL36: 21500
A37: =A36+1 -> 29 | B37: 11000 | C37: ALLAUDDIN MAINODDIN KHAJURE | D37: DG OPERATOR | E37: 31 | F37: =VLOOKUP(B37,ATTENDANCE!$B$4:$AS$113,44,0) -> 31 | G37: 0 | H37: =I37+J37+K37+L37 -> 23779.5 | I37: 4722 | J37: 13778 | K37: 5279.5 | L37: 0 | M37: =(I37+J37)*8.33% -> 1541.05 | N37: =H37*4.93% -> 1172.3293 | O37: =H37*3.29% -> 782.34555 | P37: =H37*2.88% -> 684.8496 | Q37: =I37/E37*F37 -> 4722 | R37: =J37/E37*F37 -> 13778 | S37: =+K37/E37*F37 -> 5279.5 | T37: =L37/E37*F37 -> 0 | U37: =M37/E37*F37 -> 1541.05 | V37: =N37/E37*F37 -> 1172.3293 | W37: =O37/E37*F37 -> 782.34555 | X37: =P37/E37*F37 -> 684.8496 | Y37: =(H37+M37+N37+O37+P37)/E37*G37 -> 0 | Z37: =Q37+R37+S37+T37+U37+V37+W37+X37+Y37 -> 27960.075 | AA37: =1800*F37/E37 -> 1800 | AB37: 0 | AC37: =IF(Z37>20000,200,IF(Z37>15000,150,0)) -> 200 | AD37: 0 | AE37: =AA37+AB37+AC37+AD37 -> 2000 | AF37: =ROUND(Z37-AE37,0) -> 25960 | AG37: =AA37*13/12 -> 1950 | AH37: 1000 | AI37: =Z37+AG37+AH37 -> 30910.075 | AJ37: =26472*(F37+G37)/E37 -> 26472 | AK37: =AJ37-AI37 -> -4438.0745 | AL37: 25960
A38: =A37+1 -> 30 | B38: 11551 | C38: RAUPYA PRAKASH | D38: DG OPERATOR | E38: 31 | F38: =VLOOKUP(B38,ATTENDANCE!$B$4:$AS$113,44,0) -> 31 | G38: 0 | H38: =I38+J38+K38+L38 -> 18775 | I38: 4722 | J38: 13778 | K38: 275 | L38: 0 | M38: =(I38+J38)*8.33% -> 1541.05 | N38: =H38*4.93% -> 925.6075 | O38: =H38*3.29% -> 617.6975 | P38: =H38*2.88% -> 540.72 | Q38: =I38/E38*F38 -> 4722 | R38: =J38/E38*F38 -> 13778 | S38: =+K38/E38*F38 -> 275 | T38: =L38/E38*F38 -> 0 | U38: =M38/E38*F38 -> 1541.05 | V38: =N38/E38*F38 -> 925.6075 | W38: =O38/E38*F38 -> 617.6975 | X38: =P38/E38*F38 -> 540.72 | Y38: =(H38+M38+N38+O38+P38)/E38*G38 -> 0 | Z38: =Q38+R38+S38+T38+U38+V38+W38+X38+Y38 -> 22400.075 | AA38: =1800*F38/E38 -> 1800 | AB38: 0 | AC38: =IF(Z38>20000,200,IF(Z38>15000,150,0)) -> 200 | AD38: 0 | AE38: =AA38+AB38+AC38+AD38 -> 2000 | AF38: =ROUND(Z38-AE38,0) -> 20400 | AG38: =AA38*13/12 -> 1950 | AH38: 1000 | AI38: =Z38+AG38+AH38 -> 25350.075 | AJ38: =26472*(F38+G38)/E38 -> 26472 | AK38: =AJ38-AI38 -> 1121.925 | AL38: 20400
C39: DG OPERATOR | E39: =SUM(E35:E38) -> 124 | F39: =SUM(F35:F38) -> 124 | G39: =SUM(G35:G38) -> 0 | H39: =SUM(H35:H38) -> 80154.5 | I39: =SUM(I35:I38) -> 18888 | J39: =SUM(J35:J38) -> 54447 | K39: =SUM(K35:K38) -> 6819.5 | L39: =SUM(L35:L38) -> 0 | ... AL39: =SUM(AL35:AL38) -> 87160
A40: =A38+1 -> 31 | B40: 10991 | C40: JOGENDRA SETHI | D40: HVAC OPERATOR | E40: 31 | F40: =VLOOKUP(B40,ATTENDANCE!$B$4:$AS$113,44,0) -> 31 | G40: 0 | H40: =I40+J40+K40+L40 -> 23815.4 | I40: 4722 | J40: 13778 | K40: 5315.4 | L40: 0 | M40: =(I40+J40)*8.33% -> 1541.05 | N40: =H40*4.93% -> 1174.0992 | O40: =H40*3.29% -> 783.52666 | P40: =H40*2.88% -> 685.88352 | Q40: =I40/E40*F40 -> 4722 | R40: =J40/E40*F40 -> 13778 | S40: =+K40/E40*F40 -> 5315.4 | T40: =L40/E40*F40 -> 0 | U40: =M40/E40*F40 -> 1541.05 | V40: =N40/E40*F40 -> 1174.0992 | W40: =O40/E40*F40 -> 783.52666 | X40: =P40/E40*F40 -> 685.88352 | Y40: =(H40+M40+N40+O40+P40)/E40*G40 -> 0 | Z40: =Q40+R40+S40+T40+U40+V40+W40+X40+Y40 -> 27999.959 | AA40: =1800*F40/E40 -> 1800 | AB40: 0 | AC40: =IF(Z40>20000,200,IF(Z40>15000,150,0)) -> 200 | AD40: 0 | AE40: =AA40+AB40+AC40+AD40 -> 2000 | AF40: =ROUND(Z40-AE40,0) -> 26000 | AG40: =AA40*13/12 -> 1950 | AH40: 1000 | AI40: =Z40+AG40+AH40 -> 30949.959 | AJ40: =26552*(F40+G40)/E40 -> 26552 | AK40: =AJ40-AI40 -> -4397.9594 | AL40: 26000
A41: =A40+1 -> 32 | B41: 11476 | C41: HARISH KHAN | D41: HVAC OPERATOR | E41: 31 | F41: =VLOOKUP(B41,ATTENDANCE!$B$4:$AS$113,44,0) -> 23 | G41: 0 | H41: =I41+J41+K41+L41 -> 19900 | I41: 4722 | J41: 13778 | K41: 1400 | L41: 0 | M41: =(I41+J41)*8.33% -> 1541.05 | N41: =H41*4.93% -> 981.07 | O41: =H41*3.29% -> 654.71 | P41: =H41*2.88% -> 573.12 | Q41: =I41/E41*F41 -> 3503.4194 | R41: =J41/E41*F41 -> 10222.387 | S41: =+K41/E41*F41 -> 1038.7097 | T41: =L41/E41*F41 -> 0 | U41: =M41/E41*F41 -> 1143.3597 | V41: =N41/E41*F41 -> 727.89065 | W41: =O41/E41*F41 -> 485.75258 | X41: =P41/E41*F41 -> 425.21806 | Y41: =(H41+M41+N41+O41+P41)/E41*G41 -> 0 | Z41: =Q41+R41+S41+T41+U41+V41+W41+X41+Y41 -> 17546.737 | AA41: =1800*F41/E41 -> 1335.4839 | AB41: 0 | AC41: =IF(Z41>20000,200,IF(Z41>15000,150,0)) -> 150 | AD41: 0 | AE41: =AA41+AB41+AC41+AD41 -> 1485.4839 | AF41: =ROUND(Z41-AE41,0) -> 16061 | AG41: =AA41*13/12 -> 1446.7742 | AH41: 1000 | AI41: =Z41+AG41+AH41 -> 19993.511 | AJ41: =26552*(F41+G41)/E41 -> 19699.871 | AK41: =AJ41-AI41 -> -293.64032 | AL41: 21650
A42: =A41+1 -> 33 | B42: 11954 | C42: AKASHSHA | D42: HVAC OPERATOR | E42: 31 | F42: =VLOOKUP(B42,ATTENDANCE!$B$4:$AS$113,44,0) -> 30 | G42: 0 | H42: =I42+J42+K42+L42 -> 18421 | I42: 4722 | J42: 13699 | K42: 0 | L42: 0 | M42: =(I42+J42)*8.33% -> 1534.4693 | N42: =H42*4.93% -> 908.1553 | O42: =H42*3.29% -> 606.0509 | P42: =H42*2.88% -> 530.5248 | Q42: =I42/E42*F42 -> 4569.6774 | R42: =J42/E42*F42 -> 13257.097 | S42: =+K42/E42*F42 -> 0 | T42: =L42/E42*F42 -> 0 | U42: =M42/E42*F42 -> 1484.9703 | V42: =N42/E42*F42 -> 878.85997 | W42: =O42/E42*F42 -> 586.50087 | X42: =P42/E42*F42 -> 513.4111 | Y42: =(H42+M42+N42+O42+P42)/E42*G42 -> 0 | Z42: =Q42+R42+S42+T42+U42+V42+W42+X42+Y42 -> 21290.516 | AA42: =1800*F42/E42 -> 1741.9355 | AB42: 0 | AC42: =IF(Z42>20000,200,IF(Z42>15000,150,0)) -> 200 | AD42: 0 | AE42: =AA42+AB42+AC42+AD42 -> 1941.9355 | AF42: =ROUND(Z42-AE42,0) -> 19349 | AG42: =AA42*13/12 -> 1887.0968 | AH42: 1000 | AI42: =Z42+AG42+AH42 -> 24177.613 | AJ42: =26552*(F42+G42)/E42 -> 25695.484 | AK42: =AJ42-AI42 -> 1517.8707 | AL42: 20000
A43: =A42+1 -> 34 | B43: 11749 | C43: SAJID HUSAIN | D43: HVAC OPERATOR | E43: 31 | F43: =VLOOKUP(B43,ATTENDANCE!$B$4:$AS$113,44,0) -> 31 | G43: 0 | H43: =I43+J43+K43+L43 -> 18865 | I43: 4722 | J43: 13778 | K43: 365 | L43: 0 | M43: =(I43+J43)*8.33% -> 1541.05 | N43: =H43*4.93% -> 930.0445 | O43: =H43*3.29% -> 620.6585 | P43: =H43*2.88% -> 543.312 | Q43: =I43/E43*F43 -> 4722 | R43: =J43/E43*F43 -> 13778 | S43: =+K43/E43*F43 -> 365 | T43: =L43/E43*F43 -> 0 | U43: =M43/E43*F43 -> 1541.05 | V43: =N43/E43*F43 -> 930.0445 | W43: =O43/E43*F43 -> 620.6585 | X43: =P43/E43*F43 -> 543.312 | Y43: =(H43+M43+N43+O43+P43)/E43*G43 -> 0 | Z43: =Q43+R43+S43+T43+U43+V43+W43+X43+Y43 -> 22500.065 | AA43: =1800*F43/E43 -> 1800 | AB43: 0 | AC43: =IF(Z43>20000,200,IF(Z43>15000,150,0)) -> 200 | AD43: 0 | AE43: =AA43+AB43+AC43+AD43 -> 2000 | AF43: =ROUND(Z43-AE43,0) -> 20500 | AG43: =AA43*13/12 -> 1950 | AH43: 1000 | AI43: =Z43+AG43+AH43 -> 25450.065 | AJ43: =26552*(F43+G43)/E43 -> 26552 | AK43: =AJ43-AI43 -> 1101.935 | AL43: 20500
A44: =A43+1 -> 35 | B44: 11862 | C44: MOHAMAD REHAN RAJE | D44: HVAC OPERATOR | E44: 31 | F44: =VLOOKUP(B44,ATTENDANCE!$B$4:$AS$113,44,0) -> 30 | G44: 0 | H44: =I44+J44+K44+L44 -> 18595 | I44: 4722 | J44: 13778 | K44: 95 | L44: 0 | M44: =(I44+J44)*8.33% -> 1541.05 | N44: =H44*4.93% -> 916.7335 | O44: =H44*3.29% -> 611.7755 | P44: =H44*2.88% -> 535.536 | Q44: =I44/E44*F44 -> 4569.6774 | R44: =J44/E44*F44 -> 13333.548 | S44: =+K44/E44*F44 -> 91.935484 | T44: =L44/E44*F44 -> 0 | U44: =M44/E44*F44 -> 1491.3387 | V44: =N44/E44*F44 -> 887.16145 | W44: =O44/E44*F44 -> 592.04081 | X44: =P44/E44*F44 -> 518.26065 | Y44: =(H44+M44+N44+O44+P44)/E44*G44 -> 0 | Z44: =Q44+R44+S44+T44+U44+V44+W44+X44+Y44 -> 21483.963 | AA44: =1800*F44/E44 -> 1741.9355 | AB44: 0 | AC44: =IF(Z44>20000,200,IF(Z44>15000,150,0)) -> 200 | AD44: 0 | AE44: =AA44+AB44+AC44+AD44 -> 1941.9355 | AF44: =ROUND(Z44-AE44,0) -> 19542 | AG44: =AA44*13/12 -> 1887.0968 | AH44: 1000 | AI44: =Z44+AG44+AH44 -> 24371.06 | AJ44: =26552*(F44+G44)/E44 -> 25695.484 | AK44: =AJ44-AI44 -> 1324.4242 | AL44: 20200
A45: =A44+1 -> 36 | B45: 11558 | C45: CHANDRA PRAKASH MOHANTY | D45: HVAC OPERATOR | E45: 31 | F45: =VLOOKUP(B45,ATTENDANCE!$B$4:$AS$113,44,0) -> 3 | G45: 0 | H45: =I45+J45+K45+L45 -> 19315 | I45: 4722 | J45: 13778 | K45: 815 | L45: 0 | M45: =(I45+J45)*8.33% -> 1541.05 | N45: =H45*4.93% -> 952.2295 | O45: =H45*3.29% -> 635.4635 | P45: =H45*2.88% -> 556.272 | Q45: =I45/E45*F45 -> 456.96774 | R45: =J45/E45*F45 -> 1333.3548 | S45: =+K45/E45*F45 -> 78.870968 | T45: =L45/E45*F45 -> 0 | U45: =M45/E45*F45 -> 149.13387 | V45: =N45/E45*F45 -> 92.151242 | W45: =O45/E45*F45 -> 61.496468 | X45: =P45/E45*F45 -> 53.832774 | Y45: =(H45+M45+N45+O45+P45)/E45*G45 -> 0 | Z45: =Q45+R45+S45+T45+U45+V45+W45+X45+Y45 -> 2225.8079 | AA45: =1800*F45/E45 -> 174.19355 | AB45: 0 | AC45: =IF(Z45>20000,200,IF(Z45>15000,150,0)) -> 0 | AD45: 0 | AE45: =AA45+AB45+AC45+AD45 -> 174.19355 | AF45: =ROUND(Z45-AE45,0) -> 2052 | AG45: =AA45*13/12 -> 188.70968 | AH45: 1000 | AI45: =Z45+AG45+AH45 -> 3414.5176 | AJ45: =26552*(F45+G45)/E45 -> 2569.5484 | AK45: =AJ45-AI45 -> -844.96919 | AL45: 21650
A46: =A45+1 -> 37 | B46: 9 | C46: MURALI KRUSHNA | D46: HVAC OPERATOR | E46: 31 | F46: =VLOOKUP(B46,ATTENDANCE!$B$4:$AS$113,44,0) -> 26 | G46: 0 | H46: =I46+J46+K46+L46 -> 17716 | I46: 4722 | J46: 12994 | K46: 0 | L46: 0 | M46: =(I46+J46)*8.33% -> 1475.7428 | N46: =H46*4.93% -> 873.3988 | O46: =H46*3.29% -> 582.8564 | P46: =H46*2.88% -> 510.2208 | Q46: =I46/E46*F46 -> 3960.3871 | R46: =J46/E46*F46 -> 10898.194 | S46: =+K46/E46*F46 -> 0 | T46: =L46/E46*F46 -> 0 | U46: =M46/E46*F46 -> 1237.7198 | V46: =N46/E46*F46 -> 732.52803 | W46: =O46/E46*F46 -> 488.8473 | X46: =P46/E46*F46 -> 427.92712 | Y46: =(H46+M46+N46+O46+P46)/E46*G46 -> 0 | Z46: =Q46+R46+S46+T46+U46+V46+W46+X46+Y46 -> 17745.603 | AA46: =1800*F46/E46 -> 1509.6774 | AB46: =Z46*0.75% -> 133.09202 | AC46: =IF(Z46>20000,200,IF(Z46>15000,150,0)) -> 150 | AD46: 0 | AE46: =AA46+AB46+AC46+AD46 -> 1792.7694 | AF46: =ROUND(Z46-AE46,0) -> 15953 | AG46: =AA46*13/12 -> 1635.4839 | AH46: =AB46*3.25/0.75 -> 576.73209 | AI46: =Z46+AG46+AH46 -> 19957.819 | AJ46: =26552*(F46+G46)/E46 -> 22269.419 | AK46: =AJ46-AI46 -> 2311.6005 | AL46: 21650
A47: =A46+1 -> 38 | B47: 10 | C47: RAMGIRI SATISH | D47: HVAC OPERATOR | E47: 31 | F47: =VLOOKUP(B47,ATTENDANCE!$B$4:$AS$113,44,0) -> 25 | G47: 0 | H47: =I47+J47+K47+L47 -> 17716 | I47: 4722 | J47: 12994 | K47: 0 | L47: 0 | M47: =(I47+J47)*8.33% -> 1475.7428 | N47: =H47*4.93% -> 873.3988 | O47: =H47*3.29% -> 582.8564 | P47: =H47*2.88% -> 510.2208 | Q47: =I47/E47*F47 -> 3808.0645 | R47: =J47/E47*F47 -> 10479.032 | S47: =+K47/E47*F47 -> 0 | T47: =L47/E47*F47 -> 0 | U47: =M47/E47*F47 -> 1190.1152 | V47: =N47/E47*F47 -> 704.35387 | W47: =O47/E47*F47 -> 470.04548 | X47: =P47/E47*F47 -> 411.46839 | Y47: =(H47+M47+N47+O47+P47)/E47*G47 -> 0 | Z47: =Q47+R47+S47+T47+U47+V47+W47+X47+Y47 -> 17063.08 | AA47: =1800*F47/E47 -> 1451.6129 | AB47: =Z47*0.75% -> 127.9731 | AC47: =IF(Z47>20000,200,IF(Z47>15000,150,0)) -> 150 | AD47: 0 | AE47: =AA47+AB47+AC47+AD47 -> 1729.586 | AF47: =ROUND(Z47-AE47,0) -> 15333 | AG47: =AA47*13/12 -> 1572.5806 | AH47: =AB47*3.25/0.75 -> 554.55009 | AI47: =Z47+AG47+AH47 -> 19190.21 | AJ47: =26552*(F47+G47)/E47 -> 21412.903 | AK47: =AJ47-AI47 -> 2222.6928 | AL47: 21650
A48: =A47+1 -> 39 | B48: 12035 | C48: SAMAR QUADIR | D48: HVAC OPERATOR | E48: 31 | F48: =VLOOKUP(B48,ATTENDANCE!$B$4:$AS$113,44,0) -> 31 | G48: 0 | H48: =I48+J48+K48+L48 -> 19315 | I48: 4722 | J48: 13778 | K48: 815 | L48: 0 | M48: =(I48+J48)*8.33% -> 1541.05 | N48: =H48*4.93% -> 952.2295 | O48: =H48*3.29% -> 635.4635 | P48: =H48*2.88% -> 556.272 | Q48: =I48/E48*F48 -> 4722 | R48: =J48/E48*F48 -> 13778 | S48: =+K48/E48*F48 -> 815 | T48: =L48/E48*F48 -> 0 | U48: =M48/E48*F48 -> 1541.05 | V48: =N48/E48*F48 -> 952.2295 | W48: =O48/E48*F48 -> 635.4635 | X48: =P48/E48*F48 -> 556.272 | Y48: =(H48+M48+N48+O48+P48)/E48*G48 -> 0 | Z48: =Q48+R48+S48+T48+U48+V48+W48+X48+Y48 -> 23000.015 | AA48: =1800*F48/E48 -> 1800 | AB48: 0 | AC48: =IF(Z48>20000,200,IF(Z48>15000,150,0)) -> 200 | AD48: 0 | AE48: =AA48+AB48+AC48+AD48 -> 2000 | AF48: =ROUND(Z48-AE48,0) -> 21000 | AG48: =AA48*13/12 -> 1950 | AH48: 1000 | AI48: =Z48+AG48+AH48 -> 25950.015 | AJ48: =26552*(F48+G48)/E48 -> 26552 | AK48: =AJ48-AI48 -> 601.985 | AL48: 21000
C49: HVAC Technician | E49: =SUM(E40:E48) -> 279 | F49: =SUM(F40:F48) -> 230 | G49: =SUM(G40:G48) -> 0 | H49: =SUM(H40:H48) -> 173658.4 | I49: =SUM(I40:I48) -> 42498 | J49: =SUM(J40:J48) -> 122355 | K49: =SUM(K40:K48) -> 8805.4 | L49: =SUM(L40:L48) -> 0 | ... AL49: =SUM(AL40:AL48) -> 194300
A50: =A48+1 -> 40 | B50: 10980 | C50: ANURUDHA SAMAL | D50: PLUMBER | E50: 31 | F50: =VLOOKUP(B50,ATTENDANCE!$B$4:$AS$113,44,0) -> 5 | G50: 0 | H50: =I50+J50+K50+L50 -> 24085.4 | I50: 4722 | J50: 13778 | K50: 5585.4 | L50: 0 | M50: =(I50+J50)*8.33% -> 1541.05 | N50: =H50*4.93% -> 1187.4102 | O50: =H50*3.29% -> 792.40966 | P50: =H50*2.88% -> 693.65952 | Q50: =I50/E50*F50 -> 761.6129 | R50: =J50/E50*F50 -> 2222.2581 | S50: =+K50/E50*F50 -> 900.87097 | T50: =L50/E50*F50 -> 0 | U50: =M50/E50*F50 -> 248.55645 | V50: =N50/E50*F50 -> 191.51778 | W50: =O50/E50*F50 -> 127.80801 | X50: =P50/E50*F50 -> 111.88057 | Y50: =(H50+M50+N50+O50+P50)/E50*G50 -> 0 | Z50: =Q50+R50+S50+T50+U50+V50+W50+X50+Y50 -> 4564.5047 | AA50: =1800*F50/E50 -> 290.32258 | AB50: 0 | AC50: =IF(Z50>20000,200,IF(Z50>15000,150,0)) -> 0 | AD50: 0 | AE50: =AA50+AB50+AC50+AD50 -> 290.32258 | AF50: =ROUND(Z50-AE50,0) -> 4274 | AG50: =AA50*13/12 -> 314.51613 | AH50: 1000 | AI50: =Z50+AG50+AH50 -> 5879.0209 | AJ50: =26959*(F50+G50)/E50 -> 4348.2258 | AK50: =AJ50-AI50 -> -1530.7951 | AL50: 26300
A51: =A50+1 -> 41 | B51: 10978 | C51: PABITRA MALIK | D51: PLUMBER | E51: 31 | F51: =VLOOKUP(B51,ATTENDANCE!$B$4:$AS$113,44,0) -> 31 | G51: 0 | H51: =I51+J51+K51+L51 -> 22015 | I51: 4722 | J51: 13778 | K51: 3515 | L51: 0 | M51: =(I51+J51)*8.33% -> 1541.05 | N51: =H51*4.93% -> 1085.3395 | O51: =H51*3.29% -> 724.2935 | P51: =H51*2.88% -> 634.032 | Q51: =I51/E51*F51 -> 4722 | R51: =J51/E51*F51 -> 13778 | S51: =+K51/E51*F51 -> 3515 | T51: =L51/E51*F51 -> 0 | U51: =M51/E51*F51 -> 1541.05 | V51: =N51/E51*F51 -> 1085.3395 | W51: =O51/E51*F51 -> 724.2935 | X51: =P51/E51*F51 -> 634.032 | Y51: =(H51+M51+N51+O51+P51)/E51*G51 -> 0 | Z51: =Q51+R51+S51+T51+U51+V51+W51+X51+Y51 -> 25999.715 | AA51: =1800*F51/E51 -> 1800 | AB51: 0 | AC51: =IF(Z51>20000,200,IF(Z51>15000,150,0)) -> 200 | AD51: 0 | AE51: =AA51+AB51+AC51+AD51 -> 2000 | AF51: =ROUND(Z51-AE51,0) -> 24000 | AG51: =AA51*13/12 -> 1950 | AH51: 1000 | AI51: =Z51+AG51+AH51 -> 28949.715 | AJ51: =26959*(F51+G51)/E51 -> 26959 | AK51: =AJ51-AI51 -> -1990.715 | AL51: 24000
A52: =A51+1 -> 42 | B52: 10974 | C52: GADADHAR MALIK | D52: PLUMBER | E52: 31 | F52: =VLOOKUP(B52,ATTENDANCE!$B$4:$AS$113,44,0) -> 31 | G52: 0 | H52: =I52+J52+K52+L52 -> 20305 | I52: 4722 | J52: 13778 | K52: 1805 | L52: 0 | M52: =(I52+J52)*8.33% -> 1541.05 | N52: =H52*4.93% -> 1001.0365 | O52: =H52*3.29% -> 668.0345 | P52: =H52*2.88% -> 584.784 | Q52: =I52/E52*F52 -> 4722 | R52: =J52/E52*F52 -> 13778 | S52: =+K52/E52*F52 -> 1805 | T52: =L52/E52*F52 -> 0 | U52: =M52/E52*F52 -> 1541.05 | V52: =N52/E52*F52 -> 1001.0365 | W52: =O52/E52*F52 -> 668.0345 | X52: =P52/E52*F52 -> 584.784 | Y52: =(H52+M52+N52+O52+P52)/E52*G52 -> 0 | Z52: =Q52+R52+S52+T52+U52+V52+W52+X52+Y52 -> 24099.905 | AA52: =1800*F52/E52 -> 1800 | AB52: 0 | AC52: =IF(Z52>20000,200,IF(Z52>15000,150,0)) -> 200 | AD52: 0 | AE52: =AA52+AB52+AC52+AD52 -> 2000 | AF52: =ROUND(Z52-AE52,0) -> 22100 | AG52: =AA52*13/12 -> 1950 | AH52: 1000 | AI52: =Z52+AG52+AH52 -> 27049.905 | AJ52: =26959*(F52+G52)/E52 -> 26959 | AK52: =AJ52-AI52 -> -90.905 | AL52: 22100
A53: =A52+1 -> 43 | B53: 11439 | C53: RAJA MALIK | D53: PLUMBER | E53: 31 | F53: =VLOOKUP(B53,ATTENDANCE!$B$4:$AS$113,44,0) -> 16 | G53: 0 | H53: =I53+J53+K53+L53 -> 18421 | I53: 4722 | J53: 13699 | K53: 0 | L53: 0 | M53: =(I53+J53)*8.33% -> 1534.4693 | N53: =H53*4.93% -> 908.1553 | O53: =H53*3.29% -> 606.0509 | P53: =H53*2.88% -> 530.5248 | Q53: =I53/E53*F53 -> 2437.1613 | R53: =J53/E53*F53 -> 7070.4516 | S53: =+K53/E53*F53 -> 0 | T53: =L53/E53*F53 -> 0 | U53: =M53/E53*F53 -> 791.98415 | V53: =N53/E53*F53 -> 468.72532 | W53: =O53/E53*F53 -> 312.80046 | X53: =P53/E53*F53 -> 273.81925 | Y53: =(H53+M53+N53+O53+P53)/E53*G53 -> 0 | Z53: =Q53+R53+S53+T53+U53+V53+W53+X53+Y53 -> 11354.942 | AA53: =1800*F53/E53 -> 929.03226 | AB53: 0 | AC53: =IF(Z53>20000,200,IF(Z53>15000,150,0)) -> 0 | AD53: 0 | AE53: =AA53+AB53+AC53+AD53 -> 929.03226 | AF53: =ROUND(Z53-AE53,0) -> 10426 | AG53: =AA53*13/12 -> 1006.4516 | AH53: 1000 | AI53: =Z53+AG53+AH53 -> 13361.394 | AJ53: =26959*(F53+G53)/E53 -> 13914.323 | AK53: =AJ53-AI53 -> 552.92888 | AL53: 20000
A54: =A53+1 -> 44 | B54: 10983 | C54: NEELAIAH GARI SUDHAKAR | D54: PLUMBER | E54: 31 | F54: =VLOOKUP(B54,ATTENDANCE!$B$4:$AS$113,44,0) -> 7 | G54: 0 | H54: =I54+J54+K54+L54 -> 19404 | I54: 4722 | J54: 13788 | K54: 894 | L54: 0 | M54: =(I54+J54)*8.33% -> 1541.883 | N54: =H54*4.93% -> 956.6172 | O54: =H54*3.29% -> 638.3916 | P54: =H54*2.88% -> 558.8352 | Q54: =I54/E54*F54 -> 1066.2581 | R54: =J54/E54*F54 -> 3113.4194 | S54: =+K54/E54*F54 -> 201.87097 | T54: =L54/E54*F54 -> 0 | U54: =M54/E54*F54 -> 348.16713 | V54: =N54/E54*F54 -> 216.01034 | W54: =O54/E54*F54 -> 144.15294 | X54: =P54/E54*F54 -> 126.18859 | Y54: =(H54+M54+N54+O54+P54)/E54*G54 -> 0 | Z54: =Q54+R54+S54+T54+U54+V54+W54+X54+Y54 -> 5216.0674 | AA54: =1800*F54/E54 -> 406.45161 | AB54: 0 | AC54: =IF(Z54>20000,200,IF(Z54>15000,150,0)) -> 0 | AD54: 0 | AE54: =AA54+AB54+AC54+AD54 -> 406.45161 | AF54: =ROUND(Z54-AE54,0) -> 4810 | AG54: =AA54*13/12 -> 440.32258 | AH54: 1000 | AI54: =Z54+AG54+AH54 -> 6656.39 | AJ54: =26959*(F54+G54)/E54 -> 6087.5161 | AK54: =AJ54-AI54 -> -568.87384 | AL54: 21100
A55: =A54+1 -> 45 | B55: 11158 | C55: NARESH DAS | D55: PLUMBER | E55: 31 | F55: =VLOOKUP(B55,ATTENDANCE!$B$4:$AS$113,44,0) -> 31 | G55: 0 | H55: =I55+J55+K55+L55 -> 19585 | I55: 4722 | J55: 13778 | K55: 1085 | L55: 0 | M55: =(I55+J55)*8.33% -> 1541.05 | N55: =H55*4.93% -> 965.5405 | O55: =H55*3.29% -> 644.3465 | P55: =H55*2.88% -> 564.048 | Q55: =I55/E55*F55 -> 4722 | R55: =J55/E55*F55 -> 13778 | S55: =+K55/E55*F55 -> 1085 | T55: =L55/E55*F55 -> 0 | U55: =M55/E55*F55 -> 1541.05 | V55: =N55/E55*F55 -> 965.5405 | W55: =O55/E55*F55 -> 644.3465 | X55: =P55/E55*F55 -> 564.048 | Y55: =(H55+M55+N55+O55+P55)/E55*G55 -> 0 | Z55: =Q55+R55+S55+T55+U55+V55+W55+X55+Y55 -> 23299.985 | AA55: =1800*F55/E55 -> 1800 | AB55: 0 | AC55: =IF(Z55>20000,200,IF(Z55>15000,150,0)) -> 200 | AD55: 0 | AE55: =AA55+AB55+AC55+AD55 -> 2000 | AF55: =ROUND(Z55-AE55,0) -> 21300 | AG55: =AA55*13/12 -> 1950 | AH55: 1000 | AI55: =Z55+AG55+AH55 -> 26249.985 | AJ55: =26959*(F55+G55)/E55 -> 26959 | AK55: =AJ55-AI55 -> 709.015 | AL55: 21300
A56: =A55+1 -> 46 | B56: 11203 | C56: BISWAJIT SAHOO | D56: PLUMBER | E56: 31 | F56: =VLOOKUP(B56,ATTENDANCE!$B$4:$AS$113,44,0) -> 23 | G56: 0 | H56: =I56+J56+K56+L56 -> 19315 | I56: 4722 | J56: 13778 | K56: 815 | L56: 0 | M56: =(I56+J56)*8.33% -> 1541.05 | N56: =H56*4.93% -> 952.2295 | O56: =H56*3.29% -> 635.4635 | P56: =H56*2.88% -> 556.272 | Q56: =I56/E56*F56 -> 3503.4194 | R56: =J56/E56*F56 -> 10222.387 | S56: =+K56/E56*F56 -> 604.67742 | T56: =L56/E56*F56 -> 0 | U56: =M56/E56*F56 -> 1143.3597 | V56: =N56/E56*F56 -> 706.49285 | W56: =O56/E56*F56 -> 471.47292 | X56: =P56/E56*F56 -> 412.71794 | Y56: =(H56+M56+N56+O56+P56)/E56*G56 -> 0 | Z56: =Q56+R56+S56+T56+U56+V56+W56+X56+Y56 -> 17064.527 | AA56: =1800*F56/E56 -> 1335.4839 | AB56: 0 | AC56: =IF(Z56>20000,200,IF(Z56>15000,150,0)) -> 150 | AD56: 0 | AE56: =AA56+AB56+AC56+AD56 -> 1485.4839 | AF56: =ROUND(Z56-AE56,0) -> 15579 | AG56: =AA56*13/12 -> 1446.7742 | AH56: 1000 | AI56: =Z56+AG56+AH56 -> 19511.301 | AJ56: =26959*(F56+G56)/E56 -> 20001.839 | AK56: =AJ56-AI56 -> 490.53726 | AL56: 21000
A57: =A56+1 -> 47 | B57: 12 | C57: Tapas Malik | D57: PLUMBER | E57: 31 | F57: =VLOOKUP(B57,ATTENDANCE!$B$4:$AS$113,44,0) -> 10 | G57: 0 | H57: =I57+J57+K57+L57 -> 18865 | I57: 4722 | J57: 13778 | K57: 365 | L57: 0 | M57: =(I57+J57)*8.33% -> 1541.05 | N57: =H57*4.93% -> 930.0445 | O57: =H57*3.29% -> 620.6585 | P57: =H57*2.88% -> 543.312 | Q57: =I57/E57*F57 -> 1523.2258 | R57: =J57/E57*F57 -> 4444.5161 | S57: =+K57/E57*F57 -> 117.74194 | T57: =L57/E57*F57 -> 0 | U57: =M57/E57*F57 -> 497.1129 | V57: =N57/E57*F57 -> 300.01435 | W57: =O57/E57*F57 -> 200.21242 | X57: =P57/E57*F57 -> 175.26194 | Y57: =(H57+M57+N57+O57+P57)/E57*G57 -> 0 | Z57: =Q57+R57+S57+T57+U57+V57+W57+X57+Y57 -> 7258.0855 | AA57: =1800*F57/E57 -> 580.64516 | AB57: 0 | AC57: =IF(Z57>20000,200,IF(Z57>15000,150,0)) -> 0 | AD57: 0 | AE57: =AA57+AB57+AC57+AD57 -> 580.64516 | AF57: =ROUND(Z57-AE57,0) -> 6677 | AG57: =AA57*13/12 -> 629.03226 | AH57: 1000 | AI57: =Z57+AG57+AH57 -> 8887.1177 | AJ57: =26959*(F57+G57)/E57 -> 8696.4516 | AK57: =AJ57-AI57 -> -190.66613 | AL57: 21500
A58: =A57+1 -> 48 | B58: 10985 | C58: SURYA PRAKASH ROUT | D58: PLUMBER | E58: 31 | F58: =VLOOKUP(B58,ATTENDANCE!$B$4:$AS$113,44,0) -> 3 | G58: 0 | H58: =I58+J58+K58+L58 -> 19315 | I58: 4722 | J58: 13778 | K58: 815 | L58: 0 | M58: =(I58+J58)*8.33% -> 1541.05 | N58: =H58*4.93% -> 952.2295 | O58: =H58*3.29% -> 635.4635 | P58: =H58*2.88% -> 556.272 | Q58: =I58/E58*F58 -> 456.96774 | R58: =J58/E58*F58 -> 1333.3548 | S58: =+K58/E58*F58 -> 78.870968 | T58: =L58/E58*F58 -> 0 | U58: =M58/E58*F58 -> 149.13387 | V58: =N58/E58*F58 -> 92.151242 | W58: =O58/E58*F58 -> 61.496468 | X58: =P58/E58*F58 -> 53.832774 | Y58: =(H58+M58+N58+O58+P58)/E58*G58 -> 0 | Z58: =Q58+R58+S58+T58+U58+V58+W58+X58+Y58 -> 2225.8079 | AA58: =1800*F58/E58 -> 174.19355 | AB58: 0 | AC58: =IF(Z58>20000,200,IF(Z58>15000,150,0)) -> 0 | AD58: 0 | AE58: =AA58+AB58+AC58+AD58 -> 174.19355 | AF58: =ROUND(Z58-AE58,0) -> 2052 | AG58: =AA58*13/12 -> 188.70968 | AH58: 1000 | AI58: =Z58+AG58+AH58 -> 3414.5176 | AJ58: =26959*(F58+G58)/E58 -> 2608.9355 | AK58: =AJ58-AI58 -> -805.5821 | AL58: 21500
A59: =A58+1 -> 49 | B59: 11276 | C59: GOPAL ROUT | D59: PLUMBER | E59: 31 | F59: =VLOOKUP(B59,ATTENDANCE!$B$4:$AS$113,44,0) -> 31 | G59: 0 | H59: =I59+J59+K59+L59 -> 20575 | I59: 4722 | J59: 13778 | K59: 2075 | L59: 0 | M59: =(I59+J59)*8.33% -> 1541.05 | N59: =H59*4.93% -> 1014.3475 | O59: =H59*3.29% -> 676.9175 | P59: =H59*2.88% -> 592.56 | Q59: =I59/E59*F59 -> 4722 | R59: =J59/E59*F59 -> 13778 | S59: =+K59/E59*F59 -> 2075 | T59: =L59/E59*F59 -> 0 | U59: =M59/E59*F59 -> 1541.05 | V59: =N59/E59*F59 -> 1014.3475 | W59: =O59/E59*F59 -> 676.9175 | X59: =P59/E59*F59 -> 592.56 | Y59: =(H59+M59+N59+O59+P59)/E59*G59 -> 0 | Z59: =Q59+R59+S59+T59+U59+V59+W59+X59+Y59 -> 24399.875 | AA59: =1800*F59/E59 -> 1800 | AB59: 0 | AC59: =IF(Z59>20000,200,IF(Z59>15000,150,0)) -> 200 | AD59: 0 | AE59: =AA59+AB59+AC59+AD59 -> 2000 | AF59: =ROUND(Z59-AE59,0) -> 22400 | AG59: =AA59*13/12 -> 1950 | AH59: 1000 | AI59: =Z59+AG59+AH59 -> 27349.875 | AJ59: =26959*(F59+G59)/E59 -> 26959 | AK59: =AJ59-AI59 -> -390.875 | AL59: 22400
C60: Plumber | E60: =SUM(E50:E59) -> 310 | F60: =SUM(F50:F59) -> 188 | G60: =SUM(G50:G59) -> 0 | H60: =SUM(H50:H59) -> 201885.4 | I60: =SUM(I50:I59) -> 47220 | J60: =SUM(J50:J59) -> 137711 | K60: =SUM(K50:K59) -> 16954.4 | L60: =SUM(L50:L59) -> 0 | ... AL60: =SUM(AL50:AL59) -> 221200
A61: =A59+1 -> 50 | B61: 11572 | C61: KALLOL SEN | D61: PAINTER | E61: 31 | F61: =VLOOKUP(B61,ATTENDANCE!$B$4:$AS$113,44,0) -> 31 | G61: 0 | H61: =I61+J61+K61+L61 -> 20386 | I61: 4722 | J61: 13778 | K61: 1886 | L61: 0 | M61: =(I61+J61)*8.33% -> 1541.05 | N61: =H61*4.93% -> 1005.0298 | O61: =H61*3.29% -> 670.6994 | P61: =H61*2.88% -> 587.1168 | Q61: =I61/E61*F61 -> 4722 | R61: =J61/E61*F61 -> 13778 | S61: =+K61/E61*F61 -> 1886 | T61: =L61/E61*F61 -> 0 | U61: =M61/E61*F61 -> 1541.05 | V61: =N61/E61*F61 -> 1005.0298 | W61: =O61/E61*F61 -> 670.6994 | X61: =P61/E61*F61 -> 587.1168 | Y61: =(H61+M61+N61+O61+P61)/E61*G61 -> 0 | Z61: =Q61+R61+S61+T61+U61+V61+W61+X61+Y61 -> 24189.896 | AA61: =1800*F61/E61 -> 1800 | AB61: 0 | AC61: =IF(Z61>20000,200,IF(Z61>15000,150,0)) -> 200 | AD61: 0 | AE61: =AA61+AB61+AC61+AD61 -> 2000 | AF61: =ROUND(Z61-AE61,0) -> 22190 | AG61: =AA61*13/12 -> 1950 | AH61: 1000 | AI61: =Z61+AG61+AH61 -> 27139.896 | AJ61: =27140*(F61+G61)/E61 -> 27140 | AK61: =AJ61-AI61 -> 0.104 | AL61: 22190
C62: PAINTER | E62: =SUM(E61) -> 31 | F62: =SUM(F61) -> 31 | G62: =SUM(G61) -> 0 | H62: =SUM(H61) -> 20386 | I62: =SUM(I61) -> 4722 | J62: =SUM(J61) -> 13778 | K62: =SUM(K61) -> 1886 | L62: =SUM(L61) -> 0 | ... AL62: =SUM(AL61) -> 22190
A63: =A61+1 -> 51 | B63: 11214 | C63: M.LAXMINARAYANA | D63: MASON | E63: 31 | F63: =VLOOKUP(B63,ATTENDANCE!$B$4:$AS$113,44,0) -> 31 | G63: 0 | H63: =I63+J63+K63+L63 -> 20386 | I63: 4722 | J63: 13778 | K63: 1886 | L63: 0 | M63: =(I63+J63)*8.33% -> 1541.05 | N63: =H63*4.93% -> 1005.0298 | O63: =H63*3.29% -> 670.6994 | P63: =H63*2.88% -> 587.1168 | Q63: =I63/E63*F63 -> 4722 | R63: =J63/E63*F63 -> 13778 | S63: =+K63/E63*F63 -> 1886 | T63: =L63/E63*F63 -> 0 | U63: =M63/E63*F63 -> 1541.05 | V63: =N63/E63*F63 -> 1005.0298 | W63: =O63/E63*F63 -> 670.6994 | X63: =P63/E63*F63 -> 587.1168 | Y63: =(H63+M63+N63+O63+P63)/E63*G63 -> 0 | Z63: =Q63+R63+S63+T63+U63+V63+W63+X63+Y63 -> 24189.896 | AA63: =1800*F63/E63 -> 1800 | AB63: 0 | AC63: =IF(Z63>20000,200,IF(Z63>15000,150,0)) -> 200 | AD63: 0 | AE63: =AA63+AB63+AC63+AD63 -> 2000 | AF63: =ROUND(Z63-AE63,0) -> 22190 | AG63: =AA63*13/12 -> 1950 | AH63: 1000 | AI63: =Z63+AG63+AH63 -> 27139.896 | AJ63: =27140*(F63+G63)/E63 -> 27140 | AK63: =AJ63-AI63 -> 0.104 | AL63: 22458
C64: Mason | E64: =SUM(E63) -> 31 | F64: =SUM(F63) -> 31 | G64: =SUM(G63) -> 0 | H64: =SUM(H63) -> 20386 | I64: =SUM(I63) -> 4722 | J64: =SUM(J63) -> 13778 | K64: =SUM(K63) -> 1886 | L64: =SUM(L63) -> 0 | ... AL64: =SUM(AL63) -> 22458
A65: =A63+1 -> 52 | B65: 11640 | C65: BODESH | D65: WELDER | E65: 31 | F65: =VLOOKUP(B65,ATTENDANCE!$B$4:$AS$113,44,0) -> 31 | G65: 0 | H65: =I65+J65+K65+L65 -> 19315 | I65: 4722 | J65: 13778 | K65: 815 | L65: 0 | M65: =(I65+J65)*8.33% -> 1541.05 | N65: =H65*4.93% -> 952.2295 | O65: =H65*3.29% -> 635.4635 | P65: =H65*2.88% -> 556.272 | Q65: =I65/E65*F65 -> 4722 | R65: =J65/E65*F65 -> 13778 | S65: =+K65/E65*F65 -> 815 | T65: =L65/E65*F65 -> 0 | U65: =M65/E65*F65 -> 1541.05 | V65: =N65/E65*F65 -> 952.2295 | W65: =O65/E65*F65 -> 635.4635 | X65: =P65/E65*F65 -> 556.272 | Y65: =(H65+M65+N65+O65+P65)/E65*G65 -> 0 | Z65: =Q65+R65+S65+T65+U65+V65+W65+X65+Y65 -> 23000.015 | AA65: =1800*F65/E65 -> 1800 | AB65: 0 | AC65: =IF(Z65>20000,200,IF(Z65>15000,150,0)) -> 200 | AD65: 0 | AE65: =AA65+AB65+AC65+AD65 -> 2000 | AF65: =ROUND(Z65-AE65,0) -> 21000 | AG65: =AA65*13/12 -> 1950 | AH65: 1000 | AI65: =Z65+AG65+AH65 -> 25950.015 | AJ65: =27140*(F65+G65)/E65 -> 27140 | AK65: =AJ65-AI65 -> 1189.985 | AL65: 21000
C66: WELDER | E66: =SUM(E65) -> 31 | F66: =SUM(F65) -> 31 | G66: =SUM(G65) -> 0 | H66: =SUM(H65) -> 19315 | I66: =SUM(I65) -> 4722 | J66: =SUM(J65) -> 13778 | K66: =SUM(K65) -> 815 | L66: =SUM(L65) -> 0 | ... AL66: =SUM(AL65) -> 21000
A67: =A65+1 -> 53 | B67: 12141 | C67: BANDARI DHAN RAJ | D67: Carpenter | E67: 31 | F67: =VLOOKUP(B67,ATTENDANCE!$B$4:$AS$113,44,0) -> 26 | G67: 0 | H67: =I67+J67+K67+L67 -> 21115 | I67: 4722 | J67: 13778 | K67: 2615 | L67: 0 | M67: =(I67+J67)*8.33% -> 1541.05 | N67: =H67*4.93% -> 1040.9695 | O67: =H67*3.29% -> 694.6835 | P67: =H67*2.88% -> 608.112 | Q67: =I67/E67*F67 -> 3960.3871 | R67: =J67/E67*F67 -> 11555.742 | S67: =+K67/E67*F67 -> 2193.2258 | T67: =L67/E67*F67 -> 0 | U67: =M67/E67*F67 -> 1292.4935 | V67: =N67/E67*F67 -> 873.07119 | W67: =O67/E67*F67 -> 582.63777 | X67: =P67/E67*F67 -> 510.02942 | Y67: =(H67+M67+N67+O67+P67)/E67*G67 -> 0 | Z67: =Q67+R67+S67+T67+U67+V67+W67+X67+Y67 -> 20967.587 | AA67: =1800*F67/E67 -> 1509.6774 | AB67: 0 | AC67: =IF(Z67>20000,200,IF(Z67>15000,150,0)) -> 200 | AD67: 0 | AE67: =AA67+AB67+AC67+AD67 -> 1709.6774 | AF67: =ROUND(Z67-AE67,0) -> 19258 | AG67: =AA67*13/12 -> 1635.4839 | AH67: 1000 | AI67: =Z67+AG67+AH67 -> 23603.071 | AJ67: =26959*(F67+G67)/E67 -> 22610.774 | AK67: =AJ67-AI67 -> -992.29645 | AL67: 23000
C68: Carpenter | E68: =SUM(E67) -> 31 | F68: =SUM(F67) -> 26 | G68: =SUM(G67) -> 0 | H68: =SUM(H67) -> 21115 | I68: =SUM(I67) -> 4722 | J68: =SUM(J67) -> 13778 | K68: =SUM(K67) -> 2615 | L68: =SUM(L67) -> 0 | ... AL68: =SUM(AL67) -> 23000
A69: =A67+1 -> 54 | B69: 12057 | C69: GALLI KIRAN KUMAR | D69: FIRE TECHNICIAN | E69: 31 | F69: =VLOOKUP(B69,ATTENDANCE!$B$4:$AS$113,44,0) -> 31 | G69: 0 | H69: =I69+J69+K69+L69 -> 20386 | I69: 4722 | J69: 13778 | K69: 1886 | L69: 0 | M69: =(I69+J69)*8.33% -> 1541.05 | N69: =H69*4.93% -> 1005.0298 | O69: =H69*3.29% -> 670.6994 | P69: =H69*2.88% -> 587.1168 | Q69: =I69/E69*F69 -> 4722 | R69: =J69/E69*F69 -> 13778 | S69: =+K69/E69*F69 -> 1886 | T69: =L69/E69*F69 -> 0 | U69: =M69/E69*F69 -> 1541.05 | V69: =N69/E69*F69 -> 1005.0298 | W69: =O69/E69*F69 -> 670.6994 | X69: =P69/E69*F69 -> 587.1168 | Y69: =(H69+M69+N69+O69+P69)/E69*G69 -> 0 | Z69: =Q69+R69+S69+T69+U69+V69+W69+X69+Y69 -> 24189.896 | AA69: =1800*F69/E69 -> 1800 | AB69: 0 | AC69: =IF(Z69>20000,200,IF(Z69>15000,150,0)) -> 200 | AD69: 0 | AE69: =AA69+AB69+AC69+AD69 -> 2000 | AF69: =ROUND(Z69-AE69,0) -> 22190 | AG69: =AA69*13/12 -> 1950 | AH69: 1000 | AI69: =Z69+AG69+AH69 -> 27139.896 | AJ69: =27140*(F69+G69)/E69 -> 27140 | AK69: =AJ69-AI69 -> 0.104 | AL69: 20000
C70: Fire Technician | E70: =SUM(E69:E69) -> 31 | F70: =SUM(F69:F69) -> 31 | G70: =SUM(G69:G69) -> 0 | H70: =SUM(H69:H69) -> 20386 | I70: =SUM(I69:I69) -> 4722 | J70: =SUM(J69:J69) -> 13778 | K70: =SUM(K69:K69) -> 1886 | L70: =SUM(L69:L69) -> 0 | ... AL70: =SUM(AL69:AL69) -> 20000
E71: =E6+E15+E29+E34+E39+E49+E60+E62+E64+E70+E66+E68 -> 1674 | F71: =F6+F15+F29+F34+F39+F49+F60+F62+F64+F70+F66+F68 -> 1315 | G71: =G6+G15+G29+G34+G39+G49+G60+G62+G64+G70+G66+G68 -> 0 | H71: =H6+H15+H29+H34+H39+H49+H60+H62+H64+H70+H66+H68 -> 1104384.5 | I71: =I6+I15+I29+I34+I39+I49+I60+I62+I64+I70+I66+I68 -> 255823 | J71: =J6+J15+J29+J34+J39+J49+J60+J62+J64+J70+J66+J68 -> 736152 | K71: =K6+K15+K29+K34+K39+K49+K60+K62+K64+K70+K66+K68 -> 107089.5 | L71: =L6+L15+L29+L34+L39+L49+L60+L62+L64+L70+L66+L68 -> 5320 | ... AL71: =AL6+AL15+AL29+AL34+AL39+AL49+AL60+AL62+AL64+AL70+AL66+AL68 -> 1232708
V77: =Z4 -> GROSS EARNINGS | Y77: = | Z77: =Z71 -> 1038916
V78: EMPLOYER PF @13% | Y78: = | Z78: =AG71 -> 82717.742
V79: EMPLOYER ESI @3.25% | Y79: = | Z79: =AH71 -> 49480.765
V80: TOTAL COST | Y80: = | Z80: =SUM(Z77:Z79) -> 1171114.6 | AA80: =Z80-AI71 -> 0
V81: MANAGEMENT FEE 8% | Y81: = | Z81: =Z80*8% -> 93689.164
V82: GRAND TOTAL | Y82: = | Z82: =Z80+Z81 -> 1264803.7

Sheet FULL
AB2: grooming deduction
A3: MIDAS-B1&B2 FOR THE MONTH OF APR 2025 | H3: ACTUAL COMPONENTS | P3: EARNING COMPONENTS | Y3: DEDUCTIONS
A4: S.NO | B4: EMP CODE | C4: EMPLOYEE NAME | D4: Designation | E4: ACTUAL DAYS | F4: NET PAID DAYS | G4: EXTRA DEPLOYMENT | H4: GROSS SALARY | I4: BASIC | J4: DA | K4: OTHER ALLOWANCE | L4: Bonus 8.33% (Basic + DA) | M4: Leave Wage (EL @ 18days) 4.93% | N4: Leave Wage (CL @ 12days) 3.29% | O4: National Holiday and Festival Holidays 10 days @2.88% | P4: BASIC | Q4: DA | R4: OTHER ALLOWANCE | S4: Bonus 8.33% (Basic + DA) | T4: Leave Wage (EL @ 18days) 4.93% | U4: Leave Wage (CL @ 12days) 3.29% | V4: National Holiday and Festival Holidays 10 days @2.88% | W4: Extra Deployment Amount | X4: GROSS EARNINGS | Y4: EMPLOYEE PF@12% | Z4: EMPLOYEE ESI@0.75% | AA4: PROFESSION TAX | AB4: Advances | AC4: TOTAL DEDUCTIONS | AD4: NET PAY | AE4: EMPLOYER PF@13% | AF4: EMPLOYER ESI @3.25% / INSURANCE | AG4: CTC
A5: 1 | B5: 11029 | C5: SUDHIR KUMAR RAUTARAY | D5: TECHNICAL EXECUTIVE | E5: 30 | F5: 30 | G5: 0 | H5: =I5+J5+K5 -> 30365 | I5: 5557 | J5: 9050 | K5: 15758 | L5: =(I5+J5)*8.33% -> 1216.7631 | M5: =H5*4.93% -> 1496.9945 | N5: =H5*3.29% -> 999.0085 | O5: =H5*2.88% -> 874.512 | P5: =I5/E5*F5 -> 5557 | Q5: =J5/E5*F5 -> 9050 | R5: =K5/E5*F5 -> 15758 | S5: =L5/E5*F5 -> 1216.7631 | T5: =M5/E5*F5 -> 1496.9945 | U5: =N5/E5*F5 -> 999.0085 | V5: =O5/E5*F5 -> 874.512 | W5: =(H5+L5+M5+N5+O5)/E5*G5 -> 0 | X5: =P5+Q5+R5+S5+T5+U5+V5+W5 -> 34952.278 | Y5: =(P5+Q5)*12% -> 1752.84 | Z5: 0 | AA5: =IF(X5>20000,200,IF(X5>15000,150,0)) -> 200 | AC5: =Y5+Z5+AA5+AB5 -> 1952.84 | AD5: =ROUND(X5-AC5,0) -> 32999 | AE5: =(P5+Q5)*13% -> 1898.91 | AF5: 800 | AG5: =X5+AE5+AF5 -> 37651.188 | AH5: 36834
C6: TECHNICAL EXECUTIVE | E6: =SUM(E5) -> 30 | F6: =SUM(F5) -> 30 | G6: =SUM(G5) -> 0 | H6: =SUM(H5) -> 30365 | I6: =SUM(I5) -> 5557 | J6: =SUM(J5) -> 9050 | K6: =SUM(K5) -> 15758 | L6: =SUM(L5) -> 1216.7631 | ... AH6: =SUM(AH5) -> 36834 | AI6: =AH6-AG6 -> -817.1881
A7: 2 | B7: 10984 | C7: K.RAJYALAKSHMI | D7: TECHNICAL SUPERVISOR | E7: 30 | F7: 30 | G7: 0 | H7: =I7+J7+K7 -> 22687 | I7: 4722 | J7: 9050 | K7: 8915 | L7: =(I7+J7)*8.33% -> 1147.2076 | M7: =H7*4.93% -> 1118.4691 | N7: =H7*3.29% -> 746.4023 | O7: =H7*2.88% -> 653.3856 | P7: =I7/E7*F7 -> 4722 | Q7: =J7/E7*F7 -> 9050 | R7: =K7/E7*F7 -> 8915 | S7: =L7/E7*F7 -> 1147.2076 | T7: =M7/E7*F7 -> 1118.4691 | U7: =N7/E7*F7 -> 746.4023 | V7: =O7/E7*F7 -> 653.3856 | W7: =(H7+L7+M7+N7+O7)/E7*G7 -> 0 | X7: =P7+Q7+R7+S7+T7+U7+V7+W7 -> 26352.465 | Y7: =(P7+Q7)*12% -> 1652.64 | Z7: 0 | AA7: =IF(X7>20000,200,IF(X7>15000,150,0)) -> 200 | AC7: =Y7+Z7+AA7+AB7 -> 1852.64 | AD7: =ROUND(X7-AC7,0) -> 24500 | AE7: =(P7+Q7)*13% -> 1790.36 | AF7: 800 | AG7: =X7+AE7+AF7 -> 28942.825 | AH7: 28930 | AI7: =AH7-AG7 -> -12.8246
A8: =A7+1 -> 3 | B8: 10986 | C8: KHIROD DAS | D8: TECHNICAL SUPERVISOR | E8: 30 | F8: 30 | G8: 0 | H8: =I8+J8+K8 -> 23896 | I8: 4722 | J8: 9050 | K8: 10124 | L8: =(I8+J8)*8.33% -> 1147.2076 | M8: =H8*4.93% -> 1178.0728 | N8: =H8*3.29% -> 786.1784 | O8: =H8*2.88% -> 688.2048 | P8: =I8/E8*F8 -> 4722 | Q8: =J8/E8*F8 -> 9050 | R8: =K8/E8*F8 -> 10124 | S8: =L8/E8*F8 -> 1147.2076 | T8: =M8/E8*F8 -> 1178.0728 | U8: =N8/E8*F8 -> 786.1784 | V8: =O8/E8*F8 -> 688.2048 | W8: =(H8+L8+M8+N8+O8)/E8*G8 -> 0 | X8: =P8+Q8+R8+S8+T8+U8+V8+W8 -> 27695.664 | Y8: =(P8+Q8)*12% -> 1652.64 | Z8: 0 | AA8: =IF(X8>20000,200,IF(X8>15000,150,0)) -> 200 | AC8: =Y8+Z8+AA8+AB8 -> 1852.64 | AD8: =ROUND(X8-AC8,0) -> 25843 | AE8: =(P8+Q8)*13% -> 1790.36 | AF8: 800 | AG8: =X8+AE8+AF8 -> 30286.024 | AH8: 28930 | AI8: =AH8-AG8 -> -1356.0236
A9: =A8+1 -> 4 | B9: 10989 | C9: NAGENDRA | D9: TECHNICAL SUPERVISOR | E9: 30 | F9: 30 | G9: 0 | H9: =I9+J9+K9 -> 22417 | I9: 4722 | J9: 9050 | K9: 8645 | L9: =(I9+J9)*8.33% -> 1147.2076 | M9: =H9*4.93% -> 1105.1581 | N9: =H9*3.29% -> 737.5193 | O9: =H9*2.88% -> 645.6096 | P9: =I9/E9*F9 -> 4722 | Q9: =J9/E9*F9 -> 9050 | R9: =K9/E9*F9 -> 8645 | S9: =L9/E9*F9 -> 1147.2076 | T9: =M9/E9*F9 -> 1105.1581 | U9: =N9/E9*F9 -> 737.5193 | V9: =O9/E9*F9 -> 645.6096 | W9: =(H9+L9+M9+N9+O9)/E9*G9 -> 0 | X9: =P9+Q9+R9+S9+T9+U9+V9+W9 -> 26052.495 | Y9: =(P9+Q9)*12% -> 1652.64 | Z9: 0 | AA9: =IF(X9>20000,200,IF(X9>15000,150,0)) -> 200 | AC9: =Y9+Z9+AA9+AB9 -> 1852.64 | AD9: =ROUND(X9-AC9,0) -> 24200 | AE9: =(P9+Q9)*13% -> 1790.36 | AF9: 800 | AG9: =X9+AE9+AF9 -> 28642.855 | AH9: 28930 | AI9: =AH9-AG9 -> 287.1454
A10: =A9+1 -> 5 | B10: 10988 | C10: KAKARLA BASHA | D10: TECHNICAL SUPERVISOR | E10: 30 | F10: 30 | G10: 0 | H10: =I10+J10+K10 -> 22417 | I10: 4722 | J10: 9050 | K10: 8645 | L10: =(I10+J10)*8.33% -> 1147.2076 | M10: =H10*4.93% -> 1105.1581 | N10: =H10*3.29% -> 737.5193 | O10: =H10*2.88% -> 645.6096 | P10: =I10/E10*F10 -> 4722 | Q10: =J10/E10*F10 -> 9050 | R10: =K10/E10*F10 -> 8645 | S10: =L10/E10*F10 -> 1147.2076 | T10: =M10/E10*F10 -> 1105.1581 | U10: =N10/E10*F10 -> 737.5193 | V10: =O10/E10*F10 -> 645.6096 | W10: =(H10+L10+M10+N10+O10)/E10*G10 -> 0 | X10: =P10+Q10+R10+S10+T10+U10+V10+W10 -> 26052.495 | Y10: =(P10+Q10)*12% -> 1652.64 | Z10: 0 | AA10: =IF(X10>20000,200,IF(X10>15000,150,0)) -> 200 | AC10: =Y10+Z10+AA10+AB10 -> 1852.64 | AD10: =ROUND(X10-AC10,0) -> 24200 | AE10: =(P10+Q10)*13% -> 1790.36 | AF10: 800 | AG10: =X10+AE10+AF10 -> 28642.855 | AH10: 28930 | AI10: =AH10-AG10 -> 287.1454
A11: =A10+1 -> 6 | B11: 11215 | C11: K.RAMESH | D11: TECHNICAL SUPERVISOR | E11: 30 | F11: 30 | G11: 0 | H11: =I11+J11+K11 -> 21787 | I11: 4722 | J11: 9050 | K11: 8015 | L11: =(I11+J11)*8.33% -> 1147.2076 | M11: =H11*4.93% -> 1074.0991 | N11: =H11*3.29% -> 716.7923 | O11: =H11*2.88% -> 627.4656 | P11: =I11/E11*F11 -> 4722 | Q11: =J11/E11*F11 -> 9050 | R11: =K11/E11*F11 -> 8015 | S11: =L11/E11*F11 -> 1147.2076 | T11: =M11/E11*F11 -> 1074.0991 | U11: =N11/E11*F11 -> 716.7923 | V11: =O11/E11*F11 -> 627.4656 | W11: =(H11+L11+M11+N11+O11)/E11*G11 -> 0 | X11: =P11+Q11+R11+S11+T11+U11+V11+W11 -> 25352.565 | Y11: =(P11+Q11)*12% -> 1652.64 | Z11: 0 | AA11: =IF(X11>20000,200,IF(X11>15000,150,0)) -> 200 | AC11: =Y11+Z11+AA11+AB11 -> 1852.64 | AD11: =ROUND(X11-AC11,0) -> 23500 | AE11: =(P11+Q11)*13% -> 1790.36 | AF11: 800 | AG11: =X11+AE11+AF11 -> 27942.925 | AH11: 28930 | AI11: =AH11-AG11 -> 987.0754
A12: =A11+1 -> 7 | B12: 10976 | C12: KONGANI NARAYANA | D12: TECHNICAL SUPERVISOR | E12: 30 | F12: 30 | G12: 0 | H12: =I12+J12+K12 -> 22867 | I12: 4722 | J12: 9050 | K12: 9095 | L12: =(I12+J12)*8.33% -> 1147.2076 | M12: =H12*4.93% -> 1127.3431 | N12: =H12*3.29% -> 752.3243 | O12: =H12*2.88% -> 658.5696 | P12: =I12/E12*F12 -> 4722 | Q12: =J12/E12*F12 -> 9050 | R12: =K12/E12*F12 -> 9095 | S12: =L12/E12*F12 -> 1147.2076 | T12: =M12/E12*F12 -> 1127.3431 | U12: =N12/E12*F12 -> 752.3243 | V12: =O12/E12*F12 -> 658.5696 | W12: =(H12+L12+M12+N12+O12)/E12*G12 -> 0 | X12: =P12+Q12+R12+S12+T12+U12+V12+W12 -> 26552.445 | Y12: =(P12+Q12)*12% -> 1652.64 | Z12: 0 | AA12: =IF(X12>20000,200,IF(X12>15000,150,0)) -> 200 | AC12: =Y12+Z12+AA12+AB12 -> 1852.64 | AD12: =ROUND(X12-AC12,0) -> 24700 | AE12: =(P12+Q12)*13% -> 1790.36 | AF12: 800 | AG12: =X12+AE12+AF12 -> 29142.805 | AH12: 28930 | AI12: =AH12-AG12 -> -212.8046
A13: =A12+1 -> 8 | B13: 10312 | C13: T.BALAJI | D13: TECHNICAL SUPERVISOR | E13: 30 | F13: 30 | G13: 0 | H13: =I13+J13+K13 -> 22777 | I13: 4722 | J13: 9050 | K13: 9005 | L13: =(I13+J13)*8.33% -> 1147.2076 | M13: =H13*4.93% -> 1122.9061 | N13: =H13*3.29% -> 749.3633 | O13: =H13*2.88% -> 655.9776 | P13: =I13/E13*F13 -> 4722 | Q13: =J13/E13*F13 -> 9050 | R13: =K13/E13*F13 -> 9005 | S13: =L13/E13*F13 -> 1147.2076 | T13: =M13/E13*F13 -> 1122.9061 | U13: =N13/E13*F13 -> 749.3633 | V13: =O13/E13*F13 -> 655.9776 | W13: =(H13+L13+M13+N13+O13)/E13*G13 -> 0 | X13: =P13+Q13+R13+S13+T13+U13+V13+W13 -> 26452.455 | Y13: =(P13+Q13)*12% -> 1652.64 | Z13: 0 | AA13: =IF(X13>20000,200,IF(X13>15000,150,0)) -> 200 | AC13: =Y13+Z13+AA13+AB13 -> 1852.64 | AD13: =ROUND(X13-AC13,0) -> 24600 | AE13: =(P13+Q13)*13% -> 1790.36 | AF13: 800 | AG13: =X13+AE13+AF13 -> 29042.815 | AH13: 28930 | AI13: =AH13-AG13 -> -112.8146
A14: =A13+1 -> 9 | B14: 10999 | C14: VISHAL | D14: TECHNICAL SUPERVISOR | E14: 30 | F14: 30 | G14: 0 | H14: =I14+J14+K14 -> 21067 | I14: 4722 | J14: 9050 | K14: 7295 | L14: =(I14+J14)*8.33% -> 1147.2076 | M14: =H14*4.93% -> 1038.6031 | N14: =H14*3.29% -> 693.1043 | O14: =H14*2.88% -> 606.7296 | P14: =I14/E14*F14 -> 4722 | Q14: =J14/E14*F14 -> 9050 | R14: =K14/E14*F14 -> 7295 | S14: =L14/E14*F14 -> 1147.2076 | T14: =M14/E14*F14 -> 1038.6031 | U14: =N14/E14*F14 -> 693.1043 | V14: =O14/E14*F14 -> 606.7296 | W14: =(H14+L14+M14+N14+O14)/E14*G14 -> 0 | X14: =P14+Q14+R14+S14+T14+U14+V14+W14 -> 24552.645 | Y14: =(P14+Q14)*12% -> 1652.64 | Z14: 0 | AA14: =IF(X14>20000,200,IF(X14>15000,150,0)) -> 200 | AC14: =Y14+Z14+AA14+AB14 -> 1852.64 | AD14: =ROUND(X14-AC14,0) -> 22700 | AE14: =(P14+Q14)*13% -> 1790.36 | AF14: 800 | AG14: =X14+AE14+AF14 -> 27143.005 | AH14: 28930 | AI14: =AH14-AG14 -> 1786.9954
A15: =A14+1 -> 10 | B15: 11337 | C15: A.JITHENDER KUMAR | D15: TECHNICAL SUPERVISOR | E15: 30 | F15: 30 | G15: 0 | H15: =I15+J15+K15 -> 22237 | I15: 4722 | J15: 9050 | K15: 8465 | L15: =(I15+J15)*8.33% -> 1147.2076 | M15: =H15*4.93% -> 1096.2841 | N15: =H15*3.29% -> 731.5973 | O15: =H15*2.88% -> 640.4256 | P15: =I15/E15*F15 -> 4722 | Q15: =J15/E15*F15 -> 9050 | R15: =K15/E15*F15 -> 8465 | S15: =L15/E15*F15 -> 1147.2076 | T15: =M15/E15*F15 -> 1096.2841 | U15: =N15/E15*F15 -> 731.5973 | V15: =O15/E15*F15 -> 640.4256 | W15: =(H15+L15+M15+N15+O15)/E15*G15 -> 0 | X15: =P15+Q15+R15+S15+T15+U15+V15+W15 -> 25852.515 | Y15: =(P15+Q15)*12% -> 1652.64 | Z15: 0 | AA15: =IF(X15>20000,200,IF(X15>15000,150,0)) -> 200 | AC15: =Y15+Z15+AA15+AB15 -> 1852.64 | AD15: =ROUND(X15-AC15,0) -> 24000 | AE15: =(P15+Q15)*13% -> 1790.36 | AF15: 800 | AG15: =X15+AE15+AF15 -> 28442.875 | AH15: 28930 | AI15: =AH15-AG15 -> 487.1254
A16: =A15+1 -> 11 | B16: 10339 | C16: V.SRIKANTH | D16: TECHNICAL SUPERVISOR | E16: 30 | F16: 30 | G16: 0 | H16: =I16+J16+K16 -> 21444 | I16: 4722 | J16: 9050 | K16: 7672 | L16: =(I16+J16)*8.33% -> 1147.2076 | M16: =H16*4.93% -> 1057.1892 | N16: =H16*3.29% -> 705.5076 | O16: =H16*2.88% -> 617.5872 | P16: =I16/E16*F16 -> 4722 | Q16: =J16/E16*F16 -> 9050 | R16: =K16/E16*F16 -> 7672 | S16: =L16/E16*F16 -> 1147.2076 | T16: =M16/E16*F16 -> 1057.1892 | U16: =N16/E16*F16 -> 705.5076 | V16: =O16/E16*F16 -> 617.5872 | W16: =(H16+L16+M16+N16+O16)/E16*G16 -> 0 | X16: =P16+Q16+R16+S16+T16+U16+V16+W16 -> 24971.492 | Y16: =(P16+Q16)*12% -> 1652.64 | Z16: 0 | AA16: =IF(X16>20000,200,IF(X16>15000,150,0)) -> 200 | AC16: =Y16+Z16+AA16+AB16 -> 1852.64 | AD16: =ROUND(X16-AC16,0) -> 23119 | AE16: =(P16+Q16)*13% -> 1790.36 | AF16: 800 | AG16: =X16+AE16+AF16 -> 27561.852 | AH16: 28930 | AI16: =AH16-AG16 -> 1368.1484
C17: TECHNICAL SUPERVISOR | E17: =SUM(E7:E16) -> 300 | F17: =SUM(F7:F16) -> 300 | G17: =SUM(G7:G16) -> 0 | H17: =SUM(H7:H16) -> 223596 | I17: =SUM(I7:I16) -> 47220 | J17: =SUM(J7:J16) -> 90500 | K17: =SUM(K7:K16) -> 85876 | L17: =SUM(L7:L16) -> 11472.076 | ... AI17: =SUM(AI7:AI16) -> 3509.168
A18: 12 | B18: 10979 | C18: B.APPANA | D18: ELECTRICIAN | E18: 30 | F18: 30 | G18: 0 | H18: =I18+J18+K18 -> 18540 | I18: 4520 | J18: 9050 | K18: 4970 | L18: =(I18+J18)*8.33% -> 1130.381 | M18: =H18*4.93% -> 914.022 | N18: =H18*3.29% -> 609.966 | O18: =H18*2.88% -> 533.952 | P18: =I18/E18*F18 -> 4520 | Q18: =J18/E18*F18 -> 9050 | R18: =K18/E18*F18 -> 4970 | S18: =L18/E18*F18 -> 1130.381 | T18: =M18/E18*F18 -> 914.022 | U18: =N18/E18*F18 -> 609.966 | V18: =O18/E18*F18 -> 533.952 | W18: =(H18+L18+M18+N18+O18)/E18*G18 -> 0 | X18: =P18+Q18+R18+S18+T18+U18+V18+W18 -> 21728.321 | Y18: =(P18+Q18)*12% -> 1628.4 | Z18: 0 | AA18: =IF(X18>20000,200,IF(X18>15000,150,0)) -> 200 | AC18: =Y18+Z18+AA18+AB18 -> 1828.4 | AD18: =ROUND(X18-AC18,0) -> 19900 | AE18: =(P18+Q18)*13% -> 1764.1 | AF18: 800 | AG18: =X18+AE18+AF18 -> 24292.421 | AH18: 24637 | AI18: =AH18-AG18 -> 344.579
A19: =A18+1 -> 13 | B19: 10982 | C19: SAGAR KUMAR BEHERA | D19: ELECTRICIAN | E19: 30 | F19: 30 | G19: 0 | H19: =I19+J19+K19 -> 19530 | I19: 4520 | J19: 9050 | K19: 5960 | L19: =(I19+J19)*8.33% -> 1130.381 | M19: =H19*4.93% -> 962.829 | N19: =H19*3.29% -> 642.537 | O19: =H19*2.88% -> 562.464 | P19: =I19/E19*F19 -> 4520 | Q19: =J19/E19*F19 -> 9050 | R19: =K19/E19*F19 -> 5960 | S19: =L19/E19*F19 -> 1130.381 | T19: =M19/E19*F19 -> 962.829 | U19: =N19/E19*F19 -> 642.537 | V19: =O19/E19*F19 -> 562.464 | W19: =(H19+L19+M19+N19+O19)/E19*G19 -> 0 | X19: =P19+Q19+R19+S19+T19+U19+V19+W19 -> 22828.211 | Y19: =(P19+Q19)*12% -> 1628.4 | Z19: 0 | AA19: =IF(X19>20000,200,IF(X19>15000,150,0)) -> 200 | AC19: =Y19+Z19+AA19+AB19 -> 1828.4 | AD19: =ROUND(X19-AC19,0) -> 21000 | AE19: =(P19+Q19)*13% -> 1764.1 | AF19: 800 | AG19: =X19+AE19+AF19 -> 25392.311 | AH19: 24637 | AI19: =AH19-AG19 -> -755.311
A20: =A19+1 -> 14 | B20: 11032 | C20: ANANDA SHA | D20: ELECTRICIAN | E20: 30 | F20: 30 | G20: 0 | H20: =I20+J20+K20 -> 19530 | I20: 4520 | J20: 9050 | K20: 5960 | L20: =(I20+J20)*8.33% -> 1130.381 | M20: =H20*4.93% -> 962.829 | N20: =H20*3.29% -> 642.537 | O20: =H20*2.88% -> 562.464 | P20: =I20/E20*F20 -> 4520 | Q20: =J20/E20*F20 -> 9050 | R20: =K20/E20*F20 -> 5960 | S20: =L20/E20*F20 -> 1130.381 | T20: =M20/E20*F20 -> 962.829 | U20: =N20/E20*F20 -> 642.537 | V20: =O20/E20*F20 -> 562.464 | W20: =(H20+L20+M20+N20+O20)/E20*G20 -> 0 | X20: =P20+Q20+R20+S20+T20+U20+V20+W20 -> 22828.211 | Y20: =(P20+Q20)*12% -> 1628.4 | Z20: 0 | AA20: =IF(X20>20000,200,IF(X20>15000,150,0)) -> 200 | AC20: =Y20+Z20+AA20+AB20 -> 1828.4 | AD20: =ROUND(X20-AC20,0) -> 21000 | AE20: =(P20+Q20)*13% -> 1764.1 | AF20: 800 | AG20: =X20+AE20+AF20 -> 25392.311 | AH20: 24637 | AI20: =AH20-AG20 -> -755.311
A21: =A20+1 -> 15 | B21: 11217 | C21: K.TARUN | D21: ELECTRICIAN | E21: 30 | F21: 30 | G21: 0 | H21: =I21+J21+K21 -> 17397 | I21: 4520 | J21: 9050 | K21: 3827 | L21: =(I21+J21)*8.33% -> 1130.381 | M21: =H21*4.93% -> 857.6721 | N21: =H21*3.29% -> 572.3613 | O21: =H21*2.88% -> 501.0336 | P21: =I21/E21*F21 -> 4520 | Q21: =J21/E21*F21 -> 9050 | R21: =K21/E21*F21 -> 3827 | S21: =L21/E21*F21 -> 1130.381 | T21: =M21/E21*F21 -> 857.6721 | U21: =N21/E21*F21 -> 572.3613 | V21: =O21/E21*F21 -> 501.0336 | W21: =(H21+L21+M21+N21+O21)/E21*G21 -> 0 | X21: =P21+Q21+R21+S21+T21+U21+V21+W21 -> 20458.448 | Y21: =(P21+Q21)*12% -> 1628.4 | Z21: =(P21+Q21+R21)*0.75% -> 130.4775 | AA21: =IF(X21>20000,200,IF(X21>15000,150,0)) -> 200 | AC21: =Y21+Z21+AA21+AB21 -> 1958.8775 | AD21: =ROUND(X21-AC21,0) -> 18500 | AE21: =(P21+Q21)*13% -> 1764.1 | AF21: =(P21+Q21+R21)*3.25% -> 565.4025 | AG21: =X21+AE21+AF21 -> 22787.95 | AH21: 24637 | AI21: =AH21-AG21 -> 1849.0495
A22: =A21+1 -> 16 | B22: 11246 | C22: R.HEMANTH | D22: ELECTRICIAN | E22: 30 | F22: 30 | G22: 0 | H22: =I22+J22+K22 -> 16899 | I22: 4520 | J22: 9050 | K22: 3329 | L22: =(I22+J22)*8.33% -> 1130.381 | M22: =H22*4.93% -> 833.1207 | N22: =H22*3.29% -> 555.9771 | O22: =H22*2.88% -> 486.6912 | P22: =I22/E22*F22 -> 4520 | Q22: =J22/E22*F22 -> 9050 | R22: =K22/E22*F22 -> 3329 | S22: =L22/E22*F22 -> 1130.381 | T22: =M22/E22*F22 -> 833.1207 | U22: =N22/E22*F22 -> 555.9771 | V22: =O22/E22*F22 -> 486.6912 | W22: =(H22+L22+M22+N22+O22)/E22*G22 -> 0 | X22: =P22+Q22+R22+S22+T22+U22+V22+W22 -> 19905.17 | Y22: =(P22+Q22)*12% -> 1628.4 | Z22: =(P22+Q22+R22)*0.75% -> 126.7425 | AA22: =IF(X22>20000,200,IF(X22>15000,150,0)) -> 150 | AC22: =Y22+Z22+AA22+AB22 -> 1905.1425 | AD22: =ROUND(X22-AC22,0) -> 18000 | AE22: =(P22+Q22)*13% -> 1764.1 | AF22: =(P22+Q22+R22)*3.25% -> 549.2175 | AG22: =X22+AE22+AF22 -> 22218.487 | AH22: 24637 | AI22: =AH22-AG22 -> 2418.5125
A23: =A22+1 -> 17 | B23: 11311 | C23: MOTUPALLI RAVI SANKARA DURGA | D23: ELECTRICIAN | E23: 30 | F23: 30 | G23: 0 | H23: =I23+J23+K23 -> 17851 | I23: 4520 | J23: 9050 | K23: 4281 | L23: =(I23+J23)*8.33% -> 1130.381 | M23: =H23*4.93% -> 880.0543 | N23: =H23*3.29% -> 587.2979 | O23: =H23*2.88% -> 514.1088 | P23: =I23/E23*F23 -> 4520 | Q23: =J23/E23*F23 -> 9050 | R23: =K23/E23*F23 -> 4281 | S23: =L23/E23*F23 -> 1130.381 | T23: =M23/E23*F23 -> 880.0543 | U23: =N23/E23*F23 -> 587.2979 | V23: =O23/E23*F23 -> 514.1088 | W23: =(H23+L23+M23+N23+O23)/E23*G23 -> 0 | X23: =P23+Q23+R23+S23+T23+U23+V23+W23 -> 20962.842 | Y23: =(P23+Q23)*12% -> 1628.4 | Z23: =(P23+Q23+R23)*0.75% -> 133.8825 | AA23: =IF(X23>20000,200,IF(X23>15000,150,0)) -> 200 | AC23: =Y23+Z23+AA23+AB23 -> 1962.2825 | AD23: =ROUND(X23-AC23,0) -> 19001 | AE23: =(P23+Q23)*13% -> 1764.1 | AF23: =(P23+Q23+R23)*3.25% -> 580.1575 | AG23: =X23+AE23+AF23 -> 23307.1 | AH23: 24637 | AI23: =AH23-AG23 -> 1329.9005
A24: =A23+1 -> 18 | B24: 2 | C24: G.SHANMUKHA RAO | D24: ELECTRICIAN | E24: 30 | F24: 30 | G24: 0 | H24: =I24+J24+K24 -> 18757 | I24: 4520 | J24: 9050 | K24: 5187 | L24: =(I24+J24)*8.33% -> 1130.381 | M24: =H24*4.93% -> 924.7201 | N24: =H24*3.29% -> 617.1053 | O24: =H24*2.88% -> 540.2016 | P24: =I24/E24*F24 -> 4520 | Q24: =J24/E24*F24 -> 9050 | R24: =K24/E24*F24 -> 5187 | S24: =L24/E24*F24 -> 1130.381 | T24: =M24/E24*F24 -> 924.7201 | U24: =N24/E24*F24 -> 617.1053 | V24: =O24/E24*F24 -> 540.2016 | W24: =(H24+L24+M24+N24+O24)/E24*G24 -> 0 | X24: =P24+Q24+R24+S24+T24+U24+V24+W24 -> 21969.408 | Y24: =(P24+Q24)*12% -> 1628.4 | Z24: =(P24+Q24+R24)*0.75% -> 140.6775 | AA24: =IF(X24>20000,200,IF(X24>15000,150,0)) -> 200 | AC24: =Y24+Z24+AA24+AB24 -> 1969.0775 | AD24: =ROUND(X24-AC24,0) -> 20000 | AE24: =(P24+Q24)*13% -> 1764.1 | AF24: =(P24+Q24+R24)*3.25% -> 609.6025 | AG24: =X24+AE24+AF24 -> 24343.11 | AH24: 24637 | AI24: =AH24-AG24 -> 293.8895
A25: =A24+1 -> 19 | B25: 11313 | C25: VASA SHIVA KUMARM | D25: ELECTRICIAN | E25: 30 | F25: 30 | G25: 0 | H25: =I25+J25+K25 -> 16899 | I25: 4520 | J25: 9050 | K25: 3329 | L25: =(I25+J25)*8.33% -> 1130.381 | M25: =H25*4.93% -> 833.1207 | N25: =H25*3.29% -> 555.9771 | O25: =H25*2.88% -> 486.6912 | P25: =I25/E25*F25 -> 4520 | Q25: =J25/E25*F25 -> 9050 | R25: =K25/E25*F25 -> 3329 | S25: =L25/E25*F25 -> 1130.381 | T25: =M25/E25*F25 -> 833.1207 | U25: =N25/E25*F25 -> 555.9771 | V25: =O25/E25*F25 -> 486.6912 | W25: =(H25+L25+M25+N25+O25)/E25*G25 -> 0 | X25: =P25+Q25+R25+S25+T25+U25+V25+W25 -> 19905.17 | Y25: =(P25+Q25)*12% -> 1628.4 | Z25: =(P25+Q25+R25)*0.75% -> 126.7425 | AA25: =IF(X25>20000,200,IF(X25>15000,150,0)) -> 150 | AC25: =Y25+Z25+AA25+AB25 -> 1905.1425 | AD25: =ROUND(X25-AC25,0) -> 18000 | AE25: =(P25+Q25)*13% -> 1764.1 | AF25: =(P25+Q25+R25)*3.25% -> 549.2175 | AG25: =X25+AE25+AF25 -> 22218.487 | AH25: 24637 | AI25: =AH25-AG25 -> 2418.5125
C26: ELECTRICIAN | E26: =SUM(E18:E25) -> 240 | F26: =SUM(F18:F25) -> 240 | G26: =SUM(G18:G25) -> 0 | H26: =SUM(H18:H25) -> 145403 | I26: =SUM(I18:I25) -> 36160 | J26: =SUM(J18:J25) -> 72400 | K26: =SUM(K18:K25) -> 36843 | L26: =SUM(L18:L25) -> 9043.048 | ... AG26: =SUM(AG18:AG25) -> 189952.18 | AH26: =SUM(AH18:AH23) -> 147822 | AI26: =AH26-AG26 -> -42130.179
A27: 20 | B27: 11022 | C27: P.SADDAM | D27: BMS OPERATOR | E27: 30 | F27: 30 | G27: 0 | H27: =I27+J27+K27 -> 19980 | I27: 4520 | J27: 9050 | K27: 6410 | L27: =(I27+J27)*8.33% -> 1130.381 | M27: =H27*4.93% -> 985.014 | N27: =H27*3.29% -> 657.342 | O27: =H27*2.88% -> 575.424 | P27: =I27/E27*F27 -> 4520 | Q27: =J27/E27*F27 -> 9050 | R27: =K27/E27*F27 -> 6410 | S27: =L27/E27*F27 -> 1130.381 | T27: =M27/E27*F27 -> 985.014 | U27: =N27/E27*F27 -> 657.342 | V27: =O27/E27*F27 -> 575.424 | W27: =(H27+L27+M27+N27+O27)/E27*G27 -> 0 | X27: =P27+Q27+R27+S27+T27+U27+V27+W27 -> 23328.161 | Y27: =(P27+Q27)*12% -> 1628.4 | Z27: 0 | AA27: =IF(X27>20000,200,IF(X27>15000,150,0)) -> 200 | AC27: =Y27+Z27+AA27+AB27 -> 1828.4 | AD27: =ROUND(X27-AC27,0) -> 21500 | AE27: =(P27+Q27)*13% -> 1764.1 | AF27: 800 | AG27: =X27+AE27+AF27 -> 25892.261 | AH27: 24511 | AI27: =AH27-AG27 -> -1381.261
A28: =A27+1 -> 21 | B28: 10990 | C28: MUKESH SRICHANDAN | D28: BMS OPERATOR | E28: 30 | F28: 30 | G28: 0 | H28: =I28+J28+K28 -> 18180 | I28: 4520 | J28: 9050 | K28: 4610 | L28: =(I28+J28)*8.33% -> 1130.381 | M28: =H28*4.93% -> 896.274 | N28: =H28*3.29% -> 598.122 | O28: =H28*2.88% -> 523.584 | P28: =I28/E28*F28 -> 4520 | Q28: =J28/E28*F28 -> 9050 | R28: =K28/E28*F28 -> 4610 | S28: =L28/E28*F28 -> 1130.381 | T28: =M28/E28*F28 -> 896.274 | U28: =N28/E28*F28 -> 598.122 | V28: =O28/E28*F28 -> 523.584 | W28: =(H28+L28+M28+N28+O28)/E28*G28 -> 0 | X28: =P28+Q28+R28+S28+T28+U28+V28+W28 -> 21328.361 | Y28: =(P28+Q28)*12% -> 1628.4 | Z28: 0 | AA28: =IF(X28>20000,200,IF(X28>15000,150,0)) -> 200 | AC28: =Y28+Z28+AA28+AB28 -> 1828.4 | AD28: =ROUND(X28-AC28,0) -> 19500 | AE28: =(P28+Q28)*13% -> 1764.1 | AF28: 800 | AG28: =X28+AE28+AF28 -> 23892.461 | AH28: 24511 | AI28: =AH28-AG28 -> 618.539
A29: =A28+1 -> 22 | B29: 10981 | C29: C. GANESH | D29: BMS OPERATOR | E29: 30 | F29: 30 | G29: 0 | H29: =I29+J29+K29 -> 19080 | I29: 4520 | J29: 9050 | K29: 5510 | L29: =(I29+J29)*8.33% -> 1130.381 | M29: =H29*4.93% -> 940.644 | N29: =H29*3.29% -> 627.732 | O29: =H29*2.88% -> 549.504 | P29: =I29/E29*F29 -> 4520 | Q29: =J29/E29*F29 -> 9050 | R29: =K29/E29*F29 -> 5510 | S29: =L29/E29*F29 -> 1130.381 | T29: =M29/E29*F29 -> 940.644 | U29: =N29/E29*F29 -> 627.732 | V29: =O29/E29*F29 -> 549.504 | W29: =(H29+L29+M29+N29+O29)/E29*G29 -> 0 | X29: =P29+Q29+R29+S29+T29+U29+V29+W29 -> 22328.261 | Y29: =(P29+Q29)*12% -> 1628.4 | Z29: 0 | AA29: =IF(X29>20000,200,IF(X29>15000,150,0)) -> 200 | AC29: =Y29+Z29+AA29+AB29 -> 1828.4 | AD29: =ROUND(X29-AC29,0) -> 20500 | AE29: =(P29+Q29)*13% -> 1764.1 | AF29: 800 | AG29: =X29+AE29+AF29 -> 24892.361 | AH29: 24511 | AI29: =AH29-AG29 -> -381.361
A30: =A29+1 -> 23 | B30: 11193 | C30: T.ARCHANA | D30: BMS OPERATOR | E30: 30 | F30: 30 | G30: 0 | H30: =I30+J30+K30 -> 17397 | I30: 4520 | J30: 9050 | K30: 3827 | L30: =(I30+J30)*8.33% -> 1130.381 | M30: =H30*4.93% -> 857.6721 | N30: =H30*3.29% -> 572.3613 | O30: =H30*2.88% -> 501.0336 | P30: =I30/E30*F30 -> 4520 | Q30: =J30/E30*F30 -> 9050 | R30: =K30/E30*F30 -> 3827 | S30: =L30/E30*F30 -> 1130.381 | T30: =M30/E30*F30 -> 857.6721 | U30: =N30/E30*F30 -> 572.3613 | V30: =O30/E30*F30 -> 501.0336 | W30: =(H30+L30+M30+N30+O30)/E30*G30 -> 0 | X30: =P30+Q30+R30+S30+T30+U30+V30+W30 -> 20458.448 | Y30: =(P30+Q30)*12% -> 1628.4 | Z30: =(P30+Q30+R30)*0.75% -> 130.4775 | AA30: =IF(X30>20000,200,IF(X30>15000,150,0)) -> 200 | AC30: =Y30+Z30+AA30+AB30 -> 1958.8775 | AD30: =ROUND(X30-AC30,0) -> 18500 | AE30: =(P30+Q30)*13% -> 1764.1 | AF30: =(P30+Q30+R30)*3.25% -> 565.4025 | AG30: =X30+AE30+AF30 -> 22787.95 | AH30: 24511 | AI30: =AH30-AG30 -> 1723.0495
C31: BMS Technician | E31: =SUM(E27:E30) -> 120 | F31: =SUM(F27:F30) -> 120 | G31: =SUM(G27:G30) -> 0 | H31: =SUM(H27:H30) -> 74637 | I31: =SUM(I27:I30) -> 18080 | J31: =SUM(J27:J30) -> 36200 | K31: =SUM(K27:K30) -> 20357 | L31: =SUM(L27:L30) -> 4521.524 | ... AH31: =SUM(AH27:AH30) -> 98044 | AI31: =AH31-AG31 -> 578.9665
A32: =A30+1 -> 24 | B32: 11000 | C32: ALLAUDDIN MAINODDIN KHAJURE | D32: DG OPERATOR | E32: 30 | F32: 30 | G32: 0 | H32: =I32+J32+K32 -> 22050 | I32: 4520 | J32: 9050 | K32: 8480 | L32: =(I32+J32)*8.33% -> 1130.381 | M32: =H32*4.93% -> 1087.065 | N32: =H32*3.29% -> 725.445 | O32: =H32*2.88% -> 635.04 | P32: =I32/E32*F32 -> 4520 | Q32: =J32/E32*F32 -> 9050 | R32: =K32/E32*F32 -> 8480 | S32: =L32/E32*F32 -> 1130.381 | T32: =M32/E32*F32 -> 1087.065 | U32: =N32/E32*F32 -> 725.445 | V32: =O32/E32*F32 -> 635.04 | W32: =(H32+L32+M32+N32+O32)/E32*G32 -> 0 | X32: =P32+Q32+R32+S32+T32+U32+V32+W32 -> 25627.931 | Y32: =(P32+Q32)*12% -> 1628.4 | Z32: 0 | AA32: =IF(X32>20000,200,IF(X32>15000,150,0)) -> 200 | AC32: =Y32+Z32+AA32+AB32 -> 1828.4 | AD32: =ROUND(X32-AC32,0) -> 23800 | AE32: =(P32+Q32)*13% -> 1764.1 | AF32: 800 | AG32: =X32+AE32+AF32 -> 28192.031 | AH32: 24511 | AI32: =AH32-AG32 -> -3681.031
A33: =A32+1 -> 25 | B33: 11026 | C33: JAGADEESH | D33: DG OPERATOR | E33: 30 | F33: 30 | G33: 0 | H33: =I33+J33+K33 -> 18180 | I33: 4520 | J33: 9050 | K33: 4610 | L33: =(I33+J33)*8.33% -> 1130.381 | M33: =H33*4.93% -> 896.274 | N33: =H33*3.29% -> 598.122 | O33: =H33*2.88% -> 523.584 | P33: =I33/E33*F33 -> 4520 | Q33: =J33/E33*F33 -> 9050 | R33: =K33/E33*F33 -> 4610 | S33: =L33/E33*F33 -> 1130.381 | T33: =M33/E33*F33 -> 896.274 | U33: =N33/E33*F33 -> 598.122 | V33: =O33/E33*F33 -> 523.584 | W33: =(H33+L33+M33+N33+O33)/E33*G33 -> 0 | X33: =P33+Q33+R33+S33+T33+U33+V33+W33 -> 21328.361 | Y33: =(P33+Q33)*12% -> 1628.4 | Z33: 0 | AA33: =IF(X33>20000,200,IF(X33>15000,150,0)) -> 200 | AC33: =Y33+Z33+AA33+AB33 -> 1828.4 | AD33: =ROUND(X33-AC33,0) -> 19500 | AE33: =(P33+Q33)*13% -> 1764.1 | AF33: 800 | AG33: =X33+AE33+AF33 -> 23892.461 | AH33: 24511 | AI33: =AH33-AG33 -> 618.539
A34: =A33+1 -> 26 | B34: 11049 | C34: D.RAVI | D34: DG OPERATOR | E34: 30 | F34: 30 | G34: 0 | H34: =I34+J34+K34 -> 17851 | I34: 4520 | J34: 9050 | K34: 4281 | L34: =(I34+J34)*8.33% -> 1130.381 | M34: =H34*4.93% -> 880.0543 | N34: =H34*3.29% -> 587.2979 | O34: =H34*2.88% -> 514.1088 | P34: =I34/E34*F34 -> 4520 | Q34: =J34/E34*F34 -> 9050 | R34: =K34/E34*F34 -> 4281 | S34: =L34/E34*F34 -> 1130.381 | T34: =M34/E34*F34 -> 880.0543 | U34: =N34/E34*F34 -> 587.2979 | V34: =O34/E34*F34 -> 514.1088 | W34: =(H34+L34+M34+N34+O34)/E34*G34 -> 0 | X34: =P34+Q34+R34+S34+T34+U34+V34+W34 -> 20962.842 | Y34: =(P34+Q34)*12% -> 1628.4 | Z34: =(P34+Q34+R34)*0.75% -> 133.8825 | AA34: =IF(X34>20000,200,IF(X34>15000,150,0)) -> 200 | AC34: =Y34+Z34+AA34+AB34 -> 1962.2825 | AD34: =ROUND(X34-AC34,0) -> 19001 | AE34: =(P34+Q34)*13% -> 1764.1 | AF34: =(P34+Q34+R34)*3.25% -> 580.1575 | AG34: =X34+AE34+AF34 -> 23307.1 | AH34: 24637 | AI34: =AH34-AG34 -> 1329.9005
A35: =A34+1 -> 27 | B35: 11273 | C35: CHANDRA SHAKHER | D35: DG OPERATOR | E35: 30 | F35: 30 | G35: 0 | H35: =I35+J35+K35 -> 18180 | I35: 4520 | J35: 9050 | K35: 4610 | L35: =(I35+J35)*8.33% -> 1130.381 | M35: =H35*4.93% -> 896.274 | N35: =H35*3.29% -> 598.122 | O35: =H35*2.88% -> 523.584 | P35: =I35/E35*F35 -> 4520 | Q35: =J35/E35*F35 -> 9050 | R35: =K35/E35*F35 -> 4610 | S35: =L35/E35*F35 -> 1130.381 | T35: =M35/E35*F35 -> 896.274 | U35: =N35/E35*F35 -> 598.122 | V35: =O35/E35*F35 -> 523.584 | W35: =(H35+L35+M35+N35+O35)/E35*G35 -> 0 | X35: =P35+Q35+R35+S35+T35+U35+V35+W35 -> 21328.361 | Y35: =(P35+Q35)*12% -> 1628.4 | Z35: 0 | AA35: =IF(X35>20000,200,IF(X35>15000,150,0)) -> 200 | AC35: =Y35+Z35+AA35+AB35 -> 1828.4 | AD35: =ROUND(X35-AC35,0) -> 19500 | AE35: =(P35+Q35)*13% -> 1764.1 | AF35: 800 | AG35: =X35+AE35+AF35 -> 23892.461 | AH35: 24511 | AI35: =AH35-AG35 -> 618.539
C36: DG OPERATOR | E36: =SUM(E32:E35) -> 120 | F36: =SUM(F32:F35) -> 120 | G36: =SUM(G32:G35) -> 0 | H36: =SUM(H32:H35) -> 76261 | I36: =SUM(I32:I35) -> 18080 | J36: =SUM(J32:J35) -> 36200 | K36: =SUM(K32:K35) -> 21981 | L36: =SUM(L32:L35) -> 4521.524 | ... AI36: =SUM(AI32:AI35) -> -1114.0525
A37: =A35+1 -> 28 | B37: 10991 | C37: JOGENDRA SETHI | D37: HVAC OPERATOR | E37: 30 | F37: 30 | G37: 0 | H37: =I37+J37+K37 -> 22230 | I37: 4520 | J37: 9050 | K37: 8660 | L37: =(I37+J37)*8.33% -> 1130.381 | M37: =H37*4.93% -> 1095.939 | N37: =H37*3.29% -> 731.367 | O37: =H37*2.88% -> 640.224 | P37: =I37/E37*F37 -> 4520 | Q37: =J37/E37*F37 -> 9050 | R37: =K37/E37*F37 -> 8660 | S37: =L37/E37*F37 -> 1130.381 | T37: =M37/E37*F37 -> 1095.939 | U37: =N37/E37*F37 -> 731.367 | V37: =O37/E37*F37 -> 640.224 | W37: =(H37+L37+M37+N37+O37)/E37*G37 -> 0 | X37: =P37+Q37+R37+S37+T37+U37+V37+W37 -> 25827.911 | Y37: =(P37+Q37)*12% -> 1628.4 | Z37: 0 | AA37: =IF(X37>20000,200,IF(X37>15000,150,0)) -> 200 | AC37: =Y37+Z37+AA37+AB37 -> 1828.4 | AD37: =ROUND(X37-AC37,0) -> 24000 | AE37: =(P37+Q37)*13% -> 1764.1 | AF37: 800 | AG37: =X37+AE37+AF37 -> 28392.011 | AH37: 24586 | AI37: =AG37-AH37 -> 3806.011
A38: =A37+1 -> 29 | B38: 10998 | C38: K.MABU SHAREEF | D38: HVAC OPERATOR | E38: 30 | F38: 30 | G38: 0 | H38: =I38+J38+K38 -> 19530 | I38: 4520 | J38: 9050 | K38: 5960 | L38: =(I38+J38)*8.33% -> 1130.381 | M38: =H38*4.93% -> 962.829 | N38: =H38*3.29% -> 642.537 | O38: =H38*2.88% -> 562.464 | P38: =I38/E38*F38 -> 4520 | Q38: =J38/E38*F38 -> 9050 | R38: =K38/E38*F38 -> 5960 | S38: =L38/E38*F38 -> 1130.381 | T38: =M38/E38*F38 -> 962.829 | U38: =N38/E38*F38 -> 642.537 | V38: =O38/E38*F38 -> 562.464 | W38: =(H38+L38+M38+N38+O38)/E38*G38 -> 0 | X38: =P38+Q38+R38+S38+T38+U38+V38+W38 -> 22828.211 | Y38: =(P38+Q38)*12% -> 1628.4 | Z38: 0 | AA38: =IF(X38>20000,200,IF(X38>15000,150,0)) -> 200 | AC38: =Y38+Z38+AA38+AB38 -> 1828.4 | AD38: =ROUND(X38-AC38,0) -> 21000 | AE38: =(P38+Q38)*13% -> 1764.1 | AF38: 800 | AG38: =X38+AE38+AF38 -> 25392.311 | AH38: 24586 | AI38: =AG38-AH38 -> 806.311
A39: =A38+1 -> 30 | B39: 10997 | C39: KASIM VALI | D39: HVAC OPERATOR | E39: 30 | F39: 30 | G39: 0 | H39: =I39+J39+K39 -> 19080 | I39: 4520 | J39: 9050 | K39: 5510 | L39: =(I39+J39)*8.33% -> 1130.381 | M39: =H39*4.93% -> 940.644 | N39: =H39*3.29% -> 627.732 | O39: =H39*2.88% -> 549.504 | P39: =I39/E39*F39 -> 4520 | Q39: =J39/E39*F39 -> 9050 | R39: =K39/E39*F39 -> 5510 | S39: =L39/E39*F39 -> 1130.381 | T39: =M39/E39*F39 -> 940.644 | U39: =N39/E39*F39 -> 627.732 | V39: =O39/E39*F39 -> 549.504 | W39: =(H39+L39+M39+N39+O39)/E39*G39 -> 0 | X39: =P39+Q39+R39+S39+T39+U39+V39+W39 -> 22328.261 | Y39: =(P39+Q39)*12% -> 1628.4 | Z39: 0 | AA39: =IF(X39>20000,200,IF(X39>15000,150,0)) -> 200 | AC39: =Y39+Z39+AA39+AB39 -> 1828.4 | AD39: =ROUND(X39-AC39,0) -> 20500 | AE39: =(P39+Q39)*13% -> 1764.1 | AF39: 800 | AG39: =X39+AE39+AF39 -> 24892.361 | AH39: 24586 | AI39: =AG39-AH39 -> 306.361
A40: =A39+1 -> 31 | B40: 11341 | C40: P.SRINIVAS | D40: HVAC OPERATOR | E40: 30 | F40: 30 | G40: 0 | H40: =I40+J40+K40 -> 16899 | I40: 4520 | J40: 9050 | K40: 3329 | L40: =(I40+J40)*8.33% -> 1130.381 | M40: =H40*4.93% -> 833.1207 | N40: =H40*3.29% -> 555.9771 | O40: =H40*2.88% -> 486.6912 | P40: =I40/E40*F40 -> 4520 | Q40: =J40/E40*F40 -> 9050 | R40: =K40/E40*F40 -> 3329 | S40: =L40/E40*F40 -> 1130.381 | T40: =M40/E40*F40 -> 833.1207 | U40: =N40/E40*F40 -> 555.9771 | V40: =O40/E40*F40 -> 486.6912 | W40: =(H40+L40+M40+N40+O40)/E40*G40 -> 0 | X40: =P40+Q40+R40+S40+T40+U40+V40+W40 -> 19905.17 | Y40: =(P40+Q40)*12% -> 1628.4 | Z40: =(P40+Q40+R40)*0.75% -> 126.7425 | AA40: =IF(X40>20000,200,IF(X40>15000,150,0)) -> 150 | AC40: =Y40+Z40+AA40+AB40 -> 1905.1425 | AD40: =ROUND(X40-AC40,0) -> 18000 | AE40: =(P40+Q40)*13% -> 1764.1 | AF40: =(P40+Q40+R40)*3.25% -> 549.2175 | AG40: =X40+AE40+AF40 -> 22218.487 | AH40: 24586 | AI40: =AG40-AH40 -> -2367.5125
A41: =A40+1 -> 32 | B41: 11241 | C41: SHAHBDDIN | D41: HVAC OPERATOR | E41: 30 | F41: 30 | G41: 0 | H41: =I41+J41+K41 -> 17397 | I41: 4520 | J41: 9050 | K41: 3827 | L41: =(I41+J41)*8.33% -> 1130.381 | M41: =H41*4.93% -> 857.6721 | N41: =H41*3.29% -> 572.3613 | O41: =H41*2.88% -> 501.0336 | P41: =I41/E41*F41 -> 4520 | Q41: =J41/E41*F41 -> 9050 | R41: =K41/E41*F41 -> 3827 | S41: =L41/E41*F41 -> 1130.381 | T41: =M41/E41*F41 -> 857.6721 | U41: =N41/E41*F41 -> 572.3613 | V41: =O41/E41*F41 -> 501.0336 | W41: =(H41+L41+M41+N41+O41)/E41*G41 -> 0 | X41: =P41+Q41+R41+S41+T41+U41+V41+W41 -> 20458.448 | Y41: =(P41+Q41)*12% -> 1628.4 | Z41: =(P41+Q41+R41)*0.75% -> 130.4775 | AA41: =IF(X41>20000,200,IF(X41>15000,150,0)) -> 200 | AC41: =Y41+Z41+AA41+AB41 -> 1958.8775 | AD41: =ROUND(X41-AC41,0) -> 18500 | AE41: =(P41+Q41)*13% -> 1764.1 | AF41: =(P41+Q41+R41)*3.25% -> 565.4025 | AG41: =X41+AE41+AF41 -> 22787.95 | AH41: 24586 | AI41: =AG41-AH41 -> -1798.0495
A42: =A41+1 -> 33 | B42: 11389 | C42: ARIF | D42: HVAC OPERATOR | E42: 30 | F42: 30 | G42: 0 | H42: =I42+J42+K42 -> 19080 | I42: 4520 | J42: 9050 | K42: 5510 | L42: =(I42+J42)*8.33% -> 1130.381 | M42: =H42*4.93% -> 940.644 | N42: =H42*3.29% -> 627.732 | O42: =H42*2.88% -> 549.504 | P42: =I42/E42*F42 -> 4520 | Q42: =J42/E42*F42 -> 9050 | R42: =K42/E42*F42 -> 5510 | S42: =L42/E42*F42 -> 1130.381 | T42: =M42/E42*F42 -> 940.644 | U42: =N42/E42*F42 -> 627.732 | V42: =O42/E42*F42 -> 549.504 | W42: =(H42+L42+M42+N42+O42)/E42*G42 -> 0 | X42: =P42+Q42+R42+S42+T42+U42+V42+W42 -> 22328.261 | Y42: =(P42+Q42)*12% -> 1628.4 | Z42: 0 | AA42: =IF(X42>20000,200,IF(X42>15000,150,0)) -> 200 | AC42: =Y42+Z42+AA42+AB42 -> 1828.4 | AD42: =ROUND(X42-AC42,0) -> 20500 | AE42: =(P42+Q42)*13% -> 1764.1 | AF42: 800 | AG42: =X42+AE42+AF42 -> 24892.361 | AH42: 24586 | AI42: =AG42-AH42 -> 306.361
A43: =A42+1 -> 34 | B43: 1 | C43: MOHMMED AMIR | D43: HVAC OPERATOR | E43: 30 | F43: 30 | G43: 0 | H43: =I43+J43+K43 -> 18630 | I43: 4520 | J43: 9050 | K43: 5060 | L43: =(I43+J43)*8.33% -> 1130.381 | M43: =H43*4.93% -> 918.459 | N43: =H43*3.29% -> 612.927 | O43: =H43*2.88% -> 536.544 | P43: =I43/E43*F43 -> 4520 | Q43: =J43/E43*F43 -> 9050 | R43: =K43/E43*F43 -> 5060 | S43: =L43/E43*F43 -> 1130.381 | T43: =M43/E43*F43 -> 918.459 | U43: =N43/E43*F43 -> 612.927 | V43: =O43/E43*F43 -> 536.544 | W43: =(H43+L43+M43+N43+O43)/E43*G43 -> 0 | X43: =P43+Q43+R43+S43+T43+U43+V43+W43 -> 21828.311 | Y43: =(P43+Q43)*12% -> 1628.4 | Z43: 0 | AA43: =IF(X43>20000,200,IF(X43>15000,150,0)) -> 200 | AC43: =Y43+Z43+AA43+AB43 -> 1828.4 | AD43: =ROUND(X43-AC43,0) -> 20000 | AE43: =(P43+Q43)*13% -> 1764.1 | AF43: 800 | AG43: =X43+AE43+AF43 -> 24392.411 | AH43: 24586 | AI43: =AG43-AH43 -> -193.589
C44: HVAC Technician | E44: =SUM(E37:E43) -> 210 | F44: =SUM(F37:F43) -> 210 | G44: =SUM(G37:G43) -> 0 | H44: =SUM(H37:H43) -> 132846 | I44: =SUM(I37:I43) -> 31640 | J44: =SUM(J37:J43) -> 63350 | K44: =SUM(K37:K43) -> 37856 | L44: =SUM(L37:L43) -> 7912.667 | ... AG44: =SUM(AG37:AG43) -> 172967.89 | AH44: =SUM(AH37:AH41) -> 122930 | AI44: =SUM(AI37:AI43) -> 865.893
A45: 35 | B45: 10980 | C45: ANURUDHA SAMAL | D45: PLUMER | E45: 30 | F45: 30 | G45: 0 | H45: =I45+J45+K45 -> 22951 | I45: 4520 | J45: 9050 | K45: 9381 | L45: =(I45+J45)*8.33% -> 1130.381 | M45: =H45*4.93% -> 1131.4843 | N45: =H45*3.29% -> 755.0879 | O45: =H45*2.88% -> 660.9888 | P45: =I45/E45*F45 -> 4520 | Q45: =J45/E45*F45 -> 9050 | R45: =K45/E45*F45 -> 9381 | S45: =L45/E45*F45 -> 1130.381 | T45: =M45/E45*F45 -> 1131.4843 | U45: =N45/E45*F45 -> 755.0879 | V45: =O45/E45*F45 -> 660.9888 | W45: =(H45+L45+M45+N45+O45)/E45*G45 -> 0 | X45: =P45+Q45+R45+S45+T45+U45+V45+W45 -> 26628.942 | Y45: =(P45+Q45)*12% -> 1628.4 | Z45: 0 | AA45: =IF(X45>20000,200,IF(X45>15000,150,0)) -> 200 | AC45: =Y45+Z45+AA45+AB45 -> 1828.4 | AD45: =ROUND(X45-AC45,0) -> 24801 | AE45: =(P45+Q45)*13% -> 1764.1 | AF45: 800 | AG45: =X45+AE45+AF45 -> 29193.042 | AH45: 24962 | AI45: =AH45-AG45 -> -4231.042
A46: =A45+1 -> 36 | B46: 10978 | C46: PABITRA MALIK | D46: PLUMER | E46: 30 | F46: 30 | G46: 0 | H46: =I46+J46+K46 -> 20430 | I46: 4520 | J46: 9050 | K46: 6860 | L46: =(I46+J46)*8.33% -> 1130.381 | M46: =H46*4.93% -> 1007.199 | N46: =H46*3.29% -> 672.147 | O46: =H46*2.88% -> 588.384 | P46: =I46/E46*F46 -> 4520 | Q46: =J46/E46*F46 -> 9050 | R46: =K46/E46*F46 -> 6860 | S46: =L46/E46*F46 -> 1130.381 | T46: =M46/E46*F46 -> 1007.199 | U46: =N46/E46*F46 -> 672.147 | V46: =O46/E46*F46 -> 588.384 | W46: =(H46+L46+M46+N46+O46)/E46*G46 -> 0 | X46: =P46+Q46+R46+S46+T46+U46+V46+W46 -> 23828.111 | Y46: =(P46+Q46)*12% -> 1628.4 | Z46: 0 | AA46: =IF(X46>20000,200,IF(X46>15000,150,0)) -> 200 | AC46: =Y46+Z46+AA46+AB46 -> 1828.4 | AD46: =ROUND(X46-AC46,0) -> 22000 | AE46: =(P46+Q46)*13% -> 1764.1 | AF46: 800 | AG46: =X46+AE46+AF46 -> 26392.211 | AH46: 24962 | AI46: =AH46-AG46 -> -1430.211
A47: =A46+1 -> 37 | B47: 10492 | C47: SIRAJ | D47: PLUMER | E47: 30 | F47: 30 | G47: 0 | H47: =I47+J47+K47 -> 17851 | I47: 4520 | J47: 9050 | K47: 4281 | L47: =(I47+J47)*8.33% -> 1130.381 | M47: =H47*4.93% -> 880.0543 | N47: =H47*3.29% -> 587.2979 | O47: =H47*2.88% -> 514.1088 | P47: =I47/E47*F47 -> 4520 | Q47: =J47/E47*F47 -> 9050 | R47: =K47/E47*F47 -> 4281 | S47: =L47/E47*F47 -> 1130.381 | T47: =M47/E47*F47 -> 880.0543 | U47: =N47/E47*F47 -> 587.2979 | V47: =O47/E47*F47 -> 514.1088 | W47: =(H47+L47+M47+N47+O47)/E47*G47 -> 0 | X47: =P47+Q47+R47+S47+T47+U47+V47+W47 -> 20962.842 | Y47: =(P47+Q47)*12% -> 1628.4 | Z47: =(P47+Q47+R47)*0.75% -> 133.8825 | AA47: =IF(X47>20000,200,IF(X47>15000,150,0)) -> 200 | AC47: =Y47+Z47+AA47+AB47 -> 1962.2825 | AD47: =ROUND(X47-AC47,0) -> 19001 | AE47: =(P47+Q47)*13% -> 1764.1 | AF47: =(P47+Q47+R47)*3.25% -> 580.1575 | AG47: =X47+AE47+AF47 -> 23307.1 | AH47: 24962 | AI47: =AH47-AG47 -> 1654.9005
A48: =A47+1 -> 38 | B48: 10974 | C48: GADADHAR MALIK | D48: PLUMER | E48: 30 | F48: 30 | G48: 0 | H48: =I48+J48+K48 -> 18630 | I48: 4520 | J48: 9050 | K48: 5060 | L48: =(I48+J48)*8.33% -> 1130.381 | M48: =H48*4.93% -> 918.459 | N48: =H48*3.29% -> 612.927 | O48: =H48*2.88% -> 536.544 | P48: =I48/E48*F48 -> 4520 | Q48: =J48/E48*F48 -> 9050 | R48: =K48/E48*F48 -> 5060 | S48: =L48/E48*F48 -> 1130.381 | T48: =M48/E48*F48 -> 918.459 | U48: =N48/E48*F48 -> 612.927 | V48: =O48/E48*F48 -> 536.544 | W48: =(H48+L48+M48+N48+O48)/E48*G48 -> 0 | X48: =P48+Q48+R48+S48+T48+U48+V48+W48 -> 21828.311 | Y48: =(P48+Q48)*12% -> 1628.4 | Z48: 0 | AA48: =IF(X48>20000,200,IF(X48>15000,150,0)) -> 200 | AC48: =Y48+Z48+AA48+AB48 -> 1828.4 | AD48: =ROUND(X48-AC48,0) -> 20000 | AE48: =(P48+Q48)*13% -> 1764.1 | AF48: 800 | AG48: =X48+AE48+AF48 -> 24392.411 | AH48: 24962 | AI48: =AH48-AG48 -> 569.589
A49: =A48+1 -> 39 | B49: 10983 | C49: SUDHAKAR | D49: PLUMER | E49: 30 | F49: 30 | G49: 0 | H49: =I49+J49+K49 -> 18180 | I49: 4520 | J49: 9050 | K49: 4610 | L49: =(I49+J49)*8.33% -> 1130.381 | M49: =H49*4.93% -> 896.274 | N49: =H49*3.29% -> 598.122 | O49: =H49*2.88% -> 523.584 | P49: =I49/E49*F49 -> 4520 | Q49: =J49/E49*F49 -> 9050 | R49: =K49/E49*F49 -> 4610 | S49: =L49/E49*F49 -> 1130.381 | T49: =M49/E49*F49 -> 896.274 | U49: =N49/E49*F49 -> 598.122 | V49: =O49/E49*F49 -> 523.584 | W49: =(H49+L49+M49+N49+O49)/E49*G49 -> 0 | X49: =P49+Q49+R49+S49+T49+U49+V49+W49 -> 21328.361 | Y49: =(P49+Q49)*12% -> 1628.4 | Z49: 0 | AA49: =IF(X49>20000,200,IF(X49>15000,150,0)) -> 200 | AC49: =Y49+Z49+AA49+AB49 -> 1828.4 | AD49: =ROUND(X49-AC49,0) -> 19500 | AE49: =(P49+Q49)*13% -> 1764.1 | AF49: 800 | AG49: =X49+AE49+AF49 -> 23892.461 | AH49: 24962 | AI49: =AH49-AG49 -> 1069.539
A50: =A49+1 -> 40 | B50: 11158 | C50: NARESH DAS | D50: PLUMER | E50: 30 | F50: 30 | G50: 0 | H50: =I50+J50+K50 -> 17851 | I50: 4520 | J50: 9050 | K50: 4281 | L50: =(I50+J50)*8.33% -> 1130.381 | M50: =H50*4.93% -> 880.0543 | N50: =H50*3.29% -> 587.2979 | O50: =H50*2.88% -> 514.1088 | P50: =I50/E50*F50 -> 4520 | Q50: =J50/E50*F50 -> 9050 | R50: =K50/E50*F50 -> 4281 | S50: =L50/E50*F50 -> 1130.381 | T50: =M50/E50*F50 -> 880.0543 | U50: =N50/E50*F50 -> 587.2979 | V50: =O50/E50*F50 -> 514.1088 | W50: =(H50+L50+M50+N50+O50)/E50*G50 -> 0 | X50: =P50+Q50+R50+S50+T50+U50+V50+W50 -> 20962.842 | Y50: =(P50+Q50)*12% -> 1628.4 | Z50: =(P50+Q50+R50)*0.75% -> 133.8825 | AA50: =IF(X50>20000,200,IF(X50>15000,150,0)) -> 200 | AC50: =Y50+Z50+AA50+AB50 -> 1962.2825 | AD50: =ROUND(X50-AC50,0) -> 19001 | AE50: =(P50+Q50)*13% -> 1764.1 | AF50: =(P50+Q50+R50)*3.25% -> 580.1575 | AG50: =X50+AE50+AF50 -> 23307.1 | AH50: 24962 | AI50: =AH50-AG50 -> 1654.9005
A51: =A50+1 -> 41 | B51: 11203 | C51: BISWAJIT SAHOO | D51: PLUMER | E51: 30 | F51: 30 | G51: 0 | H51: =I51+J51+K51 -> 17851 | I51: 4520 | J51: 9050 | K51: 4281 | L51: =(I51+J51)*8.33% -> 1130.381 | M51: =H51*4.93% -> 880.0543 | N51: =H51*3.29% -> 587.2979 | O51: =H51*2.88% -> 514.1088 | P51: =I51/E51*F51 -> 4520 | Q51: =J51/E51*F51 -> 9050 | R51: =K51/E51*F51 -> 4281 | S51: =L51/E51*F51 -> 1130.381 | T51: =M51/E51*F51 -> 880.0543 | U51: =N51/E51*F51 -> 587.2979 | V51: =O51/E51*F51 -> 514.1088 | W51: =(H51+L51+M51+N51+O51)/E51*G51 -> 0 | X51: =P51+Q51+R51+S51+T51+U51+V51+W51 -> 20962.842 | Y51: =(P51+Q51)*12% -> 1628.4 | Z51: =(P51+Q51+R51)*0.75% -> 133.8825 | AA51: =IF(X51>20000,200,IF(X51>15000,150,0)) -> 200 | AC51: =Y51+Z51+AA51+AB51 -> 1962.2825 | AD51: =ROUND(X51-AC51,0) -> 19001 | AE51: =(P51+Q51)*13% -> 1764.1 | AF51: =(P51+Q51+R51)*3.25% -> 580.1575 | AG51: =X51+AE51+AF51 -> 23307.1 | AH51: 24962 | AI51: =AH51-AG51 -> 1654.9005
A52: =A51+1 -> 42 | B52: 11276 | C52: GOPAL ROUT | D52: PLUMER | E52: 30 | F52: 30 | G52: 0 | H52: =I52+J52+K52 -> 18630 | I52: 4520 | J52: 9050 | K52: 5060 | L52: =(I52+J52)*8.33% -> 1130.381 | M52: =H52*4.93% -> 918.459 | N52: =H52*3.29% -> 612.927 | O52: =H52*2.88% -> 536.544 | P52: =I52/E52*F52 -> 4520 | Q52: =J52/E52*F52 -> 9050 | R52: =K52/E52*F52 -> 5060 | S52: =L52/E52*F52 -> 1130.381 | T52: =M52/E52*F52 -> 918.459 | U52: =N52/E52*F52 -> 612.927 | V52: =O52/E52*F52 -> 536.544 | W52: =(H52+L52+M52+N52+O52)/E52*G52 -> 0 | X52: =P52+Q52+R52+S52+T52+U52+V52+W52 -> 21828.311 | Y52: =(P52+Q52)*12% -> 1628.4 | Z52: 0 | AA52: =IF(X52>20000,200,IF(X52>15000,150,0)) -> 200 | AC52: =Y52+Z52+AA52+AB52 -> 1828.4 | AD52: =ROUND(X52-AC52,0) -> 20000 | AE52: =(P52+Q52)*13% -> 1764.1 | AF52: 800 | AG52: =X52+AE52+AF52 -> 24392.411 | AH52: 24962 | AI52: =AH52-AG52 -> 569.589
C53: Plumber | E53: =SUM(E45:E52) -> 240 | F53: =SUM(F45:F52) -> 240 | G53: =SUM(G45:G52) -> 0 | H53: =SUM(H45:H52) -> 152374 | I53: =SUM(I45:I52) -> 36160 | J53: =SUM(J45:J52) -> 72400 | K53: =SUM(K45:K52) -> 43814 | L53: =SUM(L45:L52) -> 9043.048 | ... AI53: =SUM(AI45:AI52) -> 1512.1655
A54: =A52+1 -> 43 | B54: 10993 | C54: VENKATESH M | D54: PAINTER | E54: 30 | F54: 30 | G54: 0 | H54: =I54+J54+K54 -> 19293 | I54: 4520 | J54: 9050 | K54: 5723 | L54: =(I54+J54)*8.33% -> 1130.381 | M54: =H54*4.93% -> 951.1449 | N54: =H54*3.29% -> 634.7397 | O54: =H54*2.88% -> 555.6384 | P54: =I54/E54*F54 -> 4520 | Q54: =J54/E54*F54 -> 9050 | R54: =K54/E54*F54 -> 5723 | S54: =L54/E54*F54 -> 1130.381 | T54: =M54/E54*F54 -> 951.1449 | U54: =N54/E54*F54 -> 634.7397 | V54: =O54/E54*F54 -> 555.6384 | W54: =(H54+L54+M54+N54+O54)/E54*G54 -> 0 | X54: =P54+Q54+R54+S54+T54+U54+V54+W54 -> 22564.904 | Y54: =(P54+Q54)*12% -> 1628.4 | Z54: 0 | AA54: =IF(X54>20000,200,IF(X54>15000,150,0)) -> 200 | AC54: =Y54+Z54+AA54+AB54 -> 1828.4 | AD54: =ROUND(X54-AC54,0) -> 20737 | AE54: =(P54+Q54)*13% -> 1764.1 | AF54: 800 | AG54: =X54+AE54+AF54 -> 25129.004 | AH54: 25129 | AI54: =AH54-AG54 -> -0.004
C55: PAINTER | E55: =SUM(E54) -> 30 | F55: =SUM(F54) -> 30 | G55: =SUM(G54) -> 0 | H55: =SUM(H54) -> 19293 | I55: =SUM(I54) -> 4520 | J55: =SUM(J54) -> 9050 | K55: =SUM(K54) -> 5723 | L55: =SUM(L54) -> 1130.381 | ... AI55: =SUM(AI54) -> -0.004
A56: 44 | B56: 11028 | C56: RAMASWAMY | D56: WELDER | E56: 30 | F56: 30 | G56: 0 | H56: =I56+J56+K56 -> 19293 | I56: 4520 | J56: 9050 | K56: 5723 | L56: =(I56+J56)*8.33% -> 1130.381 | M56: =H56*4.93% -> 951.1449 | N56: =H56*3.29% -> 634.7397 | O56: =H56*2.88% -> 555.6384 | P56: =I56/E56*F56 -> 4520 | Q56: =J56/E56*F56 -> 9050 | R56: =K56/E56*F56 -> 5723 | S56: =L56/E56*F56 -> 1130.381 | T56: =M56/E56*F56 -> 951.1449 | U56: =N56/E56*F56 -> 634.7397 | V56: =O56/E56*F56 -> 555.6384 | W56: =(H56+L56+M56+N56+O56)/E56*G56 -> 0 | X56: =P56+Q56+R56+S56+T56+U56+V56+W56 -> 22564.904 | Y56: =(P56+Q56)*12% -> 1628.4 | Z56: 0 | AA56: =IF(X56>20000,200,IF(X56>15000,150,0)) -> 200 | AC56: =Y56+Z56+AA56+AB56 -> 1828.4 | AD56: =ROUND(X56-AC56,0) -> 20737 | AE56: =(P56+Q56)*13% -> 1764.1 | AF56: 800 | AG56: =X56+AE56+AF56 -> 25129.004 | AH56: 25129 | AI56: =AH56-AG56 -> -0.004
C57: WELDER | E57: =SUM(E56) -> 30 | F57: =SUM(F56) -> 30 | G57: =SUM(G56) -> 0 | H57: =SUM(H56) -> 19293 | I57: =SUM(I56) -> 4520 | J57: =SUM(J56) -> 9050 | K57: =SUM(K56) -> 5723 | L57: =SUM(L56) -> 1130.381 | ... AI57: =SUM(AI56) -> -0.004
A58: 45 | B58: 11214 | C58: M.LAXMINARAYANA | D58: MASON | E58: 30 | F58: 30 | G58: 0 | H58: =I58+J58+K58 -> 19293 | I58: 4520 | J58: 9050 | K58: 5723 | L58: =(I58+J58)*8.33% -> 1130.381 | M58: =H58*4.93% -> 951.1449 | N58: =H58*3.29% -> 634.7397 | O58: =H58*2.88% -> 555.6384 | P58: =I58/E58*F58 -> 4520 | Q58: =J58/E58*F58 -> 9050 | R58: =K58/E58*F58 -> 5723 | S58: =L58/E58*F58 -> 1130.381 | T58: =M58/E58*F58 -> 951.1449 | U58: =N58/E58*F58 -> 634.7397 | V58: =O58/E58*F58 -> 555.6384 | W58: =(H58+L58+M58+N58+O58)/E58*G58 -> 0 | X58: =P58+Q58+R58+S58+T58+U58+V58+W58 -> 22564.904 | Y58: =(P58+Q58)*12% -> 1628.4 | Z58: 0 | AA58: =IF(X58>20000,200,IF(X58>15000,150,0)) -> 200 | AC58: =Y58+Z58+AA58+AB58 -> 1828.4 | AD58: =ROUND(X58-AC58,0) -> 20737 | AE58: =(P58+Q58)*13% -> 1764.1 | AF58: 800 | AG58: =X58+AE58+AF58 -> 25129.004 | AH58: 25129 | AI58: =AH58-AG58 -> -0.004
C59: Mason | E59: =SUM(E58) -> 30 | F59: =SUM(F58) -> 30 | G59: =SUM(G58) -> 0 | H59: =SUM(H58) -> 19293 | I59: =SUM(I58) -> 4520 | J59: =SUM(J58) -> 9050 | K59: =SUM(K58) -> 5723 | L59: =SUM(L58) -> 1130.381 | ... AI59: =SUM(AI58) -> -0.004
A60: =A58+1 -> 46 | B60: 11058 | C60: P.MOKHA LINGAM | D60: Carpenter | E60: 30 | F60: 30 | G60: 0 | H60: =I60+J60+K60 -> 19143 | I60: 4520 | J60: 9050 | K60: 5573 | L60: =(I60+J60)*8.33% -> 1130.381 | M60: =H60*4.93% -> 943.7499 | N60: =H60*3.29% -> 629.8047 | O60: =H60*2.88% -> 551.3184 | P60: =I60/E60*F60 -> 4520 | Q60: =J60/E60*F60 -> 9050 | R60: =K60/E60*F60 -> 5573 | S60: =L60/E60*F60 -> 1130.381 | T60: =M60/E60*F60 -> 943.7499 | U60: =N60/E60*F60 -> 629.8047 | V60: =O60/E60*F60 -> 551.3184 | W60: =(H60+L60+M60+N60+O60)/E60*G60 -> 0 | X60: =P60+Q60+R60+S60+T60+U60+V60+W60 -> 22398.254 | Y60: =(P60+Q60)*12% -> 1628.4 | Z60: 0 | AA60: =IF(X60>20000,200,IF(X60>15000,150,0)) -> 200 | AC60: =Y60+Z60+AA60+AB60 -> 1828.4 | AD60: =ROUND(X60-AC60,0) -> 20570 | AE60: =(P60+Q60)*13% -> 1764.1 | AF60: 800 | AG60: =X60+AE60+AF60 -> 24962.354 | AH60: 24962 | AI60: =AH60-AG60 -> -0.354
C61: Carpenter | E61: =SUM(E60) -> 30 | F61: =SUM(F60) -> 30 | G61: =SUM(G60) -> 0 | H61: =SUM(H60) -> 19143 | I61: =SUM(I60) -> 4520 | J61: =SUM(J60) -> 9050 | K61: =SUM(K60) -> 5573 | L61: =SUM(L60) -> 1130.381 | ... AI61: =SUM(AI60) -> -0.354
E62: =E59+E57+E55+E53+E44+E36+E31+E26+E17+E6+E61 -> 1380 | F62: =F59+F57+F55+F53+F44+F36+F31+F26+F17+F6+F61 -> 1380 | G62: =G59+G57+G55+G53+G44+G36+G31+G26+G17+G6+G61 -> 0 | H62: =H59+H57+H55+H53+H44+H36+H31+H26+H17+H6+H61 -> 912504 | I62: =I59+I57+I55+I53+I44+I36+I31+I26+I17+I6+I61 -> 210977 | J62: =J59+J57+J55+J53+J44+J36+J31+J26+J17+J6+J61 -> 416300 | K62: =K59+K57+K55+K53+K44+K36+K31+K26+K17+K6+K61 -> 285227 | L62: =L59+L57+L55+L53+L44+L36+L31+L26+L17+L6+L61 -> 52252.174 | ... AI62: =AI59+AI57+AI55+AI53+AI44+AI36+AI31+AI26+AI17+AI6+AI61 -> -37595.592
T68: =X4 -> GROSS EARNINGS | W68: = | X68: =X62 -> 1066044.1
T69: EMPLOYER PF @13% | W69: = | X69: =AE62 -> 81546.01
T70: EMPLOYER ESI @3.25% | W70: = | X70: =AF62 -> 34054.25
T71: TOTAL COST | W71: = | X71: =SUM(X68:X70) -> 1181644.4
T72: MANAGEMENT FEE 8% | W72: = | X72: =X71*8% -> 94531.55
T73: GRAND TOTAL | W73: = | X73: =X71+X72 -> 1276175.9 | AF73: 18500
AF74: 18000
AF75: 19000
AF76: 18501
AF77: 19000
AF78: 18000
AF79: 18500
AF80: 19000
AF81: 19000
AF82: 19000

Sheet BANK STATEMENT
D4: MIDAS B1&B2 BANK STATEMENT FOR THE MONTH OF JUL-2026
D6: SL. NO | E6: EMP NO. | F6: Name of the Employee | G6: Account No | H6: IFSC Code | I6: Amount
D7: 1 | E7: 11029 | F7: SUDHIR KUMAR RAUTARAY | G7: 5599174559 | H7: UTIB0005151 | I7: =VLOOKUP(E7,PAYSHEET!$B$5:$AF$70,31,0) -> 36000
D8: =D7+1 -> 2 | E8: 10984 | F8: K RAJYALAKSHMI | G8: 309025560518 | H8: RATN0000366 | I8: =VLOOKUP(E8,PAYSHEET!$B$5:$AF$70,31,0) -> 26123
D9: =D8+1 -> 3 | E9: 10976 | F9: KONGANI NARAYANA | G9: 20059012168 | H9: SBIN0011667 | I9: =VLOOKUP(E9,PAYSHEET!$B$5:$AF$70,31,0) -> 27000
D10: =D9+1 -> 4 | E10: 10986 | F10: KHIROD DAS | G10: 35192372300 | H10: SBIN0016125 | I10: =VLOOKUP(E10,PAYSHEET!$B$5:$AF$70,31,0) -> 13979
D11: =D10+1 -> 5 | E11: 10981 | F11: C. GANESH | G11: 40082463078 | H11: SBIN0000834 | I11: =VLOOKUP(E11,PAYSHEET!$B$5:$AF$70,31,0) -> 20568
D12: =D11+1 -> 6 | E12: 11000 | F12: ALLAUDDIN MAINODDIN KHAJURE | G12: 39377880179 | H12: SBIN0013032 | I12: =VLOOKUP(E12,PAYSHEET!$B$5:$AF$70,31,0) -> 25960
D13: =D12+1 -> 7 | E13: 10991 | F13: JOGENDRA SETHI | G13: 20077099524 | H13: SBIN0014183 | I13: =VLOOKUP(E13,PAYSHEET!$B$5:$AF$70,31,0) -> 26000
D14: =D13+1 -> 8 | E14: 10980 | F14: ANURUDHA SAMAL | G14: 23930100011966 | H14: BARB0HATINA | I14: =VLOOKUP(E14,PAYSHEET!$B$5:$AF$70,31,0) -> 4274
D15: =D14+1 -> 9 | E15: 10978 | F15: PABITRA MALIK | G15: 36718981606 | H15: SBIN0002100 | I15: =VLOOKUP(E15,PAYSHEET!$B$5:$AF$70,31,0) -> 24000
D16: =D15+1 -> 10 | E16: 10974 | F16: GADADHAR MALIK | G16: 35352487786 | H16: SBIN0002100 | I16: =VLOOKUP(E16,PAYSHEET!$B$5:$AF$70,31,0) -> 22100
D17: =D16+1 -> 11 | E17: 10983 | F17: SUDHAKAR | G17: 38524408774 | H17: SBIN0015853 | I17: =VLOOKUP(E17,PAYSHEET!$B$5:$AF$70,31,0) -> 4810
D18: =D17+1 -> 12 | E18: 11032 | F18: ANANDA SHA | G18: 50100460685195 | H18: HDFC0000512 | I18: =VLOOKUP(E18,PAYSHEET!$B$5:$AF$70,31,0) -> 22800
D19: =D18+1 -> 13 | E19: 11158 | F19: NARESH DAS | G19: 918010019983214 | H19: UTIB0000679 | I19: =VLOOKUP(E19,PAYSHEET!$B$5:$AF$70,31,0) -> 21300
... D25: =D24+1 -> 19 | E25: 10989 | F25: NAGENDRA BABU | G25: 309025560864 | H25: RATN0000366 | I25: =VLOOKUP(E25,PAYSHEET!$B$5:$AF$70,31,0) -> 27000
D26: =D25+1 -> 20 | E26: 10982 | F26: SAGAR KUMAR BEHERA | G26: 424501504162 | I26: =VLOOKUP(E26,PAYSHEET!$B$5:$AF$70,31,0) -> 25500
D27: =D26+1 -> 21 | E27: 12076 | F27: JALEM ROHAN | G27: 057210100137958 | H27: UBIN0805726 | I27: =VLOOKUP(E27,PAYSHEET!$B$5:$AF$70,31,0) -> 25000
D28: =D27+1 -> 22 | E28: 11376 | F28: J.CHATTYNYA | G28: 50100510147971 | H28: HDFC0008067 | I28: =VLOOKUP(E28,PAYSHEET!$B$5:$AF$70,31,0) -> 22500
D29: =D28+1 -> 23 | E29: 12035 | F29: SAMAR QUADIR | G29: 43175137888 | H29: SBIN0017426 | I29: =VLOOKUP(E29,PAYSHEET!$B$5:$AF$70,31,0) -> 21000
D30: =D29+1 -> 24 | E30: 12141 | F30: BANDARI DHAN RAJ | G30: 1446902842 | H30: KKBK0007463 | I30: =VLOOKUP(E30,PAYSHEET!$B$5:$AF$70,31,0) -> 19258
D31: =D30+1 -> 25 | E31: 12057 | F31: GALLI KIRAN KUMAR | G31: 40990861702 | H31: SBIN0002745 | I31: =VLOOKUP(E31,PAYSHEET!$B$5:$AF$70,31,0) -> 22190
D32: =D31+1 -> 26 | E32: 11572 | F32: KALLOL SEN | G32: 41846566728 | H32: SBIN0007503 | I32: =VLOOKUP(E32,PAYSHEET!$B$5:$AF$70,31,0) -> 22190
D33: =D32+1 -> 27 | E33: 11439 | F33: RAJA MALIK | G33: 43949385299 | H33: SBIN0002100 | I33: =VLOOKUP(E33,PAYSHEET!$B$5:$AF$70,31,0) -> 10426
D34: =D33+1 -> 28 | E34: 10013 | F34: H.PANDA | G34: 004001647503 | I34: =VLOOKUP(E34,PAYSHEET!$B$5:$AF$70,31,0) -> 26000
D35: =D34+1 -> 29 | E35: 11377 | F35: MANOJ KUMAR | G35: 309028388748 | H35: RATN0000366 | I35: =VLOOKUP(E35,PAYSHEET!$B$5:$AF$70,31,0) -> 17753
D36: =D35+1 -> 30 | E36: 1 | F36: BANAVATH BALAJI | G36: 42621662297 | H36: SBIN0020996 | I36: =VLOOKUP(E36,PAYSHEET!$B$5:$AF$70,31,0) -> 17192 | J36: PAID ON 08-08-2027
D37: =D36+1 -> 31 | E37: 2 | F37: GATTU BHANUTEJA | G37: 45263545791 | H37: SBIN0021584 | I37: =VLOOKUP(E37,PAYSHEET!$B$5:$AF$70,31,0) -> 16572
D38: =D37+1 -> 32 | E38: 3 | F38: MERUPULA SANDEEP GOUD | G38: 45412161218 | H38: SBIN0064827 | I38: =VLOOKUP(E38,PAYSHEET!$B$5:$AF$70,31,0) -> 17811
D39: =D38+1 -> 33 | E39: 5 | F39: ALOKA MUDULI | G39: 40911134034 | H39: SBIN0000055 | I39: =VLOOKUP(E39,PAYSHEET!$B$5:$AF$70,31,0) -> 18095
D40: =D39+1 -> 34 | E40: 6 | F40: MD Saleem | G40: 44467464884 | H40: SBIN0016276 | I40: =VLOOKUP(E40,PAYSHEET!$B$5:$AF$70,31,0) -> 14095
D41: =D40+1 -> 35 | E41: 7 | F41: Shaik Shaheed | G41: 017110100089730 | H41: UBIN0801712 | I41: =VLOOKUP(E41,PAYSHEET!$B$5:$AF$70,31,0) -> 14714
D42: =D41+1 -> 36 | E42: 8 | F42: KAZIPETA RAVI KIRAN | G42: 44467656204 | H42: SBIN0020776 | I42: =VLOOKUP(E42,PAYSHEET!$B$5:$AF$70,31,0) -> 6193
D43: =D42+1 -> 37 | E43: 11 | F43: DAGE RAMA KRISHNA | G43: 8813663412 | H43: KKBK0007452 | I43: =VLOOKUP(E43,PAYSHEET!$B$5:$AF$70,31,0) -> 17643
D44: =D43+1 -> 38 | E44: 11476 | F44: HARISH KHAN | G44: 43495405979 | H44: SBIN0014308 | I44: =VLOOKUP(E44,PAYSHEET!$B$5:$AF$70,31,0) -> 16061
D45: =D44+1 -> 39 | E45: 11558 | F45: CHANDRA PRAKASH MOHANTY | G45: 535518210009666 | H45: BKID0005355 | I45: =VLOOKUP(E45,PAYSHEET!$B$5:$AF$70,31,0) -> 2052
D46: =D45+1 -> 40 | E46: 9 | F46: MURALI KRUSHNA | G46: 45225409796 | H46: SBIN0001023 | I46: =VLOOKUP(E46,PAYSHEET!$B$5:$AF$70,31,0) -> 15953
D47: =D46+1 -> 41 | E47: 10 | F47: RAMGIRI SATISH | G47: 10230781622 | H47: IDFB0081802 | I47: =VLOOKUP(E47,PAYSHEET!$B$5:$AF$70,31,0) -> 15333
D48: =D47+1 -> 42 | E48: 12 | F48: Tapas Malik | G48: 45259604549 | H48: SBIN0064827 | I48: =VLOOKUP(E48,PAYSHEET!$B$5:$AF$70,31,0) -> 6677
... D55: =D54+1 -> 49 | E55: 11907 | F55: P.SAI SATHISH | G55: 20515288686 | H55: SBIN0006677 | I55: =VLOOKUP(E55,PAYSHEET!$B$5:$AF$70,31,0) -> 19300
D56: =D69+1 -> 2 | E56: 4 | F56: RAJANIKANT | G56: 309028388863 | H56: RATN0000366 | I56: =VLOOKUP(E56,PAYSHEET!$B$5:$AF$70,31,0) -> 6193 | J56: PAID ON 08-08-2027
D57: =D55+1 -> 50 | E57: 11954 | F57: AKASHSHA | G57: 540810110029964 | H57: BKID0005408 | I57: =VLOOKUP(E57,PAYSHEET!$B$5:$AF$70,31,0) -> 19349
D58: =D57+1 -> 51 | E58: 10990 | F58: MUKESH SRICHANDAN | G58: 35573873665 | H58: SBIN0007343 | I58: =VLOOKUP(E58,PAYSHEET!$B$5:$AF$70,31,0) -> 1400
I59: =SUM(I7:I58) -> 949282 | K59: =I59 -> 949282
K60: =PAYSHEET!AF71 -> 953579
K61: =K59-K60 -> -4297
D62: Prepared By | F62: Verified By | G62: Authorized By | I62: Approved By
D66: HOLD MIDAS B1&B2 BANK STATEMENT FOR THE MONTH OF JUL-2026
D68: SL. NO | E68: EMP NO. | F68: Name of the Employee | G68: Account No | H68: IFSC Code | I68: Amount
D69: 1 | E69: 11958 | F69: M.PRATHAP KUMAR | G69: 2546059375 | H69: KKBK0007822 | I69: =VLOOKUP(E69,PAYSHEET!$B$5:$AF$70,31,0) -> 4297
I70: =SUM(I69:I69) -> 4297
D76: Prepared By | F76: Verified By | G76: Authorized By | I76: Approved By

Sheet PF ESI SUMMARY
C3: PF and ESI Details of Midas Projects Pvt Ltd B1 Building for the month of Apr- 2025
C4: Sl.No | D4: Employee No | E4: Name | F4: PF UAN Number | G4: ESI Number | H4: Gross Wages | I4: BASIC+DA | J4: Employee Share PF (12%) | K4: Employer Share PF (13%) | L4: Total PF | M4: Employee Share ESI (0.75%) | N4: Employer Share ESI (3.25%) | O4: Total ESI | P4: PROF TAX
C5: 1 | D5: 11029 | E5: SUDHIR KUMAR RAUTARAY | F5: =VLOOKUP(D5,'[1]CHAN PF'!$A$2:$B$536,2,0) -> 100776108439 | G5: NA | H5: =ROUND(N5*100/3.25,0) -> 1107692 | I5: =ROUND(J5*100/12,0) -> 0 | J5: =VLOOKUP(D5,PAYSHEET!B$5:AA$84,24,0) -> 0 | K5: =I5*13% -> 0 | L5: =J5+K5 -> 0 | M5: =ROUND(VLOOKUP(D5,PAYSHEET!B$5:AB$70,25,0),0) -> 38000 | N5: =VLOOKUP(D5,PAYSHEET!B$5:AH$70,31,0) -> 36000 | O5: =M5+N5 -> 74000 | P5: =VLOOKUP(D5,PAYSHEET!B$5:AC$70,26,0) -> 1800
C6: =C5+1 -> 2 | D6: 10984 | E6: K RAJYALAKSHMI | F6: =VLOOKUP(D6,'[1]CHAN PF'!$A$2:$B$536,2,0) -> 101433827014 | G6: NA | H6: =ROUND(N6*100/3.25,0) -> 803785 | I6: =ROUND(J6*100/12,0) -> 0 | J6: =VLOOKUP(D6,PAYSHEET!B$5:AA$84,24,0) -> 0 | K6: =I6*13% -> 0 | L6: =J6+K6 -> 0 | M6: =ROUND(VLOOKUP(D6,PAYSHEET!B$5:AB$70,25,0),0) -> 28064 | N6: =VLOOKUP(D6,PAYSHEET!B$5:AH$70,31,0) -> 26123 | O6: =M6+N6 -> 54187 | P6: =VLOOKUP(D6,PAYSHEET!B$5:AC$70,26,0) -> 1741.9355
C7: =C6+1 -> 3 | D7: 10976 | E7: KONGANI NARAYANA | F7: =VLOOKUP(D7,'[1]CHAN PF'!$A$2:$B$536,2,0) -> 101132041760 | G7: NA | H7: =ROUND(N7*100/3.25,0) -> 830769 | I7: =ROUND(J7*100/12,0) -> 0 | J7: =VLOOKUP(D7,PAYSHEET!B$5:AA$84,24,0) -> 0 | K7: =I7*13% -> 0 | L7: =J7+K7 -> 0 | M7: =ROUND(VLOOKUP(D7,PAYSHEET!B$5:AB$70,25,0),0) -> 29000 | N7: =VLOOKUP(D7,PAYSHEET!B$5:AH$70,31,0) -> 27000 | O7: =M7+N7 -> 56000 | P7: =VLOOKUP(D7,PAYSHEET!B$5:AC$70,26,0) -> 1800
C8: =C7+1 -> 4 | D8: 10986 | E8: KHIROD DAS | F8: =VLOOKUP(D8,'[1]CHAN PF'!$A$2:$B$536,2,0) -> 101303714313 | G8: NA | H8: =ROUND(N8*100/3.25,0) -> 430123 | I8: =ROUND(J8*100/12,0) -> 0 | J8: =VLOOKUP(D8,PAYSHEET!B$5:AA$84,24,0) -> 0 | K8: =I8*13% -> 0 | L8: =J8+K8 -> 0 | M8: =ROUND(VLOOKUP(D8,PAYSHEET!B$5:AB$70,25,0),0) -> 15000 | N8: =VLOOKUP(D8,PAYSHEET!B$5:AH$70,31,0) -> 13979 | O8: =M8+N8 -> 28979 | P8: =VLOOKUP(D8,PAYSHEET!B$5:AC$70,26,0) -> 870.96774
C9: =C8+1 -> 5 | D9: 10989 | E9: NAGENDRA | F9: =VLOOKUP(D9,'[1]CHAN PF'!$A$2:$B$536,2,0) -> 101366451264 | G9: NA | H9: =ROUND(N9*100/3.25,0) -> 830769 | I9: =ROUND(J9*100/12,0) -> 0 | J9: =VLOOKUP(D9,PAYSHEET!B$5:AA$84,24,0) -> 0 | K9: =I9*13% -> 0 | L9: =J9+K9 -> 0 | M9: =ROUND(VLOOKUP(D9,PAYSHEET!B$5:AB$70,25,0),0) -> 29000 | N9: =VLOOKUP(D9,PAYSHEET!B$5:AH$70,31,0) -> 27000 | O9: =M9+N9 -> 56000 | P9: =VLOOKUP(D9,PAYSHEET!B$5:AC$70,26,0) -> 1800
C10: =C9+1 -> 6 | D10: 10988 | E10: KAKARLA BASHA | F10: =VLOOKUP(D10,'[1]CHAN PF'!$A$2:$B$536,2,0) -> 101419332060 | G10: NA | H10: =ROUND(N10*100/3.25,0) -> #N/A | I10: =ROUND(J10*100/12,0) -> #N/A | J10: =VLOOKUP(D10,PAYSHEET!B$5:AA$84,24,0) -> #N/A | K10: =I10*13% -> #N/A | L10: =J10+K10 -> #N/A | M10: =ROUND(VLOOKUP(D10,PAYSHEET!B$5:AB$70,25,0),0) -> #N/A | N10: =VLOOKUP(D10,PAYSHEET!B$5:AH$70,31,0) -> #N/A | O10: =M10+N10 -> #N/A | P10: =VLOOKUP(D10,PAYSHEET!B$5:AC$70,26,0) -> #N/A
C11: =C10+1 -> 7 | D11: 10979 | E11: B APPANA | F11: =VLOOKUP(D11,'[1]CHAN PF'!$A$2:$B$536,2,0) -> 101460853033 | G11: NA | H11: =ROUND(N11*100/3.25,0) -> #N/A | I11: =ROUND(J11*100/12,0) -> #N/A | J11: =VLOOKUP(D11,PAYSHEET!B$5:AA$84,24,0) -> #N/A | K11: =I11*13% -> #N/A | L11: =J11+K11 -> #N/A | M11: =ROUND(VLOOKUP(D11,PAYSHEET!B$5:AB$70,25,0),0) -> #N/A | N11: =VLOOKUP(D11,PAYSHEET!B$5:AH$70,31,0) -> #N/A | O11: =M11+N11 -> #N/A | P11: =VLOOKUP(D11,PAYSHEET!B$5:AC$70,26,0) -> #N/A
C12: =C11+1 -> 8 | D12: 10982 | E12: SAGAR KUMAR BEHERA | F12: =VLOOKUP(D12,'[1]CHAN PF'!$A$2:$B$536,2,0) -> 101296008357 | G12: NA | H12: =ROUND(N12*100/3.25,0) -> 784615 | I12: =ROUND(J12*100/12,0) -> 0 | J12: =VLOOKUP(D12,PAYSHEET!B$5:AA$84,24,0) -> 0 | K12: =I12*13% -> 0 | L12: =J12+K12 -> 0 | M12: =ROUND(VLOOKUP(D12,PAYSHEET!B$5:AB$70,25,0),0) -> 27500 | N12: =VLOOKUP(D12,PAYSHEET!B$5:AH$70,31,0) -> 25500 | O12: =M12+N12 -> 53000 | P12: =VLOOKUP(D12,PAYSHEET!B$5:AC$70,26,0) -> 1800
C13: =C12+1 -> 9 | D13: 11022 | E13: P SADDAM | F13: =VLOOKUP(D13,'[1]CHAN PF'!$A$2:$B$536,2,0) -> 101467151132 | G13: NA | H13: =ROUND(N13*100/3.25,0) -> #N/A | I13: =ROUND(J13*100/12,0) -> #N/A | J13: =VLOOKUP(D13,PAYSHEET!B$5:AA$84,24,0) -> #N/A | K13: =I13*13% -> #N/A | L13: =J13+K13 -> #N/A | M13: =ROUND(VLOOKUP(D13,PAYSHEET!B$5:AB$70,25,0),0) -> #N/A | N13: =VLOOKUP(D13,PAYSHEET!B$5:AH$70,31,0) -> #N/A | O13: =M13+N13 -> #N/A | P13: =VLOOKUP(D13,PAYSHEET!B$5:AC$70,26,0) -> #N/A
C14: =C13+1 -> 10 | D14: 10990 | E14: MUKESH SRICHANDAN | F14: =VLOOKUP(D14,'[1]CHAN PF'!$A$2:$B$536,2,0) -> 101881581733 | G14: NA | H14: =ROUND(N14*100/3.25,0) -> 43077 | I14: =ROUND(J14*100/12,0) -> 0 | J14: =VLOOKUP(D14,PAYSHEET!B$5:AA$84,24,0) -> 0 | K14: =I14*13% -> 0 | L14: =J14+K14 -> 0 | M14: =ROUND(VLOOKUP(D14,PAYSHEET!B$5:AB$70,25,0),0) -> 1516 | N14: =VLOOKUP(D14,PAYSHEET!B$5:AH$70,31,0) -> 1400 | O14: =M14+N14 -> 2916 | P14: =VLOOKUP(D14,PAYSHEET!B$5:AC$70,26,0) -> 116.12903
C15: =C14+1 -> 11 | D15: 10981 | E15: C. GANESH | F15: =VLOOKUP(D15,'[1]CHAN PF'!$A$2:$B$536,2,0) -> 101730007908 | G15: NA | H15: =ROUND(N15*100/3.25,0) -> 632862 | I15: =ROUND(J15*100/12,0) -> 0 | J15: =VLOOKUP(D15,PAYSHEET!B$5:AA$84,24,0) -> 0 | K15: =I15*13% -> 0 | L15: =J15+K15 -> 0 | M15: =ROUND(VLOOKUP(D15,PAYSHEET!B$5:AB$70,25,0),0) -> 22452 | N15: =VLOOKUP(D15,PAYSHEET!B$5:AH$70,31,0) -> 20568 | O15: =M15+N15 -> 43020 | P15: =VLOOKUP(D15,PAYSHEET!B$5:AC$70,26,0) -> 1683.871
C16: =C15+1 -> 12 | D16: 11000 | E16: ALLAUDDIN MAINODDIN KHAJURE | F16: =VLOOKUP(D16,'[1]CHAN PF'!$A$2:$B$536,2,0) -> 101617561953 | G16: NA | H16: =ROUND(N16*100/3.25,0) -> 798769 | I16: =ROUND(J16*100/12,0) -> 0 | J16: =VLOOKUP(D16,PAYSHEET!B$5:AA$84,24,0) -> 0 | K16: =I16*13% -> 0 | L16: =J16+K16 -> 0 | M16: =ROUND(VLOOKUP(D16,PAYSHEET!B$5:AB$70,25,0),0) -> 27960 | N16: =VLOOKUP(D16,PAYSHEET!B$5:AH$70,31,0) -> 25960 | O16: =M16+N16 -> 53920 | P16: =VLOOKUP(D16,PAYSHEET!B$5:AC$70,26,0) -> 1800
C17: =C16+1 -> 13 | D17: 11026 | E17: JAGADEESH | F17: =VLOOKUP(D17,'[1]CHAN PF'!$A$2:$B$536,2,0) -> 101807637370 | G17: NA | H17: =ROUND(N17*100/3.25,0) -> #N/A | I17: =ROUND(J17*100/12,0) -> #N/A | J17: =VLOOKUP(D17,PAYSHEET!B$5:AA$84,24,0) -> #N/A | K17: =I17*13% -> #N/A | L17: =J17+K17 -> #N/A | M17: =ROUND(VLOOKUP(D17,PAYSHEET!B$5:AB$70,25,0),0) -> #N/A | N17: =VLOOKUP(D17,PAYSHEET!B$5:AH$70,31,0) -> #N/A | O17: =M17+N17 -> #N/A | P17: =VLOOKUP(D17,PAYSHEET!B$5:AC$70,26,0) -> #N/A
... C28: =C27+1 -> 24 | D28: 11058 | E28: P MOKHA LINGAM | F28: =VLOOKUP(D28,'[1]CHAN PF'!$A$2:$B$536,2,0) -> 101818246573 | G28: NA | H28: =ROUND(N28*100/3.25,0) -> #N/A | I28: =ROUND(J28*100/12,0) -> #N/A | J28: =VLOOKUP(D28,PAYSHEET!B$5:AA$84,24,0) -> #N/A | K28: =I28*13% -> #N/A | L28: =J28+K28 -> #N/A | M28: =ROUND(VLOOKUP(D28,PAYSHEET!B$5:AB$70,25,0),0) -> #N/A | N28: =VLOOKUP(D28,PAYSHEET!B$5:AH$70,31,0) -> #N/A | O28: =M28+N28 -> #N/A | P28: =VLOOKUP(D28,PAYSHEET!B$5:AC$70,26,0) -> #N/A
C29: =C28+1 -> 25 | D29: 11049 | E29: AADHI NARAYANA | F29: =VLOOKUP(D29,'[1]CHAN PF'!$A$2:$B$536,2,0) -> 102095604570 | G29: =VLOOKUP(D29,[1]ESIC!$C$3:$D$324,2,0) -> 5221153012 | H29: =ROUND(N29*100/3.25,0) -> #N/A | I29: =ROUND(J29*100/12,0) -> #N/A | J29: =VLOOKUP(D29,PAYSHEET!B$5:AA$84,24,0) -> #N/A | K29: =I29*13% -> #N/A | L29: =J29+K29 -> #N/A | M29: =ROUND(VLOOKUP(D29,PAYSHEET!B$5:AB$70,25,0),0) -> #N/A | N29: =VLOOKUP(D29,PAYSHEET!B$5:AH$70,31,0) -> #N/A | O29: =M29+N29 -> #N/A | P29: =VLOOKUP(D29,PAYSHEET!B$5:AC$70,26,0) -> #N/A
C30: =C29+1 -> 26 | D30: 11032 | E30: ANANDA SHA | F30: =VLOOKUP(D30,'[1]CHAN PF'!$A$2:$B$536,2,0) -> 101760846764 | G30: NA | H30: =ROUND(N30*100/3.25,0) -> 701538 | I30: =ROUND(J30*100/12,0) -> 0 | J30: =VLOOKUP(D30,PAYSHEET!B$5:AA$84,24,0) -> 0 | K30: =I30*13% -> 0 | L30: =J30+K30 -> 0 | M30: =ROUND(VLOOKUP(D30,PAYSHEET!B$5:AB$70,25,0),0) -> 24800 | N30: =VLOOKUP(D30,PAYSHEET!B$5:AH$70,31,0) -> 22800 | O30: =M30+N30 -> 47600 | P30: =VLOOKUP(D30,PAYSHEET!B$5:AC$70,26,0) -> 1800
C31: =C30+1 -> 27 | D31: 11193 | E31: T.ARCHANA | F31: =VLOOKUP(D31,'[1]CHAN PF'!$A$2:$B$536,2,0) -> 102136413687 | G31: =VLOOKUP(D31,[1]ESIC!$C$3:$D$324,2,0) -> 5221415907 | H31: =ROUND(N31*100/3.25,0) -> #N/A | I31: =ROUND(J31*100/12,0) -> #N/A | J31: =VLOOKUP(D31,PAYSHEET!B$5:AA$84,24,0) -> #N/A | K31: =I31*13% -> #N/A | L31: =J31+K31 -> #N/A | M31: =ROUND(VLOOKUP(D31,PAYSHEET!B$5:AB$70,25,0),0) -> #N/A | N31: =VLOOKUP(D31,PAYSHEET!B$5:AH$70,31,0) -> #N/A | O31: =M31+N31 -> #N/A | P31: =VLOOKUP(D31,PAYSHEET!B$5:AC$70,26,0) -> #N/A
C32: =C31+1 -> 28 | D32: 11158 | E32: NARESH DAS | F32: =VLOOKUP(D32,'[1]CHAN PF'!$A$2:$B$536,2,0) -> 101220132820 | G32: =VLOOKUP(D32,[1]ESIC!$C$3:$D$324,2,0) -> 5221391571 | H32: =ROUND(N32*100/3.25,0) -> 655385 | I32: =ROUND(J32*100/12,0) -> 0 | J32: =VLOOKUP(D32,PAYSHEET!B$5:AA$84,24,0) -> 0 | K32: =I32*13% -> 0 | L32: =J32+K32 -> 0 | M32: =ROUND(VLOOKUP(D32,PAYSHEET!B$5:AB$70,25,0),0) -> 23300 | N32: =VLOOKUP(D32,PAYSHEET!B$5:AH$70,31,0) -> 21300 | O32: =M32+N32 -> 44600 | P32: =VLOOKUP(D32,PAYSHEET!B$5:AC$70,26,0) -> 1800
C33: =C32+1 -> 29 | D33: 11215 | E33: K.RAMESH | F33: =VLOOKUP(D33,'[1]CHAN PF'!$A$2:$B$536,2,0) -> 101817835987 | G33: NA | H33: =ROUND(N33*100/3.25,0) -> #N/A | I33: =ROUND(J33*100/12,0) -> #N/A | J33: =VLOOKUP(D33,PAYSHEET!B$5:AA$84,24,0) -> #N/A | K33: =I33*13% -> #N/A | L33: =J33+K33 -> #N/A | M33: =ROUND(VLOOKUP(D33,PAYSHEET!B$5:AB$70,25,0),0) -> #N/A | N33: =VLOOKUP(D33,PAYSHEET!B$5:AH$70,31,0) -> #N/A | O33: =M33+N33 -> #N/A | P33: =VLOOKUP(D33,PAYSHEET!B$5:AC$70,26,0) -> #N/A
C34: =C33+1 -> 30 | D34: 10339 | E34: V.SRIKANTH | F34: =VLOOKUP(D34,'[1]CHAN PF'!$A$2:$B$536,2,0) -> 101401592178 | G34: NA | H34: =ROUND(N34*100/3.25,0) -> #N/A | I34: =ROUND(J34*100/12,0) -> #N/A | J34: =VLOOKUP(D34,PAYSHEET!B$5:AA$84,24,0) -> #N/A | K34: =I34*13% -> #N/A | L34: =J34+K34 -> #N/A | M34: =ROUND(VLOOKUP(D34,PAYSHEET!B$5:AB$70,25,0),0) -> #N/A | N34: =VLOOKUP(D34,PAYSHEET!B$5:AH$70,31,0) -> #N/A | O34: =M34+N34 -> #N/A | P34: =VLOOKUP(D34,PAYSHEET!B$5:AC$70,26,0) -> #N/A
C35: =C34+1 -> 31 | D35: 11217 | E35: K.TARUN | F35: =VLOOKUP(D35,'[1]CHAN PF'!$A$2:$B$536,2,0) -> 102106814769 | G35: =VLOOKUP(D35,[1]ESIC!$C$3:$D$324,2,0) -> 5221038656 | H35: =ROUND(N35*100/3.25,0) -> #N/A | I35: =ROUND(J35*100/12,0) -> #N/A | J35: =VLOOKUP(D35,PAYSHEET!B$5:AA$84,24,0) -> #N/A | K35: =I35*13% -> #N/A | L35: =J35+K35 -> #N/A | M35: =ROUND(VLOOKUP(D35,PAYSHEET!B$5:AB$70,25,0),0) -> #N/A | N35: =VLOOKUP(D35,PAYSHEET!B$5:AH$70,31,0) -> #N/A | O35: =M35+N35 -> #N/A | P35: =VLOOKUP(D35,PAYSHEET!B$5:AC$70,26,0) -> #N/A
C36: =C35+1 -> 32 | D36: 11203 | E36: BISWAJIT SAHOO | F36: =VLOOKUP(D36,'[1]CHAN PF'!$A$2:$B$536,2,0) -> 102140355601 | G36: =VLOOKUP(D36,[1]ESIC!$C$3:$D$324,2,0) -> 5221514932 | H36: =ROUND(N36*100/3.25,0) -> 479354 | I36: =ROUND(J36*100/12,0) -> 0 | J36: =VLOOKUP(D36,PAYSHEET!B$5:AA$84,24,0) -> 0 | K36: =I36*13% -> 0 | L36: =J36+K36 -> 0 | M36: =ROUND(VLOOKUP(D36,PAYSHEET!B$5:AB$70,25,0),0) -> 17065 | N36: =VLOOKUP(D36,PAYSHEET!B$5:AH$70,31,0) -> 15579 | O36: =M36+N36 -> 32644 | P36: =VLOOKUP(D36,PAYSHEET!B$5:AC$70,26,0) -> 1335.4839
C37: =C36+1 -> 33 | D37: 11214 | E37: M.LAXMINARAYANA | F37: =VLOOKUP(D37,'[1]CHAN PF'!$A$2:$B$536,2,0) -> 102141445630 | G37: NA | H37: =ROUND(N37*100/3.25,0) -> 682769 | I37: =ROUND(J37*100/12,0) -> 0 | J37: =VLOOKUP(D37,PAYSHEET!B$5:AA$84,24,0) -> 0 | K37: =I37*13% -> 0 | L37: =J37+K37 -> 0 | M37: =ROUND(VLOOKUP(D37,PAYSHEET!B$5:AB$70,25,0),0) -> 24190 | N37: =VLOOKUP(D37,PAYSHEET!B$5:AH$70,31,0) -> 22190 | O37: =M37+N37 -> 46380 | P37: =VLOOKUP(D37,PAYSHEET!B$5:AC$70,26,0) -> 1800
C38: =C37+1 -> 34 | D38: 11246 | E38: R.HEMANTH | F38: =VLOOKUP(D38,'[1]CHAN PF'!$A$2:$B$536,2,0) -> 101858145524 | G38: =VLOOKUP(D38,[1]ESIC!$C$3:$D$324,2,0) -> 5221618572 | H38: =ROUND(N38*100/3.25,0) -> #N/A | I38: =ROUND(J38*100/12,0) -> #N/A | J38: =VLOOKUP(D38,PAYSHEET!B$5:AA$84,24,0) -> #N/A | K38: =I38*13% -> #N/A | L38: =J38+K38 -> #N/A | M38: =ROUND(VLOOKUP(D38,PAYSHEET!B$5:AB$70,25,0),0) -> #N/A | N38: =VLOOKUP(D38,PAYSHEET!B$5:AH$70,31,0) -> #N/A | O38: =M38+N38 -> #N/A | P38: =VLOOKUP(D38,PAYSHEET!B$5:AC$70,26,0) -> #N/A
C39: =C38+1 -> 35 | D39: 11241 | E39: SHAHBDDIN | F39: =VLOOKUP(D39,'[1]CHAN PF'!$A$2:$B$536,2,0) -> 102153844190 | G39: =VLOOKUP(D39,[1]ESIC!$C$3:$D$324,2,0) -> 5221635639 | H39: =ROUND(N39*100/3.25,0) -> #N/A | I39: =ROUND(J39*100/12,0) -> #N/A | J39: =VLOOKUP(D39,PAYSHEET!B$5:AA$84,24,0) -> #N/A | K39: =I39*13% -> #N/A | L39: =J39+K39 -> #N/A | M39: =ROUND(VLOOKUP(D39,PAYSHEET!B$5:AB$70,25,0),0) -> #N/A | N39: =VLOOKUP(D39,PAYSHEET!B$5:AH$70,31,0) -> #N/A | O39: =M39+N39 -> #N/A | P39: =VLOOKUP(D39,PAYSHEET!B$5:AC$70,26,0) -> #N/A
C40: =C39+1 -> 36 | D40: 11313 | E40: VASA SHIVA KUMARM | F40: =VLOOKUP(D40,'[1]CHAN PF'!$A$2:$B$536,2,0) -> 101945909041 | G40: =VLOOKUP(D40,[1]ESIC!$C$3:$D$324,2,0) -> 5221821075 | H40: =ROUND(N40*100/3.25,0) -> #N/A | I40: =ROUND(J40*100/12,0) -> #N/A | J40: =VLOOKUP(D40,PAYSHEET!B$5:AA$84,24,0) -> #N/A | K40: =I40*13% -> #N/A | L40: =J40+K40 -> #N/A | M40: =ROUND(VLOOKUP(D40,PAYSHEET!B$5:AB$70,25,0),0) -> #N/A | N40: =VLOOKUP(D40,PAYSHEET!B$5:AH$70,31,0) -> #N/A | O40: =M40+N40 -> #N/A | P40: =VLOOKUP(D40,PAYSHEET!B$5:AC$70,26,0) -> #N/A
C41: =C40+1 -> 37 | D41: 11311 | E41: MOTUPALLI RAVI SANKARA DURGA | F41: =VLOOKUP(D41,'[1]CHAN PF'!$A$2:$B$536,2,0) -> 101109085478 | G41: =VLOOKUP(D41,[1]ESIC!$C$3:$D$324,2,0) -> 5221751222 | H41: =ROUND(N41*100/3.25,0) -> 633846 | I41: =ROUND(J41*100/12,0) -> 0 | J41: =VLOOKUP(D41,PAYSHEET!B$5:AA$84,24,0) -> 0 | K41: =I41*13% -> 0 | L41: =J41+K41 -> 0 | M41: =ROUND(VLOOKUP(D41,PAYSHEET!B$5:AB$70,25,0),0) -> 22600 | N41: =VLOOKUP(D41,PAYSHEET!B$5:AH$70,31,0) -> 20600 | O41: =M41+N41 -> 43200 | P41: =VLOOKUP(D41,PAYSHEET!B$5:AC$70,26,0) -> 1800
C42: =C41+1 -> 38 | D42: 10492 | E42: SIRAJ | F42: =VLOOKUP(D42,'[1]CHAN PF'!$A$2:$B$536,2,0) -> 101925800595 | G42: =VLOOKUP(D42,[1]ESIC!$C$3:$D$324,2,0) -> 5220323113 | H42: =ROUND(N42*100/3.25,0) -> #N/A | I42: =ROUND(J42*100/12,0) -> #N/A | J42: =VLOOKUP(D42,PAYSHEET!B$5:AA$84,24,0) -> #N/A | K42: =I42*13% -> #N/A | L42: =J42+K42 -> #N/A | M42: =ROUND(VLOOKUP(D42,PAYSHEET!B$5:AB$70,25,0),0) -> #N/A | N42: =VLOOKUP(D42,PAYSHEET!B$5:AH$70,31,0) -> #N/A | O42: =M42+N42 -> #N/A | P42: =VLOOKUP(D42,PAYSHEET!B$5:AC$70,26,0) -> #N/A
C43: =C42+1 -> 39 | D43: 11273 | E43: CHANDRA SHAKHER | F43: =VLOOKUP(D43,'[1]CHAN PF'!$A$2:$B$536,2,0) -> 101331571871 | G43: NA | H43: =ROUND(N43*100/3.25,0) -> 661538 | I43: =ROUND(J43*100/12,0) -> 0 | J43: =VLOOKUP(D43,PAYSHEET!B$5:AA$84,24,0) -> 0 | K43: =I43*13% -> 0 | L43: =J43+K43 -> 0 | M43: =ROUND(VLOOKUP(D43,PAYSHEET!B$5:AB$70,25,0),0) -> 23500 | N43: =VLOOKUP(D43,PAYSHEET!B$5:AH$70,31,0) -> 21500 | O43: =M43+N43 -> 45000 | P43: =VLOOKUP(D43,PAYSHEET!B$5:AC$70,26,0) -> 1800
C44: =C43+1 -> 40 | D44: 11276 | E44: GOPAL ROUT | F44: =VLOOKUP(D44,'[1]CHAN PF'!$A$2:$B$536,2,0) -> 102075233629 | G44: NA | H44: =ROUND(N44*100/3.25,0) -> 689231 | I44: =ROUND(J44*100/12,0) -> 0 | J44: =VLOOKUP(D44,PAYSHEET!B$5:AA$84,24,0) -> 0 | K44: =I44*13% -> 0 | L44: =J44+K44 -> 0 | M44: =ROUND(VLOOKUP(D44,PAYSHEET!B$5:AB$70,25,0),0) -> 24400 | N44: =VLOOKUP(D44,PAYSHEET!B$5:AH$70,31,0) -> 22400 | O44: =M44+N44 -> 46800 | P44: =VLOOKUP(D44,PAYSHEET!B$5:AC$70,26,0) -> 1800
C45: =C44+1 -> 41 | D45: 10312 | E45: T.BALAJI | F45: =VLOOKUP(D45,'[1]CHAN PF'!$A$2:$B$536,2,0) -> 101810762450 | G45: NA | H45: =ROUND(N45*100/3.25,0) -> #N/A | I45: =ROUND(J45*100/12,0) -> #N/A | J45: =VLOOKUP(D45,PAYSHEET!B$5:AA$84,24,0) -> #N/A | K45: =I45*13% -> #N/A | L45: =J45+K45 -> #N/A | M45: =ROUND(VLOOKUP(D45,PAYSHEET!B$5:AB$70,25,0),0) -> #N/A | N45: =VLOOKUP(D45,PAYSHEET!B$5:AH$70,31,0) -> #N/A | O45: =M45+N45 -> #N/A | P45: =VLOOKUP(D45,PAYSHEET!B$5:AC$70,26,0) -> #N/A
C46: =C45+1 -> 42 | D46: 11337 | E46: A.JITHENDER KUMAR | F46: =VLOOKUP(D46,'[1]CHAN PF'!$A$2:$B$536,2,0) -> 101494571258 | G46: NA | H46: =ROUND(N46*100/3.25,0) -> #N/A | I46: =ROUND(J46*100/12,0) -> #N/A | J46: =VLOOKUP(D46,PAYSHEET!B$5:AA$84,24,0) -> #N/A | K46: =I46*13% -> #N/A | L46: =J46+K46 -> #N/A | M46: =ROUND(VLOOKUP(D46,PAYSHEET!B$5:AB$70,25,0),0) -> #N/A | N46: =VLOOKUP(D46,PAYSHEET!B$5:AH$70,31,0) -> #N/A | O46: =M46+N46 -> #N/A | P46: =VLOOKUP(D46,PAYSHEET!B$5:AC$70,26,0) -> #N/A
C47: =C46+1 -> 43 | D47: 11341 | E47: P.SRINIVAS | F47: =VLOOKUP(D47,'[1]CHAN PF'!$A$2:$B$536,2,0) -> 102182356204 | G47: =VLOOKUP(D47,[1]ESIC!$C$3:$D$324,2,0) -> 5221882923 | H47: =ROUND(N47*100/3.25,0) -> #N/A | I47: =ROUND(J47*100/12,0) -> #N/A | J47: =VLOOKUP(D47,PAYSHEET!B$5:AA$84,24,0) -> #N/A | K47: =I47*13% -> #N/A | L47: =J47+K47 -> #N/A | M47: =ROUND(VLOOKUP(D47,PAYSHEET!B$5:AB$70,25,0),0) -> #N/A | N47: =VLOOKUP(D47,PAYSHEET!B$5:AH$70,31,0) -> #N/A | O47: =M47+N47 -> #N/A | P47: =VLOOKUP(D47,PAYSHEET!B$5:AC$70,26,0) -> #N/A
C48: =C47+1 -> 44 | D48: 1 | E48: MOHMMED AMIR | F48: NA | G48: NA | H48: =ROUND(N48*100/3.25,0) -> 528985 | I48: =ROUND(J48*100/12,0) -> 0 | J48: =VLOOKUP(D48,PAYSHEET!B$5:AA$84,24,0) -> 0 | K48: =I48*13% -> 0 | L48: =J48+K48 -> 0 | M48: =ROUND(VLOOKUP(D48,PAYSHEET!B$5:AB$70,25,0),0) -> 19111 | N48: =VLOOKUP(D48,PAYSHEET!B$5:AH$70,31,0) -> 17192 | O48: =M48+N48 -> 36303 | P48: =VLOOKUP(D48,PAYSHEET!B$5:AC$70,26,0) -> 1625.8065
C49: =C48+1 -> 45 | D49: 2 | E49: G.SHANMUKHA RAO | F49: NA | G49: NA | H49: =ROUND(N49*100/3.25,0) -> 509908 | I49: =ROUND(J49*100/12,0) -> 0 | J49: =VLOOKUP(D49,PAYSHEET!B$5:AA$84,24,0) -> 0 | K49: =I49*13% -> 0 | L49: =J49+K49 -> 0 | M49: =ROUND(VLOOKUP(D49,PAYSHEET!B$5:AB$70,25,0),0) -> 18428 | N49: =VLOOKUP(D49,PAYSHEET!B$5:AH$70,31,0) -> 16572 | O49: =M49+N49 -> 35000 | P49: =VLOOKUP(D49,PAYSHEET!B$5:AC$70,26,0) -> 1567.7419
C50: =C49+1 -> 46 | D50: 11389 | E50: ARIF | F50: =VLOOKUP(D50,'[1]CHAN PF'!$A$2:$B$536,2,0) -> 102193316312 | G50: NA | H50: =ROUND(N50*100/3.25,0) -> #N/A | I50: =ROUND(J50*100/12,0) -> #N/A | J50: =VLOOKUP(D50,PAYSHEET!B$5:AA$84,24,0) -> #N/A | K50: =I50*13% -> #N/A | L50: =J50+K50 -> #N/A | M50: =ROUND(VLOOKUP(D50,PAYSHEET!B$5:AB$70,25,0),0) -> #N/A | N50: =VLOOKUP(D50,PAYSHEET!B$5:AH$70,31,0) -> #N/A | O50: =M50+N50 -> #N/A | P50: =VLOOKUP(D50,PAYSHEET!B$5:AC$70,26,0) -> #N/A
H51: =SUBTOTAL(9,H5:H50) -> #N/A | I51: =SUBTOTAL(9,I5:I50) -> #N/A | J51: =SUBTOTAL(9,J5:J50) -> #N/A | K51: =SUBTOTAL(9,K5:K50) -> #N/A | L51: =SUBTOTAL(9,L5:L50) -> #N/A | M51: =SUBTOTAL(9,M5:M50) -> #N/A | N51: =SUBTOTAL(9,N5:N50) -> #N/A | O51: =SUBTOTAL(9,O5:O50) -> #N/A | P51: =SUBTOTAL(9,P5:P50) -> #N/A
C55: Note: The PF and ESI challans for the month of Apr-2025 were paid on 16/05/2025 vide TRRN no: 1202505025534 and ESIC Challan no: 05225116525402
C63: =C7+1 -> 4 | D63: 10987 | E63: KANNAIAH | F63: 101354500139 | G63: 5214479356 | H63: =ROUND(N63*100/3.25,0) -> #N/A | I63: =ROUND(J63*100/12,0) -> #N/A | J63: =VLOOKUP(D63,PAYSHEET!B$5:AA$84,24,0) -> #N/A | K63: =I63*13% -> #N/A | L63: =J63+K63 -> #N/A | M63: =ROUND(VLOOKUP(D63,PAYSHEET!B$5:AB$70,25,0),0) -> #N/A | N63: =VLOOKUP(D63,PAYSHEET!B$5:AH$70,31,0) -> #N/A | O63: =M63+N63 -> #N/A | P63: =VLOOKUP(D63,PAYSHEET!B$5:AC$70,26,0) -> #N/A
C64: =C10+1 -> 7 | D64: 11002 | E64: A NARESH | F64: 101247198972 | G64: 5218632918 | H64: =ROUND(N64*100/3.25,0) -> #N/A | I64: =ROUND(J64*100/12,0) -> #N/A | J64: =VLOOKUP(D64,PAYSHEET!B$5:AA$84,24,0) -> #N/A | K64: =I64*13% -> #N/A | L64: =J64+K64 -> #N/A | M64: =ROUND(VLOOKUP(D64,PAYSHEET!B$5:AB$70,25,0),0) -> #N/A | N64: =VLOOKUP(D64,PAYSHEET!B$5:AH$70,31,0) -> #N/A | O64: =M64+N64 -> #N/A | P64: =VLOOKUP(D64,PAYSHEET!B$5:AC$70,26,0) -> #N/A
C65: =C64+1 -> 8 | D65: 11030 | E65: VENKATESWARLU | F65: 101195365890 | G65: 5218814959 | H65: =ROUND(N65*100/3.25,0) -> #N/A | I65: =ROUND(J65*100/12,0) -> #N/A | J65: =VLOOKUP(D65,PAYSHEET!B$5:AA$84,24,0) -> #N/A | K65: =I65*13% -> #N/A | L65: =J65+K65 -> #N/A | M65: =ROUND(VLOOKUP(D65,PAYSHEET!B$5:AB$70,25,0),0) -> #N/A | N65: =VLOOKUP(D65,PAYSHEET!B$5:AH$70,31,0) -> #N/A | O65: =M65+N65 -> #N/A | P65: =VLOOKUP(D65,PAYSHEET!B$5:AC$70,26,0) -> #N/A
C66: =C65+1 -> 9 | D66: 10970 | E66: K SAIBABA | F66: 101397264446 | G66: 5219189859 | H66: =ROUND(N66*100/3.25,0) -> #N/A | I66: =ROUND(J66*100/12,0) -> #N/A | J66: =VLOOKUP(D66,PAYSHEET!B$5:AA$84,24,0) -> #N/A | K66: =I66*13% -> #N/A | L66: =J66+K66 -> #N/A | M66: =ROUND(VLOOKUP(D66,PAYSHEET!B$5:AB$70,25,0),0) -> #N/A | N66: =VLOOKUP(D66,PAYSHEET!B$5:AH$70,31,0) -> #N/A | O66: =M66+N66 -> #N/A | P66: =VLOOKUP(D66,PAYSHEET!B$5:AC$70,26,0) -> #N/A
C67: =C15+1 -> 12 | D67: 10977 | E67: KHADHAR BASHA | F67: 101823804746 | G67: 5218553222 | H67: =ROUND(N67*100/3.25,0) -> #N/A | I67: =ROUND(J67*100/12,0) -> #N/A | J67: =VLOOKUP(D67,PAYSHEET!B$5:AA$84,24,0) -> #N/A | K67: =I67*13% -> #N/A | L67: =J67+K67 -> #N/A | M67: =ROUND(VLOOKUP(D67,PAYSHEET!B$5:AB$70,25,0),0) -> #N/A | N67: =VLOOKUP(D67,PAYSHEET!B$5:AH$70,31,0) -> #N/A | O67: =M67+N67 -> #N/A | P67: =VLOOKUP(D67,PAYSHEET!B$5:AC$70,26,0) -> #N/A
C68: =C23+1 -> 20 | D68: 10985 | E68: SURYA PRAKASH ROUT | F68: 101611612492 | G68: 5219243373 | H68: =ROUND(N68*100/3.25,0) -> 63138 | I68: =ROUND(J68*100/12,0) -> 0 | J68: =VLOOKUP(D68,PAYSHEET!B$5:AA$84,24,0) -> 0 | K68: =I68*13% -> 0 | L68: =J68+K68 -> 0 | M68: =ROUND(VLOOKUP(D68,PAYSHEET!B$5:AB$70,25,0),0) -> 2226 | N68: =VLOOKUP(D68,PAYSHEET!B$5:AH$70,31,0) -> 2052 | O68: =M68+N68 -> 4278 | P68: =VLOOKUP(D68,PAYSHEET!B$5:AC$70,26,0) -> 174.19355
C69: =C29+1 -> 26 | D69: 11050 | E69: DUNDALWAR RAVI | F69: 102095604570 | G69: 5221153012 | H69: =ROUND(N69*100/3.25,0) -> #N/A | I69: =ROUND(J69*100/12,0) -> #N/A | J69: =VLOOKUP(D69,PAYSHEET!B$5:AA$84,24,0) -> #N/A | K69: =I69*13% -> #N/A | L69: =J69+K69 -> #N/A | M69: =ROUND(VLOOKUP(D69,PAYSHEET!B$5:AB$70,25,0),0) -> #N/A | N69: =VLOOKUP(D69,PAYSHEET!B$5:AH$70,31,0) -> #N/A | O69: =M69+N69 -> #N/A | P69: =VLOOKUP(D69,PAYSHEET!B$5:AC$70,26,0) -> #N/A
C71: =C31+1 -> 28 | D71: 11182 | E71: ZEESHAN KHAN | F71: 101155846091 | G71: 5221451665 | H71: =ROUND(N71*100/3.25,0) -> #N/A | I71: =ROUND(J71*100/12,0) -> #N/A | J71: =VLOOKUP(D71,PAYSHEET!B$5:AA$84,24,0) -> #N/A | K71: =I71*13% -> #N/A | L71: =J71+K71 -> #N/A | M71: =ROUND(VLOOKUP(D71,PAYSHEET!B$5:AB$70,25,0),0) -> #N/A | N71: =VLOOKUP(D71,PAYSHEET!B$5:AH$70,31,0) -> #N/A | O71: =M71+N71 -> #N/A | P71: =VLOOKUP(D71,PAYSHEET!B$5:AC$70,26,0) -> #N/A
C72: =C37+1 -> 34 | D72: 10585 | E72: A.RAMESH | F72: =VLOOKUP(D72,[2]PF!$B$2:$C$499,2,0) -> 101201162069 | G72: NA | H72: =ROUND(N72*100/3.25,0) -> #N/A | I72: =ROUND(J72*100/12,0) -> #N/A | J72: =VLOOKUP(D72,PAYSHEET!B$5:AA$84,24,0) -> #N/A | K72: =I72*13% -> #N/A | L72: =J72+K72 -> #N/A | M72: =ROUND(VLOOKUP(D72,PAYSHEET!B$5:AB$70,25,0),0) -> #N/A | N72: =VLOOKUP(D72,PAYSHEET!B$5:AH$70,31,0) -> #N/A | O72: =M72+N72 -> #N/A | P72: =VLOOKUP(D72,PAYSHEET!B$5:AC$70,26,0) -> #N/A
C73: =C72+1 -> 35 | D73: 11247 | E73: M.KRANTHI | F73: =VLOOKUP(D73,[3]PF!$C$3:$D$485,2,0) -> 101626727030 | G73: =VLOOKUP(D73,[3]ESIC!$B$4:$C$420,2,0) -> 5220204602 | H73: =ROUND(N73*100/3.25,0) -> #N/A | I73: =ROUND(J73*100/12,0) -> #N/A | J73: =VLOOKUP(D73,PAYSHEET!B$5:AA$84,24,0) -> #N/A | K73: =I73*13% -> #N/A | L73: =J73+K73 -> #N/A | M73: =ROUND(VLOOKUP(D73,PAYSHEET!B$5:AB$70,25,0),0) -> #N/A | N73: =VLOOKUP(D73,PAYSHEET!B$5:AH$70,31,0) -> #N/A | O73: =M73+N73 -> #N/A | P73: =VLOOKUP(D73,PAYSHEET!B$5:AC$70,26,0) -> #N/A
C74: =C38+1 -> 35 | D74: 11256 | E74: M.SRI HARI | F74: =VLOOKUP(D74,[3]PF!$C$3:$D$485,2,0) -> 102155632619 | G74: =VLOOKUP(D74,[3]ESIC!$B$4:$C$420,2,0) -> 5221617942 | H74: =ROUND(N74*100/3.25,0) -> #N/A | I74: =ROUND(J74*100/12,0) -> #N/A | J74: =VLOOKUP(D74,PAYSHEET!B$5:AA$84,24,0) -> #N/A | K74: =I74*13% -> #N/A | L74: =J74+K74 -> #N/A | M74: =ROUND(VLOOKUP(D74,PAYSHEET!B$5:AB$70,25,0),0) -> #N/A | N74: =VLOOKUP(D74,PAYSHEET!B$5:AH$70,31,0) -> #N/A | O74: =M74+N74 -> #N/A | P74: =VLOOKUP(D74,PAYSHEET!B$5:AC$70,26,0) -> #N/A
C79: =C30+1 -> 27 | D79: 11116 | E79: RUDRAKANT BEDANT | F79: 102120711813 | G79: 5221323720 | H79: =ROUND(N79*100/3.25,0) -> #N/A | I79: =ROUND(J79*100/12,0) -> #N/A | J79: =VLOOKUP(D79,PAYSHEET!B$5:AA$84,24,0) -> #N/A | K79: =I79*13% -> #N/A | L79: =J79+K79 -> #N/A | M79: =ROUND(VLOOKUP(D79,PAYSHEET!B$5:AB$70,25,0),0) -> #N/A | N79: =VLOOKUP(D79,PAYSHEET!B$5:AH$70,31,0) -> #N/A | O79: =M79+N79 -> #N/A | P79: =VLOOKUP(D79,PAYSHEET!B$5:AC$70,26,0) -> #N/A
C83: =C31+1 -> 28 | D83: 11175 | E83: DANEYAL | F83: 102120060074 | G83: 5221466856 | H83: =ROUND(N83*100/3.25,0) -> #N/A | I83: =ROUND(J83*100/12,0) -> #N/A | J83: =VLOOKUP(D83,PAYSHEET!B$5:AA$84,24,0) -> #N/A | K83: =I83*13% -> #N/A | L83: =J83+K83 -> #N/A | M83: =ROUND(VLOOKUP(D83,PAYSHEET!B$5:AB$70,25,0),0) -> #N/A | N83: =VLOOKUP(D83,PAYSHEET!B$5:AH$70,31,0) -> #N/A | O83: =M83+N83 -> #N/A | P83: =VLOOKUP(D83,PAYSHEET!B$5:AC$70,26,0) -> #N/A
C84: =C30+1 -> 27 | D84: 11110 | E84: AMANULLAH KHAN | F84: 102117145981 | G84: 5221310401 | H84: =ROUND(N84*100/3.25,0) -> #N/A | I84: =ROUND(J84*100/12,0) -> #N/A | J84: =VLOOKUP(D84,PAYSHEET!B$5:AA$84,24,0) -> #N/A | K84: =I84*13% -> #N/A | L84: =J84+K84 -> #N/A | M84: =ROUND(VLOOKUP(D84,PAYSHEET!B$5:AB$70,25,0),0) -> #N/A | N84: =VLOOKUP(D84,PAYSHEET!B$5:AH$70,31,0) -> #N/A | O84: =M84+N84 -> #N/A | P84: =VLOOKUP(D84,PAYSHEET!B$5:AC$70,26,0) -> #N/A
C85: =C27+1 -> 24 | D85: 11024 | E85: MD ANWAR | F85: 102044342511 | G85: 5220829704 | H85: =ROUND(N85*100/3.25,0) -> #N/A | I85: =ROUND(J85*100/12,0) -> #N/A | J85: =VLOOKUP(D85,PAYSHEET!B$5:AA$84,24,0) -> #N/A | K85: =I85*13% -> #N/A | L85: =J85+K85 -> #N/A | M85: =ROUND(VLOOKUP(D85,PAYSHEET!B$5:AB$70,25,0),0) -> #N/A | N85: =VLOOKUP(D85,PAYSHEET!B$5:AH$70,31,0) -> #N/A | O85: =M85+N85 -> #N/A | P85: =VLOOKUP(D85,PAYSHEET!B$5:AC$70,26,0) -> #N/A
C86: =C15+1 -> 12 | D86: 11001 | E86: VAMSHI KRISHNA | F86: 101974710875 | G86: 5219953884 | H86: =ROUND(N86*100/3.25,0) -> #N/A | I86: =ROUND(J86*100/12,0) -> #N/A | J86: =VLOOKUP(D86,PAYSHEET!B$5:AA$70,24,0) -> #N/A | K86: =I86*13% -> #N/A | L86: =J86+K86 -> #N/A | M86: =ROUND(VLOOKUP(D86,PAYSHEET!B$5:AB$70,25,0),0) -> #N/A | N86: =VLOOKUP(D86,PAYSHEET!B$5:AH$70,31,0) -> #N/A | O86: =M86+N86 -> #N/A | P86: =VLOOKUP(D86,PAYSHEET!B$5:AC$70,26,0) -> #N/A
C87: =C10+1 -> 7 | D87: 10994 | E87: G.SURESH KUMAR | F87: 101300040028 | G87: NA | H87: =ROUND(N87*100/3.25,0) -> #N/A | I87: =ROUND(J87*100/12,0) -> #N/A | J87: =VLOOKUP(D87,PAYSHEET!B$5:AA$70,24,0) -> #N/A | K87: =I87*13% -> #N/A | L87: =J87+K87 -> #N/A | M87: =ROUND(VLOOKUP(D87,PAYSHEET!B$5:AB$70,25,0),0) -> #N/A | N87: =VLOOKUP(D87,PAYSHEET!B$5:AH$70,31,0) -> #N/A | O87: =M87+N87 -> #N/A | P87: =VLOOKUP(D87,PAYSHEET!B$5:AC$70,26,0) -> #N/A
C88: =C24+1 -> 21 | D88: 10492 | E88: SIRAJ | F88: 101925800595 | G88: 5220323113 | H88: =ROUND(N88*100/3.25,0) -> #N/A | I88: =ROUND(J88*100/12,0) -> #N/A | J88: =VLOOKUP(D88,PAYSHEET!B$5:AA$70,24,0) -> #N/A | K88: =I88*13% -> #N/A | L88: =J88+K88 -> #N/A | M88: =ROUND(VLOOKUP(D88,PAYSHEET!B$5:AB$70,25,0),0) -> #N/A | N88: =VLOOKUP(D88,PAYSHEET!B$5:AH$70,31,0) -> #N/A | O88: =M88+N88 -> #N/A | P88: =VLOOKUP(D88,PAYSHEET!B$5:AC$70,26,0) -> #N/A

Sheet Sheet1
D4: MIDAS B1&B2 BANK STATEMENT FOR THE MONTH OF APR-2025
D6: SL. NO | E6: EMP NO. | F6: Name of the Employee | G6: Account No | H6: IFSC Code | I6: Amount
D7: 1 | E7: 11029 | F7: SUDHIR KUMAR RAUTARAY | G7: 5599174559 | H7: UTIB0005151 | I7: =VLOOKUP(E7,PAYSHEET!B$5:AF$84,29,0) -> 0
D8: =D7+1 -> 2 | E8: 10984 | F8: K RAJYALAKSHMI | G8: 309025560518 | H8: RATN0000366 | I8: =VLOOKUP(E8,PAYSHEET!B$5:AF$84,29,0) -> 0
D9: =D8+1 -> 3 | E9: 10976 | F9: KONGANI NARAYANA | G9: 20059012168 | H9: SBIN0011667 | I9: =VLOOKUP(E9,PAYSHEET!B$5:AF$84,29,0) -> 0
D10: =D9+1 -> 4 | E10: 10986 | F10: KHIROD DAS | G10: 35192372300 | H10: SBIN0016125 | I10: =VLOOKUP(E10,PAYSHEET!B$5:AF$84,29,0) -> 0
D11: =D10+1 -> 5 | E11: 10989 | F11: NAGENDRA | G11: 309025560864 | H11: RATN0000366 | I11: =VLOOKUP(E11,PAYSHEET!B$5:AF$84,29,0) -> 0
D12: =D11+1 -> 6 | E12: 10988 | F12: KAKARLA BASHA | G12: 32461731290 | H12: SBIN0005082 | I12: =VLOOKUP(E12,PAYSHEET!B$5:AF$84,29,0) -> #N/A
D13: =D12+1 -> 7 | E13: 10982 | F13: SAGAR KUMAR BEHERA | G13: 424501504162 | I13: =VLOOKUP(E13,PAYSHEET!B$5:AF$84,29,0) -> 0
D14: =D13+1 -> 8 | E14: 11022 | F14: P SADDAM | G14: 30861617747 | H14: SBIN0005082 | I14: =VLOOKUP(E14,PAYSHEET!B$5:AF$84,29,0) -> #N/A
D15: =D14+1 -> 9 | E15: 10990 | F15: MUKESH SRICHANDAN | G15: 35573873665 | H15: SBIN0007343 | I15: =VLOOKUP(E15,PAYSHEET!B$5:AF$84,29,0) -> 0
D16: =D15+1 -> 10 | E16: 10981 | F16: C. GANESH | G16: 40082463078 | H16: SBIN0000834 | I16: =VLOOKUP(E16,PAYSHEET!B$5:AF$84,29,0) -> 0
D17: =D16+1 -> 11 | E17: 11000 | F17: ALLAUDDIN MAINODDIN KHAJURE | G17: 39377880179 | H17: SBIN0013032 | I17: =VLOOKUP(E17,PAYSHEET!B$5:AF$84,29,0) -> 0
D18: =D17+1 -> 12 | E18: 11026 | F18: JAGADEESH | G18: 309025560837 | H18: RATN0000366 | I18: =VLOOKUP(E18,PAYSHEET!B$5:AF$84,29,0) -> #N/A
D19: =D18+1 -> 13 | E19: 10991 | F19: JOGENDRA SETHI | G19: 20077099524 | H19: SBIN0014183 | I19: =VLOOKUP(E19,PAYSHEET!B$5:AF$84,29,0) -> 0
D20: =D19+1 -> 14 | E20: 10999 | F20: VISHAL | G20: 62342323181 | H20: SBIN0021357 | I20: =VLOOKUP(E20,PAYSHEET!B$5:AF$84,29,0) -> #N/A
D21: =D20+1 -> 15 | E21: 10980 | F21: ANURUDHA SAMAL | G21: 23930100011966 | H21: BARB0HATINA | I21: =VLOOKUP(E21,PAYSHEET!B$5:AF$84,29,0) -> 0
D22: =D21+1 -> 16 | E22: 10978 | F22: PABITRA MALIK | G22: 36718981606 | H22: SBIN0002100 | I22: =VLOOKUP(E22,PAYSHEET!B$5:AF$84,29,0) -> 0
D23: =D22+1 -> 17 | E23: 10974 | F23: GADADHAR MALIK | G23: 35352487786 | H23: SBIN0002100 | I23: =VLOOKUP(E23,PAYSHEET!B$5:AF$84,29,0) -> 0
D24: =D23+1 -> 18 | E24: 10983 | F24: SUDHAKAR | G24: 38524408774 | H24: SBIN0015853 | I24: =VLOOKUP(E24,PAYSHEET!B$5:AF$84,29,0) -> 0
D25: =D24+1 -> 19 | E25: 10993 | F25: VENKATES M | G25: 44511228093 | H25: SCBL0036081 | I25: =VLOOKUP(E25,PAYSHEET!B$5:AF$84,29,0) -> #N/A
D26: =D25+1 -> 20 | E26: 10997 | F26: KASIM VALI | G26: 40963915540 | H26: SBIN0000788 | I26: =VLOOKUP(E26,PAYSHEET!B$5:AF$84,29,0) -> #N/A
D27: =D26+1 -> 21 | E27: 11058 | F27: P MOKHA LINGAM | G27: 0046168368 | H27: KKBK0007466 | I27: =VLOOKUP(E27,PAYSHEET!B$5:AF$84,29,0) -> #N/A
D28: =D27+1 -> 22 | E28: 11049 | F28: DUNDALWAR RAVI | G28: 38644051779 | H28: SBIN0020115 | I28: =VLOOKUP(E28,PAYSHEET!B$5:AF$84,29,0) -> #N/A
D29: =D28+1 -> 23 | E29: 11032 | F29: ANANDA SHA | G29: 50100460685195 | H29: HDFC0000512 | I29: =VLOOKUP(E29,PAYSHEET!B$5:AF$84,29,0) -> 0
D30: =D29+1 -> 24 | E30: 11193 | F30: T.ARCHANA | G30: 79069844609 | H30: TGRB0000077 | I30: =VLOOKUP(E30,PAYSHEET!B$5:AF$84,29,0) -> #N/A
D31: =D30+1 -> 25 | E31: 11158 | F31: NARESH DAS | G31: 918010019983214 | H31: UTIB0000679 | I31: =VLOOKUP(E31,PAYSHEET!B$5:AF$84,29,0) -> 0
D32: =D31+1 -> 26 | E32: 11215 | F32: K.RAMESH | G32: 32769838666 | H32: SBIN0008501 | I32: =VLOOKUP(E32,PAYSHEET!B$5:AF$84,29,0) -> #N/A
D33: =D32+1 -> 27 | E33: 10339 | F33: V.SRIKANTH | G33: 923010058683522 | H33: UTIB0000008 | I33: =VLOOKUP(E33,PAYSHEET!B$5:AF$84,29,0) -> #N/A
D34: =D33+1 -> 28 | E34: 11217 | F34: K.TARUN | G34: 574118210002406 | H34: BKID0005741 | I34: =VLOOKUP(E34,PAYSHEET!B$5:AF$84,29,0) -> #N/A
D35: =D34+1 -> 29 | E35: 11203 | F35: BISWAJIT SAHOO | G35: 309027166857 | H35: RATN0000376 | I35: =VLOOKUP(E35,PAYSHEET!B$5:AF$84,29,0) -> 0
D36: =D35+1 -> 30 | E36: 11214 | F36: M.LAXMINARAYANA | G36: 309027166723 | H36: RATN0000376 | I36: =VLOOKUP(E36,PAYSHEET!B$5:AF$84,29,0) -> 0
D37: =D36+1 -> 31 | E37: 11246 | F37: R.HEMANTH | G37: 309027771525 | H37: RATN0000208 | I37: =VLOOKUP(E37,PAYSHEET!B$5:AF$84,29,0) -> #N/A
D38: =D37+1 -> 32 | E38: 11273 | F38: CHANDRA SHAKHER | G38: 50100558344180 | H38: HDFC0001627 | I38: =VLOOKUP(E38,PAYSHEET!B$5:AF$84,29,0) -> 0
... D40: =D39+1 -> 34 | E40: 11311 | F40: MOTUPALLI RAVI SANKARA DURGA | G40: 62357020768 | H40: SBIN0020411 | I40: =VLOOKUP(E40,PAYSHEET!B$5:AF$84,29,0) -> 0
D41: =D40+1 -> 35 | E41: 10998 | F41: K.MABU SHAREEF | G41: 33602013886 | H41: SBIN0015374 | I41: =VLOOKUP(E41,PAYSHEET!B$5:AF$84,29,0) -> #N/A
D42: =D41+1 -> 36 | E42: 10312 | F42: T.BALAJI | G42: 50100510147955 | H42: HDFC0009401 | I42: =VLOOKUP(E42,PAYSHEET!B$5:AF$84,29,0) -> #N/A
D43: =D42+1 -> 37 | E43: 11337 | F43: A.JITHENDER KUMAR | G43: 16880100061107 | H43: FDRL0001688 | I43: =VLOOKUP(E43,PAYSHEET!B$5:AF$84,29,0) -> #N/A
D44: =D43+1 -> 38 | E44: 11341 | F44: P.SRINIVAS | G44: 40557733650 | H44: SBIN0017569 | I44: =VLOOKUP(E44,PAYSHEET!B$5:AF$84,29,0) -> #N/A
D45: =D44+1 -> 39 | E45: 11389 | F45: ARIF | G45: 6572412476 | H45: IDIB000I021 | I45: =VLOOKUP(E45,PAYSHEET!B$5:AF$84,29,0) -> #N/A
D46: =D45+1 -> 40 | E46: 10979 | F46: B.APPANA | G46: 35216855329 | H46: SBIN0011104 | I46: =VLOOKUP(E46,PAYSHEET!B$5:AF$84,29,0) -> #N/A
D47: =D46+1 -> 41 | E47: 11313 | F47: VASA SHIVA KUMARM | G47: 35336678577 | H47: SBIN0009501 | I47: =VLOOKUP(E47,PAYSHEET!B$5:AF$84,29,0) -> #N/A
D48: =D47+1 -> 42 | E48: 1 | F48: MOHMMED AMIR | G48: 7921773338 | H48: IDIB000B050 | I48: =VLOOKUP(E48,PAYSHEET!B$5:AF$84,29,0) -> 0
C49: L&T | D49: =D48+1 -> 43 | E49: 2 | F49: G.SHANMUKHA RAO | G49: 36090598041 | H49: SBIN0011104 | I49: =VLOOKUP(E49,PAYSHEET!B$5:AF$84,29,0) -> 0
D50: =D49+1 -> 44 | E50: 10492 | F50: SIRAJ | G50: 41123009226 | H50: SBIN0004904 | I50: =VLOOKUP(E50,PAYSHEET!B$5:AF$84,29,0) -> #N/A
D51: =D50+1 -> 45 | E51: 11028 | F51: RAMASWAMY | G51: 309025560855 | H51: RATN0000366 | I51: =VLOOKUP(E51,PAYSHEET!B$5:AF$84,29,0) -> #N/A
D52: =D51+1 -> 46 | E52: 11241 | F52: SHAHBDDIN | G52: 2824000100201314 | H52: PUNB0004720 | I52: =VLOOKUP(E52,PAYSHEET!B$5:AF$84,29,0) -> #N/A
I53: =SUM(I7:I52) -> #N/A | L53: =I53 -> #N/A
L54: =PAYSHEET!AF71 -> 953579
L55: =L53-L54 -> #N/A
D57: Prepared By | F57: Verified By | G57: Authorized By | I57: Approved By
D65: MIDAS B1&B2 HOLD BANK STATEMENT FOR THE MONTH OF APR-2025
D66: SL. NO | E66: EMP NO. | F66: Name of the Employee | G66: Account No | H66: IFSC Code | I66: Amount
I73: =SUM(I47:I52) -> #N/A
D77: Prepared By | F77: Verified By | G77: Authorized By | I77: Approved By

Sheet INVOICE BREAKUP
C4: MIDAS B1 INVOICE FOR THE MONTH OF APR-2025 | H4: AS PER ATTENDANCE | K4: ACTUALS
C5: S.NO | D5: DESIGNATION | E5: NO OF PERSONS | F5: RATE PER MONTH | G5: TOTAL RATE PER MONTH | H5: NO OF PERSONS | I5: NO OF DUTIES | J5: RATE PER MONTH | K5: BANK REMITTANCE | L5: PF 12% | M5: PF 13% | N5: ESI 0.75% | O5: ESI 3.25% | P5: ADVANCES | Q5: PT | R5: TOTAL
C6: 1 | D6: Technical Executive | E6: 1 | F6: 39780 | G6: =F6*E6 -> 39780 | H6: 1 | I6: =+VLOOKUP(D6,PAYSHEET!C4:F71,4,0)+VLOOKUP(D6,PAYSHEET!C4:G71,5,0) -> 31 | J6: =+VLOOKUP(D6,PAYSHEET!$C$4:$AI$71,33,0) -> 40950.144 | K6: =+VLOOKUP(D6,PAYSHEET!C4:AF71,30,0) -> 36000 | L6: =+VLOOKUP(D6,PAYSHEET!C4:AA71,25,0) -> 1800 | M6: =+VLOOKUP(D6,PAYSHEET!$C$4:$AG$70,31,0) -> 1950 | N6: =+VLOOKUP(D6,PAYSHEET!C4:AB70,26,0) -> 0 | O6: =+VLOOKUP(D6,PAYSHEET!C4:AH70,32,0) -> 1000 | P6: =+VLOOKUP(D6,PAYSHEET!C4:AD70,28,0) -> 0 | Q6: =+VLOOKUP(D6,PAYSHEET!C4:AC70,27,0) -> 200 | R6: =J6 -> 40950.144
C7: =C6+1 -> 2 | D7: Technical Supervisor | E7: 9 | F7: 31244 | G7: =F7*E7 -> 281196 | H7: 10 | I7: =+VLOOKUP(D7,PAYSHEET!C5:F72,4,0)+VLOOKUP(D7,PAYSHEET!C5:G72,5,0) -> 230 | J7: =+VLOOKUP(D7,PAYSHEET!$C$4:$AI$71,33,0) -> 233128.09 | K7: =+VLOOKUP(D7,PAYSHEET!C5:AF72,30,0) -> 195757 | L7: =+VLOOKUP(D7,PAYSHEET!C5:AA72,25,0) -> 13354.839 | M7: =+VLOOKUP(D7,PAYSHEET!$C$4:$AG$70,31,0) -> 14467.742 | N7: =+VLOOKUP(D7,PAYSHEET!C5:AB71,26,0) -> 0 | O7: =+VLOOKUP(D7,PAYSHEET!C5:AH71,32,0) -> 8000 | P7: =+VLOOKUP(D7,PAYSHEET!C5:AD71,28,0) -> 0 | Q7: =+VLOOKUP(D7,PAYSHEET!C5:AC71,27,0) -> 1550 | R7: =J7 -> 233128.09
C8: =C7+1 -> 3 | D8: Electrician | E8: 10 | F8: 26607 | G8: =F8*E8 -> 266070 | H8: 8 | I8: =+VLOOKUP(D8,PAYSHEET!C6:F73,4,0)+VLOOKUP(D8,PAYSHEET!C6:G73,5,0) -> 270 | J8: =+VLOOKUP(D8,PAYSHEET!$C$4:$AI$71,33,0) -> 220516.79 | K8: =+VLOOKUP(D8,PAYSHEET!C6:AF73,30,0) -> 176283 | L8: =+VLOOKUP(D8,PAYSHEET!C6:AA73,25,0) -> 15677.419 | M8: =+VLOOKUP(D8,PAYSHEET!$C$4:$AG$70,31,0) -> 16983.871 | N8: =+VLOOKUP(D8,PAYSHEET!C6:AB72,26,0) -> 772.95751 | O8: =+VLOOKUP(D8,PAYSHEET!C6:AH72,32,0) -> 9349.4825 | P8: =+VLOOKUP(D8,PAYSHEET!C6:AD72,28,0) -> 0 | Q8: =+VLOOKUP(D8,PAYSHEET!C6:AC72,27,0) -> 1450 | R8: =J8 -> 220516.79
C9: =C8+1 -> 4 | D9: HVAC Technician | E9: 9 | F9: 26552 | G9: =F9*E9 -> 238968 | H9: 7 | I9: =+VLOOKUP(D9,PAYSHEET!C7:F74,4,0)+VLOOKUP(D9,PAYSHEET!C7:G74,5,0) -> 230 | J9: =+VLOOKUP(D9,PAYSHEET!$C$4:$AI$71,33,0) -> 193454.77 | K9: =+VLOOKUP(D9,PAYSHEET!C7:AF74,30,0) -> 155790 | L9: =+VLOOKUP(D9,PAYSHEET!C7:AA74,25,0) -> 13354.839 | M9: =+VLOOKUP(D9,PAYSHEET!$C$4:$AG$70,31,0) -> 14467.742 | N9: =+VLOOKUP(D9,PAYSHEET!C7:AB73,26,0) -> 261.06512 | O9: =+VLOOKUP(D9,PAYSHEET!C7:AH73,32,0) -> 8131.2822 | P9: =+VLOOKUP(D9,PAYSHEET!C7:AD73,28,0) -> 0 | Q9: =+VLOOKUP(D9,PAYSHEET!C7:AC73,27,0) -> 1450 | R9: =J9 -> 193454.77 | S9: Excess
C10: =C9+1 -> 5 | D10: BMS Technician | E10: 4 | F10: 26472 | G10: =F10*E10 -> 105888 | H10: 4 | I10: =+VLOOKUP(D10,PAYSHEET!C8:F75,4,0)+VLOOKUP(D10,PAYSHEET!C8:G75,5,0) -> 92 | J10: =+VLOOKUP(D10,PAYSHEET!$C$4:$AI$71,33,0) -> 77822.307 | K10: =+VLOOKUP(D10,PAYSHEET!C8:AF75,30,0) -> 62143 | L10: =+VLOOKUP(D10,PAYSHEET!C8:AA75,25,0) -> 5341.9355 | M10: =+VLOOKUP(D10,PAYSHEET!$C$4:$AG$70,31,0) -> 5787.0968 | N10: =+VLOOKUP(D10,PAYSHEET!C8:AB74,26,0) -> 0 | O10: =+VLOOKUP(D10,PAYSHEET!C8:AH74,32,0) -> 4000 | P10: =+VLOOKUP(D10,PAYSHEET!C8:AD74,28,0) -> 0 | Q10: =+VLOOKUP(D10,PAYSHEET!C8:AC74,27,0) -> 550 | R10: =J10 -> 77822.307
C11: =C10+1 -> 6 | D11: DG Operator | E11: 4 | F11: 26472 | G11: =F11*E11 -> 105888 | H11: 4 | I11: =+VLOOKUP(D11,PAYSHEET!C9:F76,4,0)+VLOOKUP(D11,PAYSHEET!C9:G76,5,0) -> 124 | J11: =+VLOOKUP(D11,PAYSHEET!$C$4:$AI$71,33,0) -> 106960.46 | K11: =+VLOOKUP(D11,PAYSHEET!C9:AF76,30,0) -> 87160 | L11: =+VLOOKUP(D11,PAYSHEET!C9:AA76,25,0) -> 7200 | M11: =+VLOOKUP(D11,PAYSHEET!$C$4:$AG$70,31,0) -> 7800 | N11: =+VLOOKUP(D11,PAYSHEET!C9:AB75,26,0) -> 0 | O11: =+VLOOKUP(D11,PAYSHEET!C9:AH75,32,0) -> 4000 | P11: =+VLOOKUP(D11,PAYSHEET!C9:AD75,28,0) -> 0 | Q11: =+VLOOKUP(D11,PAYSHEET!C9:AC75,27,0) -> 800 | R11: =J11 -> 106960.46
C12: =C11+1 -> 7 | D12: Plumber | E12: 9 | F12: 26959 | G12: =F12*E12 -> 242631 | H12: 8 | I12: =+VLOOKUP(D12,PAYSHEET!C10:F77,4,0)+VLOOKUP(D12,PAYSHEET!C10:G77,5,0) -> 188 | J12: =+VLOOKUP(D12,PAYSHEET!$C$4:$AI$71,33,0) -> 167309.22 | K12: =+VLOOKUP(D12,PAYSHEET!C10:AF77,30,0) -> 133618 | L12: =+VLOOKUP(D12,PAYSHEET!C10:AA77,25,0) -> 10916.129 | M12: =+VLOOKUP(D12,PAYSHEET!$C$4:$AG$70,31,0) -> 11825.806 | N12: =+VLOOKUP(D12,PAYSHEET!C10:AB76,26,0) -> 0 | O12: =+VLOOKUP(D12,PAYSHEET!C10:AH76,32,0) -> 10000 | P12: =+VLOOKUP(D12,PAYSHEET!C10:AD76,28,0) -> 0 | Q12: =+VLOOKUP(D12,PAYSHEET!C10:AC76,27,0) -> 950 | R12: =J12 -> 167309.22 | S12: Excess
C13: =C12+1 -> 8 | D13: Carpenter | E13: 1 | F13: 26959 | G13: =F13*E13 -> 26959 | H13: 1 | I13: =+VLOOKUP(D13,PAYSHEET!C14:F78,4,0)+VLOOKUP(D13,PAYSHEET!C14:G78,5,0) -> 26 | J13: =+VLOOKUP(D13,PAYSHEET!$C$4:$AI$71,33,0) -> 23603.071 | K13: =+VLOOKUP(D13,PAYSHEET!C14:AF78,30,0) -> 19258 | L13: =+VLOOKUP(D13,PAYSHEET!C14:AA78,25,0) -> 1509.6774 | M13: =+VLOOKUP(D13,PAYSHEET!$C$4:$AG$70,31,0) -> 1635.4839 | N13: =+VLOOKUP(D13,PAYSHEET!C14:AB77,26,0) -> 0 | O13: =+VLOOKUP(D13,PAYSHEET!C14:AH77,32,0) -> 1000 | P13: =+VLOOKUP(D13,PAYSHEET!C14:AD77,28,0) -> 0 | Q13: =+VLOOKUP(D13,PAYSHEET!C14:AC77,27,0) -> 200 | R13: =J13 -> 23603.071 | S13: Excess
C14: =C13+1 -> 9 | D14: Painter | E14: 1 | F14: 27140 | G14: =F14*E14 -> 27140 | H14: 1 | I14: =+VLOOKUP(D14,PAYSHEET!C15:F79,4,0)+VLOOKUP(D14,PAYSHEET!C15:G79,5,0) -> 31 | J14: =+VLOOKUP(D14,PAYSHEET!$C$4:$AI$71,33,0) -> 27139.896 | K14: =+VLOOKUP(D14,PAYSHEET!C15:AF79,30,0) -> 22190 | L14: =+VLOOKUP(D14,PAYSHEET!C15:AA79,25,0) -> 1800 | M14: =+VLOOKUP(D14,PAYSHEET!$C$4:$AG$70,31,0) -> 1950 | N14: =+VLOOKUP(D14,PAYSHEET!C15:AB78,26,0) -> 0 | O14: =+VLOOKUP(D14,PAYSHEET!C15:AH78,32,0) -> 1000 | P14: =+VLOOKUP(D14,PAYSHEET!C15:AD78,28,0) -> 0 | Q14: =+VLOOKUP(D14,PAYSHEET!C15:AC78,27,0) -> 200 | R14: =J14 -> 27139.896
C15: =C14+1 -> 10 | D15: Mason | E15: 1 | F15: 27140 | G15: =F15*E15 -> 27140 | H15: 1 | I15: =+VLOOKUP(D15,PAYSHEET!C16:F80,4,0)+VLOOKUP(D15,PAYSHEET!C16:G80,5,0) -> 31 | J15: =+VLOOKUP(D15,PAYSHEET!$C$4:$AI$71,33,0) -> 27139.896 | K15: =+VLOOKUP(D15,PAYSHEET!C16:AF80,30,0) -> 22190 | L15: =+VLOOKUP(D15,PAYSHEET!C16:AA80,25,0) -> 1800 | M15: =+VLOOKUP(D15,PAYSHEET!$C$4:$AG$70,31,0) -> 1950 | N15: =+VLOOKUP(D15,PAYSHEET!C16:AB79,26,0) -> 0 | O15: =+VLOOKUP(D15,PAYSHEET!C16:AH79,32,0) -> 1000 | P15: =+VLOOKUP(D15,PAYSHEET!C16:AD79,28,0) -> 0 | Q15: =+VLOOKUP(D15,PAYSHEET!C16:AC79,27,0) -> 200 | R15: =J15 -> 27139.896
C16: =C15+1 -> 11 | D16: Welder | E16: 1 | F16: 27140 | G16: =F16*E16 -> 27140 | H16: 1 | I16: =+VLOOKUP(D16,PAYSHEET!C16:F81,4,0)+VLOOKUP(D16,PAYSHEET!C16:G81,5,0) -> 31 | J16: =+VLOOKUP(D16,PAYSHEET!$C$4:$AI$71,33,0) -> 25950.015 | K16: =+VLOOKUP(D16,PAYSHEET!C16:AF81,30,0) -> 21000 | L16: =+VLOOKUP(D16,PAYSHEET!C16:AA81,25,0) -> 1800 | M16: =+VLOOKUP(D16,PAYSHEET!$C$4:$AG$70,31,0) -> 1950 | N16: =+VLOOKUP(D16,PAYSHEET!C16:AB80,26,0) -> 0 | O16: =+VLOOKUP(D16,PAYSHEET!C16:AH80,32,0) -> 1000 | P16: =+VLOOKUP(D16,PAYSHEET!C16:AD80,28,0) -> 0 | Q16: =+VLOOKUP(D16,PAYSHEET!C16:AC80,27,0) -> 200 | R16: =J16 -> 25950.015
C17: =C16+1 -> 12 | D17: Fire Technician | E17: 1 | F17: 27140 | G17: =F17*E17 -> 27140 | H17: 1 | I17: =+VLOOKUP(D17,PAYSHEET!C16:F82,4,0)+VLOOKUP(D17,PAYSHEET!C16:G82,5,0) -> 31 | J17: =+VLOOKUP(D17,PAYSHEET!$C$4:$AI$71,33,0) -> 27139.896 | K17: =+VLOOKUP(D17,PAYSHEET!C16:AF82,30,0) -> 22190 | L17: =+VLOOKUP(D17,PAYSHEET!C16:AA82,25,0) -> 1800 | M17: =+VLOOKUP(D17,PAYSHEET!$C$4:$AG$70,31,0) -> 1950 | N17: =+VLOOKUP(D17,PAYSHEET!C16:AB81,26,0) -> 0 | O17: =+VLOOKUP(D17,PAYSHEET!C16:AH81,32,0) -> 1000 | P17: =+VLOOKUP(D17,PAYSHEET!C16:AD81,28,0) -> 0 | Q17: =+VLOOKUP(D17,PAYSHEET!C16:AC81,27,0) -> 200 | R17: =J17 -> 27139.896
E18: =SUM(E6:E17) -> 51 | G18: =SUM(G6:G17) -> 1415940 | H18: =SUM(H6:H17) -> 47 | I18: =SUM(I6:I17) -> 1315 | J18: =SUM(J6:J17) -> 1171114.6 | K18: =SUM(K6:K17) -> 953579 | L18: =SUM(L6:L17) -> 76354.839 | M18: =SUM(M6:M17) -> 82717.742 | N18: =SUM(N6:N17) -> 1034.0226 | ... R18: =SUM(R6:R17) -> 1171114.6 | S18: =R18-PAYSHEET!AI71 -> 0
M19: MANAGEMENT FEE @ 8% | R19: =R18*8% -> 93689.164
M20: TOTAL COST AS PER WORK ORDER | R20: =R18+R19 -> 1264803.7
M21: Uniform Charges Per Month | R21: =INVOICE!D34 -> 14465
